{
"meta":{"test_sets":[],"test_metrics":[],"learn_metrics":[{"best_value":"Min","name":"Logloss"}],"launch_mode":"Train","parameters":"","iteration_count":1000,"learn_sets":["learn"],"name":"experiment"},
"iterations":[
{"learn":[0.6820877896],"iteration":0,"passed_time":0.1928609262,"remaining_time":192.6680653},
{"learn":[0.6703033856],"iteration":1,"passed_time":0.2145689634,"remaining_time":107.0699127,,
{"learn":[0.6595528823],"iteration":2,"passed_time":0.2370822985,"remaining_time":78.79035054},
{"learn":[0.6498004122],"iteration":3,"passed_time":0.2480626251,"remaining_time":61.76759365,,
{"learn":[0.6399104448],"iteration":4,"passed_time":0.2671058111,"remaining_time":53.1540564},
{"learn":[0.6317460042],"iteration":5,"passed_time":0.2739736695,"remaining_time":45.38830458},
{"learn":[0.622736137],"iteration":6,"passed_time":0.2794130306,"remaining_time":39.6367342},
{"learn":[0.6150678708],"iteration":7,"passed_time":0.2848928715,"remaining_time":35.32671606},
{"learn":[0.6066390395],"iteration":8,"passed_time":0.291850478,"remaining_time":32.13598041},
{"learn":[0.5984794237],"iteration":9,"passed_time":0.3017172538,"remaining_time":29.87000813},
{"learn":[0.5920422451],"iteration":10,"passed_time":0.3123417944,"remaining_time":28.08236678},
{"learn":[0.5856533186],"iteration":11,"passed_time":0.337693572,"remaining_time":27.80343743},
{"learn":[0.5785187569],"iteration":12,"passed_time":0.3455616209,"remaining_time":26.23610152},
{"learn":[0.5727639467],"iteration":13,"passed_time":0.3561785242,"remaining_time":25.08514464},
{"learn":[0.566787877],"iteration":14,"passed_time":0.3638834529,"remaining_time":23.89501341},
{"learn":[0.5606449243],"iteration":15,"passed_time":0.3690805681,"remaining_time":22.69845494},
{"learn":[0.5551859321],"iteration":16,"passed_time":0.3766083848,"remaining_time":21.77682602},
{"learn":[0.5498785065],"iteration":17,"passed_time":0.3838935286,"remaining_time":20.94352473},
{"learn":[0.5452022066],"iteration":18,"passed_time":0.3922867779,"remaining_time":20.25438574},
{"learn":[0.5404794989],"iteration":19,"passed_time":0.3977962938,"remaining_time":19.4920184},
{"learn":[0.5360781814],"iteration":20,"passed_time":0.4029740268,"remaining_time":18.78626534},
{"learn":[0.532040924],"iteration":21,"passed_time":0.4145651337,"remaining_time":18.42930458},
{"learn":[0.5275685373],"iteration":22,"passed_time":0.4246772716,"remaining_time":18.03955193},
{"learn":[0.5225403445],"iteration":23,"passed_time":0.4292155207,"remaining_time":17.45476451},
{"learn":[0.5181755131],"iteration":24,"passed_time":0.4438559166,"remaining_time":17.31038075},
{"learn":[0.5142165738],"iteration":25,"passed_time":0.4519241176,"remaining_time":16.92977271},
{"learn":[0.5101912302],"iteration":26,"passed_time":0.4641519717,"remaining_time":16.7266618},
{"learn":[0.5066311845],"iteration":27,"passed_time":0.4702351953,"remaining_time":16.32387892},
{"learn":[0.5027384109],"iteration":28,"passed_time":0.4771402763,"remaining_time":15.9759727},
{"learn":[0.4998514774],"iteration":29,"passed_time":0.4858029212,"remaining_time":15.70762779},
{"learn":[0.4963990688],"iteration":30,"passed_time":0.4929500964,"remaining_time":15.40866592},
{"learn":[0.4933481859],"iteration":31,"passed_time":0.5034257983,"remaining_time":15.2286304},
{"learn":[0.4901829842],"iteration":32,"passed_time":0.5135321736,"remaining_time":15.04804885},
{"learn":[0.4871021832],"iteration":33,"passed_time":0.5192900387,"remaining_time":14.75394639},
{"learn":[0.4847265286],"iteration":34,"passed_time":0.5260006493,"remaining_time":14.50258933},
{"learn":[0.4821316791],"iteration":35,"passed_time":0.5363181212,"remaining_time":14.36140747},
{"learn":[0.4796735939],"iteration":36,"passed_time":0.5410317485,"remaining_time":14.08144794},
{"learn":[0.4770154505],"iteration":37,"passed_time":0.5507309036,"remaining_time":13.94218761},
{"learn":[0.4748994365],"iteration":38,"passed_time":0.5586689973,"remaining_time":13.76617709},
{"learn":[0.4730041998],"iteration":39,"passed_time":0.5657464152,"remaining_time":13.57791396},
{"learn":[0.4707868419],"iteration":40,"passed_time":0.5708048542,"remaining_time":13.35126476},
{"learn":[0.4686946624],"iteration":41,"passed_time":0.5769640264,"remaining_time":13.1602747},
{"learn":[0.466336917],"iteration":42,"passed_time":0.583329431,"remaining_time":12.98247129},
{"learn":[0.464105238],"iteration":43,"passed_time":0.5893403247,"remaining_time":12.80475796},
{"learn":[0.4621846233],"iteration":44,"passed_time":0.6006223483,"remaining_time":12.74654095},
{"learn":[0.4605108895],"iteration":45,"passed_time":0.6053163123,"remaining_time":12.55373396},
{"learn":[0.4587453628],"iteration":46,"passed_time":0.6135100805,"remaining_time":12.43989589},
{"learn":[0.4573537467],"iteration":47,"passed_time":0.6246473545,"remaining_time":12.3888392},
{"learn":[0.4556230502],"iteration":48,"passed_time":0.6335736819,"remaining_time":12.29650146},
{"learn":[0.454020777],"iteration":49,"passed_time":0.639678073,"remaining_time":12.15388339},
{"learn":[0.4525258187],"iteration":50,"passed_time":0.647080673,"remaining_time":12.04077566},
{"learn":[0.4513042946],"iteration":51,"passed_time":0.6537294868,"remaining_time":11.91799141},
{"learn":[0.449775934],"iteration":52,"passed_time":0.6695249956,"remaining_time":11.96302209},
{"learn":[0.4484766441],"iteration":53,"passed_time":0.6735887263,"remaining_time":11.80027657},
{"learn":[0.4472090949],"iteration":54,"passed_time":0.6804450392,"remaining_time":11.69128295},
{"learn":[0.4455767789],"iteration":55,"passed_time":0.6871894643,"remaining_time":11.58405097},
{"learn":[0.4438624689],"iteration":56,"passed_time":0.6941083555,"remaining_time":11.48323121},
{"learn":[0.4425087645],"iteration":57,"passed_time":0.7040089759,"remaining_time":11.43407681},
{"learn":[0.4412828273],"iteration":58,"passed_time":0.7099195785,"remaining_time":11.32261565},
{"learn":[0.4399542978],"iteration":59,"passed_time":0.7136407924,"remaining_time":11.18037241},
{"learn":[0.4388663074],"iteration":60,"passed_time":0.7187055955,"remaining_time":11.06335335},
{"learn":[0.4374822349],"iteration":61,"passed_time":0.7241361978,"remaining_time":10.9554799},
{"learn":[0.4364939599],"iteration":62,"passed_time":0.7294500511,"remaining_time":10.84912219},
{"learn":[0.435528444],"iteration":63,"passed_time":0.7336274936,"remaining_time":10.72930209},
{"learn":[0.4346612046],"iteration":64,"passed_time":0.7394522863,"remaining_time":10.63673673},
{"learn":[0.4335343584],"iteration":65,"passed_time":0.7444056937,"remaining_time":10.53446845},
{"learn":[0.4327091621],"iteration":66,"passed_time":0.7481384532,"remaining_time":10.41810712},
{"learn":[0.4318516288],"iteration":67,"passed_time":0.7528181455,"remaining_time":10.31803694},
{"learn":[0.4311421655],"iteration":68,"passed_time":0.7563318308,"remaining_time":10.20499905},
{"learn":[0.4302630725],"iteration":69,"passed_time":0.7609234888,"remaining_time":10.10941207},
{"learn":[0.4294789725],"iteration":70,"passed_time":0.7651827957,"remaining_time":10.01203968},
{"learn":[0.4286263747],"iteration":71,"passed_time":0.7698440469,"remaining_time":9.922434382},
{"learn":[0.4276449799],"iteration":72,"passed_time":0.7738908605,"remaining_time":9.827353803},
{"learn":[0.4269211363],"iteration":73,"passed_time":0.7784303128,"remaining_time":9.740898238},
{"learn":[0.426220519],"iteration":74,"passed_time":0.7822979,"remaining_time":9.648340767},
{"learn":[0.4254838683],"iteration":75,"passed_time":0.7872958424,"remaining_time":9.571859979},
{"learn":[0.4245421364],"iteration":76,"passed_time":0.7926120546,"remaining_time":9.501050992},
{"learn":[0.4238895276],"iteration":77,"passed_time":0.796312533,"remaining_time":9.412822505},
{"learn":[0.4231709443],"iteration":78,"passed_time":0.7996896162,"remaining_time":9.322963753},
{"learn":[0.4225804448],"iteration":79,"passed_time":0.8050672912,"remaining_time":9.258273849},
{"learn":[0.4219541318],"iteration":80,"passed_time":0.8123152394,"remaining_time":9.216267963},
{"learn":[0.4210997641],"iteration":81,"passed_time":0.8166554881,"remaining_time":9.142557781},
{"learn":[0.4204997375],"iteration":82,"passed_time":0.8227960621,"remaining_time":9.090409505},
{"learn":[0.4200315891],"iteration":83,"passed_time":0.8273004337,"remaining_time":9.021514253},
{"learn":[0.4194224891],"iteration":84,"passed_time":0.832190541,"remaining_time":8.958286412},
{"learn":[0.4186830983],"iteration":85,"passed_time":0.8361731294,"remaining_time":8.886770236},
{"learn":[0.4181855166],"iteration":86,"passed_time":0.8404176336,"remaining_time":8.819555166},
{"learn":[0.4176329014],"iteration":87,"passed_time":0.845944284,"remaining_time":8.767058943},
{"learn":[0.4171366028],"iteration":88,"passed_time":0.8503732057,"remaining_time":8.704381914},
{"learn":[0.4162838386],"iteration":89,"passed_time":0.8541080092,"remaining_time":8.635980982},
{"learn":[0.4154924897],"iteration":90,"passed_time":0.8575909068,"remaining_time":8.566484992},
{"learn":[0.4149668506],"iteration":91,"passed_time":0.8633893417,"remaining_time":8.521277416},
{"learn":[0.4143459928],"iteration":92,"passed_time":0.8681344884,"remaining_time":8.466644956},
{"learn":[0.4138314866],"iteration":93,"passed_time":0.8733107615,"remaining_time":8.417229254},
{"learn":[0.4133173024],"iteration":94,"passed_time":0.8789667617,"remaining_time":8.37331494},
{"learn":[0.4127133721],"iteration":95,"passed_time":0.8833111125,"remaining_time":8.31784631},
{"learn":[0.4121068083],"iteration":96,"passed_time":0.887108271,"remaining_time":8.258337821},
{"learn":[0.4117974791],"iteration":97,"passed_time":0.8915478056,"remaining_time":8.205878782},
{"learn":[0.4112405808],"iteration":98,"passed_time":0.8950005565,"remaining_time":8.145409106},
{"learn":[0.4108397361],"iteration":99,"passed_time":0.8989174931,"remaining_time":8.090257438},
{"learn":[0.4104190024],"iteration":100,"passed_time":0.9057289265,"remaining_time":8.061884208},
{"learn":[0.4098779454],"iteration":101,"passed_time":0.9115837256,"remaining_time":8.025511623},
{"learn":[0.4095559694],"iteration":102,"passed_time":0.9153099103,"remaining_time":7.971194073},
{"learn":[0.4090733865],"iteration":103,"passed_time":0.9185724308,"remaining_time":7.913854788},
{"learn":[0.4086181533],"iteration":104,"passed_time":0.922941256,"remaining_time":7.866975468},
{"learn":[0.4082484826],"iteration":105,"passed_time":0.9267883379,"remaining_time":7.816497869},
{"learn":[0.4077412502],"iteration":106,"passed_time":0.931635841,"remaining_time":7.775241178},
{"learn":[0.4071987199],"iteration":107,"passed_time":0.9374777784,"remaining_time":7.742872022},
{"learn":[0.406810738],"iteration":108,"passed_time":0.9424124073,"remaining_time":7.703572981},
{"learn":[0.4062714943],"iteration":109,"passed_time":0.9466560764,"remaining_time":7.659308255},
{"learn":[0.4059099775],"iteration":110,"passed_time":0.9502584676,"remaining_time":7.610628628},
{"learn":[0.4056650179],"iteration":111,"passed_time":0.9554779528,"remaining_time":7.575575197},
{"learn":[0.4053191477],"iteration":112,"passed_time":0.9601748327,"remaining_time":7.536947581},
{"learn":[0.4048163138],"iteration":113,"passed_time":0.9654130195,"remaining_time":7.50312224},
{"learn":[0.4043454384],"iteration":114,"passed_time":0.9697854424,"remaining_time":7.463131448},
{"learn":[0.4039463321],"iteration":115,"passed_time":0.9742734012,"remaining_time":7.42463523},
{"learn":[0.403689381],"iteration":116,"passed_time":0.9783911679,"remaining_time":7.383926507},
{"learn":[0.4033884839],"iteration":117,"passed_time":0.9841475294,"remaining_time":7.35608577},
{"learn":[0.4030933734],"iteration":118,"passed_time":0.9893954274,"remaining_time":7.324851862},
{"learn":[0.4028283633],"iteration":119,"passed_time":0.9940169313,"remaining_time":7.289457496},
{"learn":[0.4024164061],"iteration":120,"passed_time":0.99800295,"remaining_time":7.249955314},
{"learn":[0.4022096148],"iteration":121,"passed_time":1.000795963,"remaining_time":7.202449635},
{"learn":[0.4019140013],"iteration":122,"passed_time":1.006915167,"remaining_time":7.179387002},
{"learn":[0.4016593607],"iteration":123,"passed_time":1.011365271,"remaining_time":7.14480627},
{"learn":[0.4013625024],"iteration":124,"passed_time":1.017493876,"remaining_time":7.12245713},
{"learn":[0.4011625405],"iteration":125,"passed_time":1.02143696,"remaining_time":7.08520558},
{"learn":[0.4007925944],"iteration":126,"passed_time":1.025006028,"remaining_time":7.045907577},
{"learn":[0.4005589166],"iteration":127,"passed_time":1.029779404,"remaining_time":7.015372188},
{"learn":[0.400379891],"iteration":128,"passed_time":1.036518337,"remaining_time":6.998507532},
{"learn":[0.4001507309],"iteration":129,"passed_time":1.041816657,"remaining_time":6.972157625},
{"learn":[0.3999486433],"iteration":130,"passed_time":1.04835204,"remaining_time":6.954335288},
{"learn":[0.3994678926],"iteration":131,"passed_time":1.053128146,"remaining_time":6.925115382},
{"learn":[0.3991793527],"iteration":132,"passed_time":1.057387729,"remaining_time":6.892895948},
{"learn":[0.3989473034],"iteration":133,"passed_time":1.060959001,"remaining_time":6.856645487},
{"learn":[0.3987279607],"iteration":134,"passed_time":1.064838759,"remaining_time":6.822855754},
{"learn":[0.3985619396],"iteration":135,"passed_time":1.06888427,"remaining_time":6.790558891},
{"learn":[0.398261235],"iteration":136,"passed_time":1.072366566,"remaining_time":6.755126616},
{"learn":[0.3981491176],"iteration":137,"passed_time":1.075222057,"remaining_time":6.716242124},
{"learn":[0.3979923569],"iteration":138,"passed_time":1.079128981,"remaining_time":6.68438887},
{"learn":[0.3978460538],"iteration":139,"passed_time":1.083295914,"remaining_time":6.65453204},
{"learn":[0.39761621],"iteration":140,"passed_time":1.08764699,"remaining_time":6.62616145},
{"learn":[0.3974365156],"iteration":141,"passed_time":1.093715251,"remaining_time":6.608504825},
{"learn":[0.3973180319],"iteration":142,"passed_time":1.096595165,"remaining_time":6.571902494},
{"learn":[0.3970551202],"iteration":143,"passed_time":1.112117661,"remaining_time":6.610921649},
{"learn":[0.396795447],"iteration":144,"passed_time":1.136783783,"remaining_time":6.703104378},
{"learn":[0.3965542091],"iteration":145,"passed_time":1.144561443,"remaining_time":6.694900493},
{"learn":[0.3963176584],"iteration":146,"passed_time":1.15424371,"remaining_time":6.697754318},
{"learn":[0.3959726068],"iteration":147,"passed_time":1.159811903,"remaining_time":6.676755008},
{"learn":[0.3957343206],"iteration":148,"passed_time":1.166904488,"remaining_time":6.664669255},
{"learn":[0.3954862092],"iteration":149,"passed_time":1.172957936,"remaining_time":6.646761635},
{"learn":[0.3953296941],"iteration":150,"passed_time":1.178772707,"remaining_time":6.62766906},
{"learn":[0.3950499185],"iteration":151,"passed_time":1.186800439,"remaining_time":6.621097183},
{"learn":[0.3947021666],"iteration":152,"passed_time":1.199008628,"remaining_time":6.637649074},
{"learn":[0.3945013865],"iteration":153,"passed_time":1.210481544,"remaining_time":6.649788223},
{"learn":[0.3943720779],"iteration":154,"passed_time":1.217485323,"remaining_time":6.637258696},
{"learn":[0.3942083125],"iteration":155,"passed_time":1.26580199,"remaining_time":6.848313333},
{"learn":[0.3939646891],"iteration":156,"passed_time":1.279536333,"remaining_time":6.870376617},
{"learn":[0.3935757457],"iteration":157,"passed_time":1.29269743,"remaining_time":6.888931873},
{"learn":[0.3934090219],"iteration":158,"passed_time":1.296862144,"remaining_time":6.859503542},
{"learn":[0.3931295864],"iteration":159,"passed_time":1.302200662,"remaining_time":6.836553477},
{"learn":[0.3927923604],"iteration":160,"passed_time":1.307535863,"remaining_time":6.813804902},
{"learn":[0.3925449241],"iteration":161,"passed_time":1.312713666,"remaining_time":6.790457113},
{"learn":[0.39238178],"iteration":162,"passed_time":1.316927578,"remaining_time":6.762382718},
{"learn":[0.3920966572],"iteration":163,"passed_time":1.320853586,"remaining_time":6.733131693},
{"learn,
{"learn":[0.3941380026],"iteration":164,"passed_time":1.33296069,"remaining_time":6.745588945},
{"learn":[0.3938423805],"iteration":165,"passed_time":1.338998465,"remaining_time":6.72725735},
{"learn":[0.3937132319],"iteration":166,"passed_time":1.345569965,"remaining_time":6.711735214},
{"learn":[0.3934907514],"iteration":167,"passed_time":1.354488015,"remaining_time":6.707940646},
{"learn":[0.3932768963],"iteration":168,"passed_time":1.35883107,"remaining_time":6.681589461},
{"learn":[0.3930868287],"iteration":169,"passed_time":1.365101097,"remaining_time":6.664905354},
{"learn":[0.3929391143],"iteration":170,"passed_time":1.370651055,"remaining_time":6.644852189},
{"learn":[0.3928279901],"iteration":171,"passed_time":1.377975566,"remaining_time":6.633510282},
{"learn":[0.3927074282],"iteration":172,"passed_time":1.384620285,"remaining_time":6.618965177},
{"learn":[0.3925278426],"iteration":173,"passed_time":1.390549925,"remaining_time":6.601116311},
{"learn":[0.3924052694],"iteration":174,"passed_time":1.395939989,"remaining_time":6.58085995},
{"learn":[0.3923008366],"iteration":175,"passed_time":1.401206439,"remaining_time":6.56019378},
{"learn":[0.3920462914],"iteration":176,"passed_time":1.408924117,"remaining_time":6.551099144},
{"learn":[0.391937836],"iteration":177,"passed_time":1.414639406,"remaining_time":6.532772989},
{"learn":[0.3917587532],"iteration":178,"passed_time":1.421967518,"remaining_time":6.521985096},
{"learn":[0.3915747968],"iteration":179,"passed_time":1.435734353,"remaining_time":6.540567609},
{"learn":[0.391323926],"iteration":180,"passed_time":1.442409601,"remaining_time":6.526704215},
{"learn":[0.3910019636],"iteration":181,"passed_time":1.451370863,"remaining_time":6.523194319},
{"learn":[0.3907760407],"iteration":182,"passed_time":1.461442195,"remaining_time":6.524580729},
{"learn":[0.3905713912],"iteration":183,"passed_time":1.471869072,"remaining_time":6.527419365},
{"learn":[0.3901709108],"iteration":184,"passed_time":1.478513652,"remaining_time":6.513452033},
{"learn":[0.3899208137],"iteration":185,"passed_time":1.487904179,"remaining_time":6.511580656},
{"learn":[0.3897674135],"iteration":186,"passed_time":1.494707697,"remaining_time":6.498381591},
{"learn":[0.3896346292],"iteration":187,"passed_time":1.502929427,"remaining_time":6.491376035},
{"learn":[0.3895149183],"iteration":188,"passed_time":1.513909636,"remaining_time":6.496194257},
{"learn":[0.3892478411],"iteration":189,"passed_time":1.525537866,"remaining_time":6.503608798},
{"learn":[0.3889846318],"iteration":190,"passed_time":1.53247412,"remaining_time":6.490950592},
{"learn":[0.3888518862],"iteration":191,"passed_time":1.540854558,"remaining_time":6.484429598},
{"learn":[0.3886401971],"iteration":192,"passed_time":1.550149444,"remaining_time":6.481712962},
{"learn":[0.3885029647],"iteration":193,"passed_time":1.558478925,"remaining_time":6.474917597},
{"learn":[0.3883501447],"iteration":194,"passed_time":1.56321162,"remaining_time":6.453258227},
{"learn":[0.3881099493],"iteration":195,"passed_time":1.567301523,"remaining_time":6.429134819},
{"learn":[0.3879407682],"iteration":196,"passed_time":1.571679534,"remaining_time":6.406389167},
{"learn":[0.3878070943],"iteration":197,"passed_time":1.577724353,"remaining_time":6.390580461},
{"learn":[0.3876659166],"iteration":198,"passed_time":1.58492575,"remaining_time":6.379525256},
{"learn":[0.3874639746],"iteration":199,"passed_time":1.593611078,"remaining_time":6.37444431},
{"learn":[0.3872484949],"iteration":200,"passed_time":1.601649616,"remaining_time":6.366756434},
{"learn":[0.3870144882],"iteration":201,"passed_time":1.613920308,"remaining_time":6.375784186},
{"learn":[0.3868311506],"iteration":202,"passed_time":1.620997449,"remaining_time":6.364211659},
{"learn":[0.3866490121],"iteration":203,"passed_time":1.630775473,"remaining_time":6.363221945},
{"learn":[0.3864952252],"iteration":204,"passed_time":1.636555899,"remaining_time":6.34664361},
{"learn":[0.3863179215],"iteration":205,"passed_time":1.643536888,"remaining_time":6.334797518},
{"learn":[0.386186723],"iteration":206,"passed_time":1.649695593,"remaining_time":6.319848333},
{"learn":[0.386092076],"iteration":207,"passed_time":1.658324373,"remaining_time":6.31438896},
{"learn":[0.3858702917],"iteration":208,"passed_time":1.662667527,"remaining_time":6.292679493},
{"learn":[0.3857383196],"iteration":209,"passed_time":1.671648657,"remaining_time":6.288583044},
{"learn":[0.3855029591],"iteration":210,"passed_time":1.680313346,"remaining_time":6.283257013},
{"learn":[0.3853738879],"iteration":211,"passed_time":1.689091383,"remaining_time":6.2783208},
{"learn":[0.3852419545],"iteration":212,"passed_time":1.694464665,"remaining_time":6.260768505},
{"learn":[0.3851508272],"iteration":213,"passed_time":1.703326087,"remaining_time":6.256141611},
{"learn":[0.3850298012],"iteration":214,"passed_time":1.714433649,"remaining_time":6.259676346},
{"learn":[0.3846851731],"iteration":215,"passed_time":1.718806951,"remaining_time":6.238632635},
{"learn":[0.3845596604],"iteration":216,"passed_time":1.726641271,"remaining_time":6.230230945},
{"learn":[0.3844463701],"iteration":217,"passed_time":1.737510229,"remaining_time":6.232720178},
{"learn":[0.3843620503],"iteration":218,"passed_time":1.7407526,"remaining_time":6.20788941},
{"learn":[0.3842603638],"iteration":219,"passed_time":1.744315071,"remaining_time":6.184389798},
{"learn":[0.3841507867],"iteration":220,"passed_time":1.747911057,"remaining_time":6.161188748},
{"learn":[0.3839729802],"iteration":221,"passed_time":1.75151151,"remaining_time":6.138179976},
{"learn":[0.3838699399],"iteration":222,"passed_time":1.75521551,"remaining_time":6.115706059},
{"learn":[0.3837786192],"iteration":223,"passed_time":1.758826733,"remaining_time":6.093078326},
{"learn":[0.3836742251],"iteration":224,"passed_time":1.762441574,"remaining_time":6.070632087},
{"learn":[0.383651598],"iteration":225,"passed_time":1.764798684,"remaining_time":6.04404505},
{"learn":[0.3835232617],"iteration":226,"passed_time":1.768096201,"remaining_time":6.020873848},
{"learn":[0.3833355148],"iteration":227,"passed_time":1.77184178,"remaining_time":5.999394097},
{"learn":[0.3832123228],"iteration":228,"passed_time":1.775668243,"remaining_time":5.97834155},
{"learn":[0.3830691726],"iteration":229,"passed_time":1.779436093,"remaining_time":5.957242571},
{"learn":[0.3829420353],"iteration":230,"passed_time":1.783859079,"remaining_time":5.938474597},
{"learn":[0.3827171954],"iteration":231,"passed_time":1.787287646,"remaining_time":5.916538413},
{"learn":[0.382574548],"iteration":232,"passed_time":1.791184843,"remaining_time":5.896303752},
{"learn":[0.3824339118],"iteration":233,"passed_time":1.795463875,"remaining_time":5.877458669},
{"learn":[0.3822043918],"iteration":234,"passed_time":1.798979998,"remaining_time":5.856254037},
{"learn":[0.3821413454],"iteration":235,"passed_time":1.802477334,"remaining_time":5.835138489},
{"learn":[0.3820695575],"iteration":236,"passed_time":1.807625851,"remaining_time":5.819487443},
{"learn":[0.3819783915],"iteration":237,"passed_time":1.811733276,"remaining_time":5.800591414},
{"learn":[0.3818467676],"iteration":238,"passed_time":1.815761754,"remaining_time":5.781567759},
{"learn":[0.3817633374],"iteration":239,"passed_time":1.819886633,"remaining_time":5.762974339},
{"learn":[0.3816983183],"iteration":240,"passed_time":1.824011393,"remaining_time":5.744500611},
{"learn":[0.3815453049],"iteration":241,"passed_time":1.827700004,"remaining_time":5.72477935},
{"learn":[0.3814245497],"iteration":242,"passed_time":1.832099405,"remaining_time":5.70740432},
{"learn":[0.3812669723],"iteration":243,"passed_time":1.836032991,"remaining_time":5.688692383},
{"learn":[0.3810820876],"iteration":244,"passed_time":1.839716742,"remaining_time":5.669331184},
{"learn":[0.3809120555],"iteration":245,"passed_time":1.847262294,"remaining_time":5.661934023},
{"learn":[0.3808398422],"iteration":246,"passed_time":1.851574921,"remaining_time":5.644679819},
{"learn":[0.3806391379],"iteration":247,"passed_time":1.855965395,"remaining_time":5.627766037},
{"learn":[0.380574699],"iteration":248,"passed_time":1.861044609,"remaining_time":5.613030126},
{"learn":[0.3804764548],"iteration":249,"passed_time":1.86484911,"remaining_time":5.59454733},
{"learn":[0.380273159],"iteration":250,"passed_time":1.868242029,"remaining_time":5.574953304},
{"learn":[0.3801716658],"iteration":251,"passed_time":1.871834105,"remaining_time":5.556079011},
{"learn":[0.3799914226],"iteration":252,"passed_time":1.875157192,"remaining_time":5.536531315},
{"learn":[0.3797724232],"iteration":253,"passed_time":1.878855281,"remaining_time":5.518212754},
{"learn":[0.3796293116],"iteration":254,"passed_time":1.88329615,"remaining_time":5.502178949},
{"learn":[0.3795569822],"iteration":255,"passed_time":1.886877107,"remaining_time":5.483736593},
{"learn":[0.3794584286],"iteration":256,"passed_time":1.890255238,"remaining_time":5.46482350,
,
{"learn":[0.3793218538],"iteration":257,"passed_time":1.894689996,"remaining_time":5.44906967,
,
{"learn":[0.3791803667],"iteration":258,"passed_time":1.898189859,"remaining_time":5.43072851,
,
{"learn":[0.3791158118],"iteration":259,"passed_time":1.901597166,"remaining_time":5.41223808,
,
{"learn":[0.3790205072],"iteration":260,"passed_time":1.905176378,"remaining_time":5.39434997,
{"learn":[0.3770766822],"iteration":261,"passed_time":1.909468917,"remaining_time":5.378580385},
{"learn":[0.3770285774],"iteration":262,"passed_time":1.913227554,"remaining_time":5.361401929},
{"learn":[0.376907255],"iteration":263,"passed_time":1.917944829,"remaining_time":5.346997705},
{"learn":[0.3768701938],"iteration":264,"passed_time":1.92357841,"remaining_time":5.335208042},
{"learn":[0.3767630636],"iteration":265,"passed_time":1.928306749,"remaining_time":5.320966744},
{"learn":[0.3766957653],"iteration":266,"passed_time":1.933025404,"remaining_time":5.306770117},
{"learn":[0.3765994204],"iteration":267,"passed_time":1.936528787,"remaining_time":5.289324895},
{"learn":[0.3764545588],"iteration":268,"passed_time":1.940854156,"remaining_time":5.274217056},
{"learn":[0.3762734304],"iteration":269,"passed_time":1.945935676,"remaining_time":5.261233495},
{"learn":[0.3761833236],"iteration":270,"passed_time":1.950531233,"remaining_time":5.247000991},
{"learn":[0.3760801785],"iteration":271,"passed_time":1.954247545,"remaining_time":5.230486078},
{"learn":[0.3759231499],"iteration":272,"passed_time":1.959818167,"remaining_time":5.219002957},
{"learn":[0.3758156617],"iteration":273,"passed_time":1.966606219,"remaining_time":5.21078874},
{"learn":[0.3756467242],"iteration":274,"passed_time":1.970897483,"remaining_time":5.196002455},
{"learn":[0.3754743217],"iteration":275,"passed_time":1.976349573,"remaining_time":5.184337285},
{"learn":[0.3753258448],"iteration":276,"passed_time":1.981138977,"remaining_time":5.170987295},
{"learn":[0.3751294412],"iteration":277,"passed_time":1.985233776,"remaining_time":5.155894916},
{"learn":[0.3749673874],"iteration":278,"passed_time":1.989464503,"remaining_time":5.141232641},
{"learn":[0.374789516],"iteration":279,"passed_time":1.995424037,"remaining_time":5.131090381},
{"learn":[0.374644191],"iteration":280,"passed_time":2.000767921,"remaining_time":5.119402616},
{"learn":[0.3744858276],"iteration":281,"passed_time":2.009906704,"remaining_time":5.117422034},
{"learn":[0.3743299375],"iteration":282,"passed_time":2.015502502,"remaining_time":5.106414465},
{"learn":[0.3742597142],"iteration":283,"passed_time":2.022121971,"remaining_time":5.098025814},
{"learn":[0.3742066002],"iteration":284,"passed_time":2.025068232,"remaining_time":5.080434336},
{"learn":[0.3740574796],"iteration":285,"passed_time":2.029193095,"remaining_time":5.065887656},
{"learn":[0.3739088376],"iteration":286,"passed_time":2.034433359,"remaining_time":5.054184616},
{"learn":[0.3737897849],"iteration":287,"passed_time":2.040262642,"remaining_time":5.043982643},
{"learn":[0.3737766898],"iteration":288,"passed_time":2.04540217,"remaining_time":5.03211399},
{"learn":[0.3736483355],"iteration":289,"passed_time":2.051093335,"remaining_time":5.021642302},
{"learn":[0.3734868027],"iteration":290,"passed_time":2.056378558,"remaining_time":5.010214426},
{"learn":[0.3734732241],"iteration":291,"passed_time":2.05907606,"remaining_time":4.992554284},
{"learn":[0.3733550326],"iteration":292,"passed_time":2.065302711,"remaining_time":4.983512003},
{"learn":[0.3732576293],"iteration":293,"passed_time":2.071136434,"remaining_time":4.973545314},
{"learn":[0.3732074563],"iteration":294,"passed_time":2.076594747,"remaining_time":4.962709481},
{"learn":[0.3731005782],"iteration":295,"passed_time":2.082865836,"remaining_time":4.95384307},
{"learn":[0.373005748],"iteration":296,"passed_time":2.090182854,"remaining_time":4.947469852},
{"learn":[0.3729068835],"iteration":297,"passed_time":2.097921075,"remaining_time":4.942082533},
{"learn":[0.3727470605],"iteration":298,"passed_time":2.104519505,"remaining_time":4.934007267},
{"learn":[0.3726700064],"iteration":299,"passed_time":2.111313049,"remaining_time":4.926397114},
{"learn":[0.3726063671],"iteration":300,"passed_time":2.117410194,"remaining_time":4.917175168},
{"learn":[0.372558902],"iteration":301,"passed_time":2.122931356,"remaining_time":4.906642671},
{"learn":[0.3724937213],"iteration":302,"passed_time":2.130613784,"remaining_time":4.901114877},
{"learn":[0.3723866994],"iteration":303,"passed_time":2.136668746,"remaining_time":4.891846866},
{"learn":[0.3722628818],"iteration":304,"passed_time":2.142613073,"remaining_time":4.882347822},
{"learn":[0.3722616062],"iteration":305,"passed_time":2.144311928,"remaining_time":4.863243391},
{"learn":[0.3721296113],"iteration":306,"passed_time":2.150252216,"remaining_time":4.853826664},
{"learn":[0.3720690015],"iteration":307,"passed_time":2.15534301,"remaining_time":4.842523906},
{"learn":[0.3719264301],"iteration":308,"passed_time":2.159996294,"remaining_time":4.830282975},
{"learn":[0.3718426403],"iteration":309,"passed_time":2.166733624,"remaining_time":4.822729679},
{"learn":[0.3717955752],"iteration":310,"passed_time":2.172146406,"remaining_time":4.812247183},
{"learn":[0.3717471304],"iteration":311,"passed_time":2.178186285,"remaining_time":4.803180012},
{"learn":[0.3716060151],"iteration":312,"passed_time":2.181769143,"remaining_time":4.7887393},
{"learn":[0.3714991015],"iteration":313,"passed_time":2.189790069,"remaining_time":4.784063655},
{"learn":[0.3713481936],"iteration":314,"passed_time":2.195868502,"remaining_time":4.775142616},
{"learn":[0.3711193399],"iteration":315,"passed_time":2.20219299,"remaining_time":4.766772168},
{"learn":[0.3710295638],"iteration":316,"passed_time":2.212638074,"remaining_time":4.767292759},
{"learn":[0.3707897998],"iteration":317,"passed_time":2.22077613,"remaining_time":4.762796606},
{"learn":[0.370640381],"iteration":318,"passed_time":2.226108845,"remaining_time":4.752288789},
{"learn":[0.3705216017],"iteration":319,"passed_time":2.23086628,"remaining_time":4.740590844},
{"learn":[0.3704088699],"iteration":320,"passed_time":2.238257173,"remaining_time":4.734506606},
{"learn":[0.3703822972],"iteration":321,"passed_time":2.244863901,"remaining_time":4.726763121},
{"learn":[0.3701342001],"iteration":322,"passed_time":2.255901788,"remaining_time":4.728314275},
{"learn":[0.370034886],"iteration":323,"passed_time":2.262286155,"remaining_time":4.72007852},
{"learn":[0.3699212205],"iteration":324,"passed_time":2.268359631,"remaining_time":4.711208464},
{"learn":[0.3698270838],"iteration":325,"passed_time":2.274043703,"remaining_time":4.701550477},
{"learn":[0.3696961255],"iteration":326,"passed_time":2.281263328,"remaining_time":4.695077125},
{"learn":[0.3695624082],"iteration":327,"passed_time":2.287819949,"remaining_time":4.687240871},
{"learn":[0.3695113182],"iteration":328,"passed_time":2.294230089,"remaining_time":4.679113647},
{"learn":[0.3693928247],"iteration":329,"passed_time":2.297990691,"remaining_time":4.665617463},
{"learn":[0.3691769839],"iteration":330,"passed_time":2.310659028,"remaining_time":4.670183956},
{"learn":[0.3690119485],"iteration":331,"passed_time":2.321810372,"remaining_time":4.671594363},
{"learn":[0.3688638195],"iteration":332,"passed_time":2.332163072,"remaining_time":4.671329637},
{"learn":[0.368827002],"iteration":333,"passed_time":2.344525213,"remaining_time":4.675011352},
{"learn":[0.3687569555],"iteration":334,"passed_time":2.350763289,"remaining_time":4.666440559},
{"learn":[0.3685564498],"iteration":335,"passed_time":2.360642532,"remaining_time":4.66507929},
{"learn":[0.3683297867],"iteration":336,"passed_time":2.372450619,"remaining_time":4.667462197},
{"learn":[0.3682247063],"iteration":337,"passed_time":2.382322045,"remaining_time":4.665968028},
{"learn":[0.3680056558],"iteration":338,"passed_time":2.397008419,"remaining_time":4.673812875},
{"learn":[0.3678726215],"iteration":339,"passed_time":2.409345534,"remaining_time":4.67696486},
{"learn":[0.3677370197],"iteration":340,"passed_time":2.414589149,"remaining_time":4.666317446},
{"learn":[0.367684686],"iteration":341,"passed_time":2.420286073,"remaining_time":4.65657379},
{"learn":[0.3676834533],"iteration":342,"passed_time":2.422983451,"remaining_time":4.641108243},
{"learn":[0.3676190339],"iteration":343,"passed_time":2.432982513,"remaining_time":4.639641071},
{"learn":[0.3675886893],"iteration":344,"passed_time":2.43932497,"remaining_time":4.631182189},
{"learn":[0.3674968871],"iteration":345,"passed_time":2.443512862,"remaining_time":4.618663039},
{"learn":[0.367454352],"iteration":346,"passed_time":2.449583976,"remaining_time":4.60973584},
{"learn":[0.3673921055],"iteration":347,"passed_time":2.456275167,"remaining_time":4.601986807},
{"learn":[0.3672867114],"iteration":348,"passed_time":2.461287184,"remaining_time":4.591111624},
{"learn":[0.3671766046],"iteration":349,"passed_time":2.46710418,"remaining_time":4.581764905},
{"learn":[0.3670704408],"iteration":350,"passed_time":2.473634622,"remaining_time":4.573757463},
{"learn":[0.3670042672],"iteration":351,"passed_time":2.477820914,"remaining_time":4.561443045},
{"learn":[0.3669192063],"iteration":352,"passed_time":2.481582907,"remaining_time":4.548397},
{"learn":[0.3669184851],"iteration":353,"passed_time":2.483844706,"remaining_time":4.532665763},
{"learn":[0.3667990415],"iteration":354,"passed_time":2.489481844,"remaining_time":4.523143069},
{"learn":[0.3666937125],"iteration":355,"passed_time":2.496503823,"remaining_time":4.516147366},
{"learn":[0.3666338557],"iteration":356,"passed_time":2.501690145,"remaining_time":4.505845276},
{"learn":[0.3664258434],"iteration":357,"passed_time":2.50913143,"remaining_time":4.499615581},
{"learn":[0.366294528],"iteration":358,"passed_time":2.514382355,"remaining_time":4.489468216},
{"learn":[0.3662401475],"iteration":359,"passed_time":2.519279601,"remaining_time":4.478719291},
{"learn":[0.3661628284],"iteration":360,"passed_time":2.524557245,"remaining_time":4.46867612},
{"learn":[0.3661414864],"iteration":361,"passed_time":2.526926331,"remaining_time":4.453533146},
{"learn":[0.3660756757],"iteration":362,"passed_time":2.533053879,"remaining_time":4.445055981},
{"learn":[0.3660209125],"iteration":363,"passed_time":2.538257563,"remaining_time":4.4349775},
{"learn":[0.3659595169],"iteration":364,"passed_time":2.544482149,"remaining_time":4.426701822},
{"learn":[0.3658388258],"iteration":365,"passed_time":2.549003903,"remaining_time":4.415487635},
{"learn":[0.3657443127],"iteration":366,"passed_time":2.554671525,"remaining_time":4.406286309},
{"learn":[0.3656757074],"iteration":367,"passed_time":2.561078405,"remaining_time":4.398373782},
{"learn":[0.3655746504],"iteration":368,"passed_time":2.565264022,"remaining_time":4.386670997},
{"learn":[0.3654265954],"iteration":369,"passed_time":2.569540186,"remaining_time":4.375163019},
{"learn":[0.3652109249],"iteration":370,"passed_time":2.575109922,"remaining_time":4.365887172},
{"learn":[0.3650762194],"iteration":371,"passed_time":2.592123566,"remaining_time":4.375950536},
{"learn":[0.3648856378],"iteration":372,"passed_time":2.597432088,"remaining_time":4.366192812},
{"learn":[0.3648237295],"iteration":373,"passed_time":2.606596501,"remaining_time":4.36291286},
{"learn":[0.364744837],"iteration":374,"passed_time":2.610277927,"remaining_time":4.350463211},
{"learn":[0.3646549768],"iteration":375,"passed_time":2.613938266,"remaining_time":4.338025208},
{"learn":[0.364504394],"iteration":376,"passed_time":2.61770441,"remaining_time":4.325808613},
{"learn":[0.3643583356],"iteration":377,"passed_time":2.622815285,"remaining_time":4.31584949},
{"learn":[0.3642202034],"iteration":378,"passed_time":2.627796901,"remaining_time":4.305704158},
{"learn":[0.3641276391],"iteration":379,"passed_time":2.636304984,"remaining_time":4.301339711},
{"learn":[0.3641270421],"iteration":380,"passed_time":2.638458757,"remaining_time":4.286629845},
{"learn":[0.3639853722],"iteration":381,"passed_time":2.649807479,"remaining_time":4.286861314},
{"learn":[0.3638749798],"iteration":382,"passed_time":2.656790671,"remaining_time":4.279999594},
{"learn":[0.3637997396],"iteration":383,"passed_time":2.665283692,"remaining_time":4.275559255},
{"learn":[0.3637373004],"iteration":384,"passed_time":2.673644749,"remaining_time":4.270887067},
{"learn":[0.36367216],"iteration":385,"passed_time":2.680226108,"remaining_time":4.263364846},
{"learn":[0.363480883],"iteration":386,"passed_time":2.686203999,"remaining_time":4.254891606},
{"learn":[0.3634351505],"iteration":387,"passed_time":2.693927959,"remaining_time":4.249185338},
{"learn":[0.3633345146],"iteration":388,"passed_time":2.711178984,"remaining_time":4.258432801},
{"learn":[0.36323707],"iteration":389,"passed_time":2.721789213,"remaining_time":4.257157487},
{"learn":[0.3631475613],"iteration":390,"passed_time":2.738110604,"remaining_time":4.264729816},
{"learn":[0.3629381351],"iteration":391,"passed_time":2.749145371,"remaining_time":4.263980576},
{"learn":[0.3628288062],"iteration":392,"passed_time":2.767137395,"remaining_time":4.273924678},
{"learn":[0.3627467909],"iteration":393,"passed_time":2.77643838,"remaining_time":4.270359539},
{"learn":[0.362618802],"iteration":394,"passed_time":2.785696681,"remaining_time":4.26669998},
{"learn":[0.3625161476],"iteration":395,"passed_time":2.791325902,"remaining_time":4.25747688},
{"learn":[0.3624478346],"iteration":396,"passed_time":2.79491513,"remaining_time":4.245173359},
{"learn":[0.3622593476],"iteration":397,"passed_time":2.800765994,"remaining_time":4.236334494},
{"learn":[0.3622031691],"iteration":398,"passed_time":2.809664741,"remaining_time":4.232101527},
{"learn":[0.3621231728],"iteration":399,"passed_time":2.815428188,"remaining_time":4.223142282},
{"learn":[0.3619819492],"iteration":400,"passed_time":2.821189621,"remaining_time":4.214195968},
{"learn":[0.361852713],"iteration":401,"passed_time":2.827466814,"remaining_time":4.206032723},
{"learn":[0.3617636353],"iteration":402,"passed_time":2.839770796,"remaining_time":4.206806861},
{"learn":[0.3617046139],"iteration":403,"passed_time":2.843483531,"remaining_time":4.194842041},
{"learn":[0.361638463],"iteration":404,"passed_time":2.852866648,"remaining_time":4.191248533},
{"learn":[0.3614230344],"iteration":405,"passed_time":2.860110213,"remaining_time":4.184496223},
{"learn":[0.3612869169],"iteration":406,"passed_time":2.865843367,"remaining_time":4.175540827},
{"learn":[0.3612274368],"iteration":407,"passed_time":2.877789575,"remaining_time":4.175616246},
{"learn":[0.3610888055],"iteration":408,"passed_time":2.88705718,"remaining_time":4.171762331},
{"learn":[0.3609528798],"iteration":409,"passed_time":2.900665254,"remaining_time":4.174128048},
{"learn":[0.3608864262],"iteration":410,"passed_time":2.915537381,"remaining_time":4.178227537},
{"learn":[0.3607964289],"iteration":411,"passed_time":2.92479023,"remaining_time":4.174215182},
{"learn":[0.3607791624],"iteration":412,"passed_time":2.927778824,"remaining_time":4.161274018},
{"learn":[0.3606586136],"iteration":413,"passed_time":2.93122967,"remaining_time":4.149035234},
{"learn":[0.3605120864],"iteration":414,"passed_time":2.935431928,"remaining_time":4.137898019},
{"learn":[0.360380344],"iteration":415,"passed_time":2.940838366,"remaining_time":4.128484629},
{"learn":[0.3602140502],"iteration":416,"passed_time":2.945608347,"remaining_time":4.118200639},
{"learn":[0.3600784909],"iteration":417,"passed_time":2.949650912,"remaining_time":4.106930217},
{"learn":[0.3599435852],"iteration":418,"passed_time":2.953616306,"remaining_time":4.095587289},
{"learn":[0.3597606811],"iteration":419,"passed_time":2.957789359,"remaining_time":4.084566257},
{"learn":[0.3596787562],"iteration":420,"passed_time":2.962325714,"remaining_time":4.074077408},
{"learn":[0.3596055848],"iteration":421,"passed_time":2.967013113,"remaining_time":4.063823647},
{"learn":[0.3594738201],"iteration":422,"passed_time":2.971007791,"remaining_time":4.05265129},
{"learn":[0.3593146259],"iteration":423,"passed_time":2.975141999,"remaining_time":4.041702338},
{"learn":[0.3592594389],"iteration":424,"passed_time":2.979800082,"remaining_time":4.031494229},
{"learn":[0.3592028772],"iteration":425,"passed_time":2.983847729,"remaining_time":4.020489663},
{"learn":[0.3590667015],"iteration":426,"passed_time":2.988098894,"remaining_time":4.009790788},
{"learn":[0.358991892],"iteration":427,"passed_time":2.992082688,"remaining_time":3.998764714},
{"learn":[0.3589246795],"iteration":428,"passed_time":2.996390868,"remaining_time":3.988203231},
{"learn":[0.3587418838],"iteration":429,"passed_time":3.003530758,"remaining_time":3.981424493},
{"learn":[0.3586146661],"iteration":430,"passed_time":3.014425736,"remaining_time":3.979601494},
{"learn":[0.3585471871],"iteration":431,"passed_time":3.020058712,"remaining_time":3.970817936},
{"learn":[0.358367528],"iteration":432,"passed_time":3.031638768,"remaining_time":3.969836446},
{"learn":[0.3582205151],"iteration":433,"passed_time":3.052763868,"remaining_time":3.981254261},
{"learn":[0.3580740906],"iteration":434,"passed_time":3.064754397,"remaining_time":3.98065801},
{"learn":[0.3580001723],"iteration":435,"passed_time":3.07561981,"remaining_time":3.978554067},
{"learn":[0.3578948764],"iteration":436,"passed_time":3.084104782,"remaining_time":3.973343232},
{"learn":[0.3577255953],"iteration":437,"passed_time":3.093660511,"remaining_time":3.96949134},
{"learn":[0.3575928557],"iteration":438,"passed_time":3.116456901,"remaining_time":3.982533762},
{"learn":[0.3575928462],"iteration":439,"passed_time":3.120510549,"remaining_time":3.971558881},
{"learn":[0.3575081569],"iteration":440,"passed_time":3.132021118,"remaining_time":3.970067585},
{"learn":[0.3573897155],"iteration":441,"passed_time":3.143880568,"remaining_time":3.968971395},
{"learn":[0.3572517452],"iteration":442,"passed_time":3.156146325,"remaining_time":3.968337479},
{"learn":[0.3571644401],"iteration":443,"passed_time":3.168887574,"remaining_time":3.968246602},
{"learn":[0.3570358948],"iteration":444,"passed_time":3.180634485,"remaining_time":3.966858739},
{"learn":[0.3569444574],"iteration":445,"passed_time":3.188013446,"remaining_time":3.959998765},
{"learn":[0.3567551497],"iteration":446,"passed_time":3.196681312,"remaining_time":3.954731019},
{"learn":[0.3565949192],"iteration":447,"passed_time":3.207476079,"remaining_time":3.95206874},
{"learn":[0.3565162596],"iteration":448,"passed_time":3.215233904,"remaining_time":3.945643387},
{"learn":[0.3564186195],"iteration":449,"passed_time":3.223619095,"remaining_time":3.939978894},
{"learn":[0.3562214408],"iteration":450,"passed_time":3.231135878,"remaining_time":3.933245226},
{"learn":[0.3561362841],"iteration":451,"passed_time":3.244796458,"remaining_time":3.933956767},
{"learn":[0.3560300602],"iteration":452,"passed_time":3.249968909,"remaining_time":3.924355393},
{"learn":[0.3559647425],"iteration":453,"passed_time":3.255777897,"remaining_time":3.915539057},
{"learn":[0.3558687122],"iteration":454,"passed_time":3.262433085,"remaining_time":3.90774952},
{"learn":[0.3558123899],"iteration":455,"passed_time":3.268757873,"remaining_time":3.899570796},
{"learn":[0.355726339],"iteration":456,"passed_time":3.274808372,"remaining_time":3.89107428},
{"learn":[0.3556283819],"iteration":457,"passed_time":3.282215415,"remaining_time":3.884193788},
{"learn":[0.3554385995],"iteration":458,"passed_time":3.291501397,"remaining_time":3.879525612},
{"learn":[0.3553063163],"iteration":459,"passed_time":3.29842878,"remaining_time":3.872068568},
{"learn":[0.3551961619],"iteration":460,"passed_time":3.309725636,"remaining_time":3.869722599},
{"learn":[0.3550929668],"iteration":461,"passed_time":3.316268092,"remaining_time":3.861801371},
{"learn":[0.3549039961],"iteration":462,"passed_time":3.324439755,"remaining_time":3.855775698},
{"learn":[0.3548668476],"iteration":463,"passed_time":3.328314378,"remaining_time":3.844776954},
{"learn":[0.3547531006],"iteration":464,"passed_time":3.333941043,"remaining_time":3.835824641},
{"learn":[0.3545959915],"iteration":465,"passed_time":3.33991383,"remaining_time":3.82728323},
{"learn":[0.3544644923],"iteration":466,"passed_time":3.348350188,"remaining_time":3.821564561},
{"learn":[0.3543877254],"iteration":467,"passed_time":3.355317907,"remaining_time":3.8141648},
{"learn":[0.3542630249],"iteration":468,"passed_time":3.363362205,"remaining_time":3.80798578},
{"learn":[0.3541651431],"iteration":469,"passed_time":3.369496642,"remaining_time":3.79964515},
{"learn":[0.3540662588],"iteration":470,"passed_time":3.374633425,"remaining_time":3.79019338},
{"learn":[0.353923579],"iteration":471,"passed_time":3.380208956,"remaining_time":3.781250697},
{"learn":[0.3538074472],"iteration":472,"passed_time":3.387985984,"remaining_time":3.774775081},
{"learn":[0.3537147359],"iteration":473,"passed_time":3.394980649,"remaining_time":3.767425783},
{"learn":[0.3536525555],"iteration":474,"passed_time":3.404396588,"remaining_time":3.762754124},
{"learn":[0.3535307362],"iteration":475,"passed_time":3.410266688,"remaining_time":3.754159127},
{"learn":[0.3533990077],"iteration":476,"passed_time":3.416361889,"remaining_time":3.745822364},
{"learn":[0.353280004],"iteration":477,"passed_time":3.42245622,"remaining_time":3.737494031},
{"learn":[0.3531958375],"iteration":478,"passed_time":3.427808399,"remaining_time":3.728367799},
{"learn":[0.3531237836],"iteration":479,"passed_time":3.438233559,"remaining_time":3.724753023},
{"learn":[0.3530469502],"iteration":480,"passed_time":3.443860685,"remaining_time":3.715932839},
{"learn":[0.3528856518],"iteration":481,"passed_time":3.451512255,"remaining_time":3.709301552},
{"learn":[0.352784576],"iteration":482,"passed_time":3.459184745,"remaining_time":3.702688433},
{"learn":[0.3526444841],"iteration":483,"passed_time":3.464401253,"remaining_time":3.693452576},
{"learn":[0.3525235979],"iteration":484,"passed_time":3.474976104,"remaining_time":3.689923079},
{"learn":[0.3524872429],"iteration":485,"passed_time":3.484858805,"remaining_time":3.685632564},
{"learn":[0.3524486788],"iteration":486,"passed_time":3.492130576,"remaining_time":3.678568759},
{"learn":[0.3522954703],"iteration":487,"passed_time":3.498017547,"remaining_time":3.670051197},
{"learn":[0.3522399909],"iteration":488,"passed_time":3.504722966,"remaining_time":3.662399663},
{"learn":[0.3521315579],"iteration":489,"passed_time":3.510428154,"remaining_time":3.653710936},
{"learn":[0.3520289054],"iteration":490,"passed_time":3.51461684,"remaining_time":3.643462264},
{"learn":[0.3518756996],"iteration":491,"passed_time":3.518356777,"remaining_time":3.632774883},
{"learn":[0.3517287149],"iteration":492,"passed_time":3.522103265,"remaining_time":3.622122425},
{"learn":[0.3516265842],"iteration":493,"passed_time":3.526062405,"remaining_time":3.611715743},
{"learn":[0.3514925551],"iteration":494,"passed_time":3.529602139,"remaining_time":3.600907233},
{"learn":[0.3513729881],"iteration":495,"passed_time":3.533347116,"remaining_time":3.590336585},
{"learn":[0.3512215889],"iteration":496,"passed_time":3.537897392,"remaining_time":3.580608427},
{"learn":[0.3511174724],"iteration":497,"passed_time":3.541589381,"remaining_time":3.570035882},
{"learn":[0.3510523641],"iteration":498,"passed_time":3.545226399,"remaining_time":3.559435723},
{"learn":[0.3509884612],"iteration":499,"passed_time":3.549218532,"remaining_time":3.549218532},
{"learn":[0.3508847848],"iteration":500,"passed_time":3.554193968,"remaining_time":3.540005569},
{"learn":[0.3506782462],"iteration":501,"passed_time":3.557991671,"remaining_time":3.52964114},
{"learn":[0.350553051],"iteration":502,"passed_time":3.562166999,"remaining_time":3.519675941},
{"learn":[0.3503300079],"iteration":503,"passed_time":3.568392207,"remaining_time":3.511751061},
{"learn":[0.3502310786],"iteration":504,"passed_time":3.57337558,"remaining_time":3.502615667},
{"learn":[0.3501113196],"iteration":505,"passed_time":3.578475822,"remaining_time":3.493610782},
{"learn":[0.3500994503],"iteration":506,"passed_time":3.58048421,"remaining_time":3.481614824},
{"learn":[0.349890713],"iteration":507,"passed_time":3.585452571,"remaining_time":3.472524931},
{"learn":[0.3497672679],"iteration":508,"passed_time":3.590246545,"remaining_time":3.463283013},
{"learn":[0.3496432559],"iteration":509,"passed_time":3.595167641,"remaining_time":3.454180674},
{"learn":[0.3494681225],"iteration":510,"passed_time":3.598964251,"remaining_time":3.444018628},
{"learn":[0.3493760368],"iteration":511,"passed_time":3.603496942,"remaining_time":3.434583023},
{"learn":[0.3493130588],"iteration":512,"passed_time":3.612381748,"remaining_time":3.429298073},
{"learn":[0.349236138],"iteration":513,"passed_time":3.617956809,"remaining_time":3.420869667},
{"learn":[0.3491075049],"iteration":514,"passed_time":3.623673363,"remaining_time":3.412585594},
{"learn":[0.3489499448],"iteration":515,"passed_time":3.628840793,"remaining_time":3.403796402},
{"learn":[0.3488110049],"iteration":516,"passed_time":3.632371786,"remaining_time":3.393492404},
{"learn":[0.3487140452],"iteration":517,"passed_time":3.637917102,"remaining_time":3.385088886},
{"learn":[0.3486009359],"iteration":518,"passed_time":3.643866096,"remaining_time":3.377070505},
{"learn":[0.3484801147],"iteration":519,"passed_time":3.652605203,"remaining_time":3.371635572},
{"learn":[0.3483901533],"iteration":520,"passed_time":3.655973647,"remaining_time":3.361250244},
{"learn":[0.3482907012],"iteration":521,"passed_time":3.660606917,"remaining_time":3.352050012},
{"learn":[0.348154602],"iteration":522,"passed_time":3.665638136,"remaining_time":3.343230193},
{"learn":[0.3480533571],"iteration":523,"passed_time":3.67223731,"remaining_time":3.33584916},
{"learn":[0.3479402467],"iteration":524,"passed_time":3.67715577,"remaining_time":3.326950459},
{"learn":[0.3478333738],"iteration":525,"passed_time":3.682002842,"remaining_time":3.318002561},
{"learn":[0.347676075],"iteration":526,"passed_time":3.685613579,"remaining_time":3.307960575},
{"learn":[0.3475561111],"iteration":527,"passed_time":3.691036694,"remaining_time":3.299563105},
{"learn":[0.3474351555],"iteration":528,"passed_time":3.696617738,"remaining_time":3.291317494},
{"learn":[0.3473432396],"iteration":529,"passed_time":3.701629865,"remaining_time":3.282577427},
{"learn":[0.3472302481],"iteration":530,"passed_time":3.708198953,"remaining_time":3.275226571},
{"learn":[0.347118129],"iteration":531,"passed_time":3.714317585,"remaining_time":3.267482387},
{"learn":[0.3469908579],"iteration":532,"passed_time":3.720927403,"remaining_time":3.260174667},
{"learn":[0.3468963581],"iteration":533,"passed_time":3.726096557,"remaining_time":3.251612351},
{"learn":[0.3467556523],"iteration":534,"passed_time":3.7312153,"remaining_time":3.243018906},
{"learn":[0.346591602],"iteration":535,"passed_time":3.736779086,"remaining_time":3.234823687},
{"learn":[0.34640841],"iteration":536,"passed_time":3.741343023,"remaining_time":3.225776201},
{"learn":[0.3462864762],"iteration":537,"passed_time":3.74903806,"remaining_time":3.21943417},
{"learn":[0.3462044161],"iteration":538,"passed_time":3.753584306,"remaining_time":3.210393999},
{"learn":[0.3461378093],"iteration":539,"passed_time":3.75766252,"remaining_time":3.200971776},
{"learn":[0.3459282475],"iteration":540,"passed_time":3.763925992,"remaining_time":3.193423346},
{"learn":[0.345879983],"iteration":541,"passed_time":3.769486079,"remaining_time":3.185285285},
{"learn":[0.3457085462],"iteration":542,"passed_time":3.777660585,"remaining_time":3.179357067},
{"learn":[0.3455850126],"iteration":543,"passed_time":3.783715957,"remaining_time":3.171644258},
{"learn":[0.3454762963],"iteration":544,"passed_time":3.789085064,"remaining_time":3.163364594},
{"learn":[0.3453807585],"iteration":545,"passed_time":3.794562769,"remaining_time":3.155185892},
{"learn":[0.3452735952],"iteration":546,"passed_time":3.799787001,"remaining_time":3.146807151},
{"learn":[0.3451465079],"iteration":547,"passed_time":3.809123632,"remaining_time":3.141831901},
{"learn":[0.3450343617],"iteration":548,"passed_time":3.815206569,"remaining_time":3.134167873},
{"learn":[0.3449184969],"iteration":549,"passed_time":3.823232357,"remaining_time":3.128099201},
{"learn":[0.3447959147],"iteration":550,"passed_time":3.82930179,"remaining_time":3.120429226},
{"learn":[0.3446907574],"iteration":551,"passed_time":3.838703518,"remaining_time":3.115469522},
{"learn":[0.3445872287],"iteration":552,"passed_time":3.84700738,"remaining_time":3.109606327},
{"learn":[0.3444944309],"iteration":553,"passed_time":3.854853847,"remaining_time":3.103366094},
{"learn":[0.3443470681],"iteration":554,"passed_time":3.861063064,"remaining_time":3.095807321},
{"learn":[0.3441929828],"iteration":555,"passed_time":3.870046096,"remaining_time":3.090468465},
{"learn":[0.3440859433],"iteration":556,"passed_time":3.877436169,"remaining_time":3.083849592},
{"learn":[0.3439819948],"iteration":557,"passed_time":3.882259509,"remaining_time":3.075194808},
{"learn":[0.3438922848],"iteration":558,"passed_time":3.887406911,"remaining_time":3.066809388},
{"learn":[0.3437677213],"iteration":559,"passed_time":3.893824855,"remaining_time":3.059433814},
{"learn":[0.3436706518],"iteration":560,"passed_time":3.900523649,"remaining_time":3.05228143},
{"learn":[0.3435472784],"iteration":561,"passed_time":3.909273677,"remaining_time":3.046729307},
{"learn":[0.3434490042],"iteration":562,"passed_time":3.919015367,"remaining_time":3.041935551},
{"learn":[0.3433738034],"iteration":563,"passed_time":3.925628211,"remaining_time":3.034705497},
{"learn":[0.3432853533],"iteration":564,"passed_time":3.931886572,"remaining_time":3.027204706},
{"learn":[0.3431715362],"iteration":565,"passed_time":3.938659818,"remaining_time":3.020103111},
{"learn":[0.3430185312],"iteration":566,"passed_time":3.94396222,"remaining_time":3.011879437},
{"learn":[0.3429011765],"iteration":567,"passed_time":3.950050485,"remaining_time":3.004263749},
{"learn":[0.3427496621],"iteration":568,"passed_time":3.957341779,"remaining_time":2.997564687},
{"learn":[0.3426025253],"iteration":569,"passed_time":3.964608629,"remaining_time":2.990845106},
{"learn":[0.3425286922],"iteration":570,"passed_time":3.971485196,"remaining_time":2.983830384},
{"learn":[0.3424602002],"iteration":571,"passed_time":3.975550651,"remaining_time":2.974712725},
{"learn":[0.3423728769],"iteration":572,"passed_time":3.980822922,"remaining_time":2.966512021},
{"learn":[0.3422652764],"iteration":573,"passed_time":3.988976783,"remaining_time":2.960460121},
{"learn":[0.3421835096],"iteration":574,"passed_time":3.995444937,"remaining_time":2.953154954},
{"learn":[0.3421180802],"iteration":575,"passed_time":4.002592855,"remaining_time":2.946353074},
{"learn":[0.3420434692],"iteration":576,"passed_time":4.009292792,"remaining_time":2.939221579},
{"learn":[0.3419608729],"iteration":577,"passed_time":4.01469151,"remaining_time":2.931141552},
{"learn":[0.3418811538],"iteration":578,"passed_time":4.022648876,"remaining_time":2.92493122},
{"learn":[0.3417560997],"iteration":579,"passed_time":4.028870936,"remaining_time":2.917458264},
{"learn":[0.3416272535],"iteration":580,"passed_time":4.034660582,"remaining_time":2.909677769},
{"learn":[0.3414926286],"iteration":581,"passed_time":4.039529913,"remaining_time":2.901243134},
{"learn":[0.3414143141],"iteration":582,"passed_time":4.045700932,"remaining_time":2.893751781},
{"learn":[0.3412878476],"iteration":583,"passed_time":4.052681409,"remaining_time":2.886841551},
{"learn":[0.3411522704],"iteration":584,"passed_time":4.057826339,"remaining_time":2.878628941},
{"learn":[0.3410504185],"iteration":585,"passed_time":4.065643294,"remaining_time":2.872314546},
{"learn":[0.3409115604],"iteration":586,"passed_time":4.073141917,"remaining_time":2.865771059},
{"learn":[0.3408106884],"iteration":587,"passed_time":4.081031964,"remaining_time":2.859498587},
{"learn":[0.3406804103],"iteration":588,"passed_time":4.088086451,"remaining_time":2.852637575},
{"learn":[0.3405492456],"iteration":589,"passed_time":4.092933005,"remaining_time":2.84424158},
{"learn":[0.3404112807],"iteration":590,"passed_time":4.099508528,"remaining_time":2.837054125},
{"learn":[0.3403208907],"iteration":591,"passed_time":4.106546592,"remaining_time":2.830187516},
{"learn":[0.3401972233],"iteration":592,"passed_time":4.112786974,"remaining_time":2.822772847},
{"learn":[0.3400947671],"iteration":593,"passed_time":4.124190923,"remaining_time":2.818891439},
{"learn":[0.3399989205],"iteration":594,"passed_time":4.130052908,"remaining_time":2.811212484},
{"learn":[0.3398833265],"iteration":595,"passed_time":4.13602485,"remaining_time":2.80361416},
{"learn":[0.3397479659],"iteration":596,"passed_time":4.141443525,"remaining_time":2.795647807},
{"learn":[0.3396613149],"iteration":597,"passed_time":4.148068356,"remaining_time":2.788500801},
{"learn":[0.3395811693],"iteration":598,"passed_time":4.154033249,"remaining_time":2.780913744},
{"learn":[0.3394810776],"iteration":599,"passed_time":4.159948752,"remaining_time":2.773299168},
{"learn":[0.3393369289],"iteration":600,"passed_time":4.165748951,"remaining_time":2.765613696},
{"learn":[0.3392443021],"iteration":601,"passed_time":4.177191793,"remaining_time":2.761665006},
{"learn":[0.3391597423],"iteration":602,"passed_time":4.183800225,"remaining_time":2.754508606},
{"learn":[0.3390239038],"iteration":603,"passed_time":4.18970143,"remaining_time":2.746890341},
{"learn":[0.3388659704],"iteration":604,"passed_time":4.197275198,"remaining_time":2.740369758},
{"learn":[0.338688617],"iteration":605,"passed_time":4.207404554,"remaining_time":2.735507251},
{"learn":[0.3385579086],"iteration":606,"passed_time":4.213957196,"remaining_time":2.72831166},
{"learn":[0.3384744963],"iteration":607,"passed_time":4.220998784,"remaining_time":2.721433427},
{"learn":[0.3383251495],"iteration":608,"passed_time":4.227905769,"remaining_time":2.714468236},
{"learn":[0.33820,
{"learn":[0.3375451846],"iteration":609,"passed_time":4.232356043,"remaining,
{"learn":[0.3381110874],"iteration":610,"passed_time":4.2414991,"remaining_time":2.700397954},
{"learn":[0.3380129757],"iteration":611,"passed_time":4.252163028,"remaining_time":2.695815776},
{"learn":[0.3379317205],"iteration":612,"passed_time":4.26207958,"remaining_time":2.690741921},
{"learn":[0.3378674317],"iteration":613,"passed_time":4.269988559,"remaining_time":2.684390202},
{"learn":[0.3377737002],"iteration":614,"passed_time":4.27457741,"remaining_time":2.675954964},
{"learn":[0.3377122469],"iteration":615,"passed_time":4.282215811,"remaining_time":2.669433233},
{"learn":[0.3375772388],"iteration":616,"passed_time":4.292410412,"remaining_time":2.664494632},
{"learn":[0.3374560149],"iteration":617,"passed_time":4.301868174,"remaining_time":2.659083564},
{"learn":[0.3373565962],"iteration":618,"passed_time":4.311070061,"remaining_time":2.653501927},
{"learn":[0.3372111142],"iteration":619,"passed_time":4.318943291,"remaining_time":2.647094275},
{"learn":[0.3371269302],"iteration":620,"passed_time":4.329151561,"remaining_time":2.642106991},
{"learn":[0.3370388006],"iteration":621,"passed_time":4.334918746,"remaining_time":2.634403997},
{"learn":[0.336980088],"iteration":622,"passed_time":4.342878698,"remaining_time":2.62803414},
{"learn":[0.3369038719],"iteration":623,"passed_time":4.349167884,"remaining_time":2.620652443},
{"learn":[0.3367983961],"iteration":624,"passed_time":4.356877245,"remaining_time":2.614126347},
{"learn":[0.3367216378],"iteration":625,"passed_time":4.367730902,"remaining_time":2.609475012},
{"learn":[0.3365788463],"iteration":626,"passed_time":4.377299969,"remaining_time":2.604039695},
{"learn":[0.336527784],"iteration":627,"passed_time":4.394537014,"remaining_time":2.60313339},
{"learn":[0.336467246],"iteration":628,"passed_time":4.40279311,"remaining_time":2.596877971},
{"learn":[0.3363761969],"iteration":629,"passed_time":4.407685461,"remaining_time":2.588640668},
{"learn":[0.336265337],"iteration":630,"passed_time":4.411795034,"remaining_time":2.579956209},
{"learn":[0.336137991],"iteration":631,"passed_time":4.415872235,"remaining_time":2.571267377},
{"learn":[0.3360794331],"iteration":632,"passed_time":4.421381229,"remaining_time":2.56342324},
{"learn":[0.3360000272],"iteration":633,"passed_time":4.426808574,"remaining_time":2.555539334},
{"learn":[0.3359052074],"iteration":634,"passed_time":4.430895616,"remaining_time":2.546892756},
{"learn":[0.3357794467],"iteration":635,"passed_time":4.43558083,"remaining_time":2.538602865},
{"learn":[0.3356629475],"iteration":636,"passed_time":4.440703112,"remaining_time":2.530573359},
{"learn":[0.3355356686],"iteration":637,"passed_time":4.444646186,"remaining_time":2.521883886},
{"learn":[0.3354520342],"iteration":638,"passed_time":4.449282954,"remaining_time":2.513601168},
{"learn":[0.3353626218],"iteration":639,"passed_time":4.454974302,"remaining_time":2.505923045},
{"learn":[0.3352660451],"iteration":640,"passed_time":4.459082632,"remaining_time":2.497364532},
{"learn":[0.3351438648],"iteration":641,"passed_time":4.463428205,"remaining_time":2.488952176},
{"learn":[0.3350102928],"iteration":642,"passed_time":4.468857525,"remaining_time":2.481154178},
{"learn":[0.3349472272],"iteration":643,"passed_time":4.472481573,"remaining_time":2.47236559},
{"learn":[0.33484517,
{"learn":[0.33347776],"iteration":644,"passed_time":4.479581948,"remainin,
{"learn":[0.334734,
{"learn":[0.3333870195],"iteration":645,"passed_time":4.490073338,"remaining_time":2.460504585},
{"learn":[0.3332210874],"iteration":646,"passed_time":4.494959044,"remaining_time":2.452427423},
{"learn":[0.3331239263],"iteration":647,"passed_time":4.505829184,"remaining_time":2.447610915},
{"learn":[0.3330284283],"iteration":648,"passed_time":4.515860119,"remaining_time":2.442321882},
{"learn":[0.3329229899],"iteration":649,"passed_time":4.521948988,"remaining_time":2.434895609},
{"learn":[0.3328609104],"iteration":650,"passed_time":4.529094312,"remaining_time":2.428039808},
{"learn":[0.3327749274],"iteration":651,"passed_time":4.53585427,"remaining_time":2.420977432},
{"learn":[0.3327273912],"iteration":652,"passed_time":4.546104812,"remaining_time":2.415770857},
{"learn":[0.3325807985],"iteration":653,"passed_time":4.556348241,"remaining_time":2.410545094},
{"learn":[0.3324853392],"iteration":654,"passed_time":4.56507155,"remaining_time":2.404503336},
{"learn":[0.3323422663],"iteration":655,"passed_time":4.57597833,"remaining_time":2.399598392},
{"learn":[0.3322218592],"iteration":656,"passed_time":4.587204195,"remaining_time":2.394841764},
{"learn":[0.3321209462],"iteration":657,"passed_time":4.593542184,"remaining_time":2.387524965},
{"learn":[0.3319917203],"iteration":658,"passed_time":4.599039142,"remaining_time":2.379775944},
{"learn":[0.3317915961],"iteration":659,"passed_time":4.609958622,"remaining_time":2.374827169},
{"learn":[0.3317211233],"iteration":660,"passed_time":4.61461909,"remaining_time":2.366650335},
{"learn":[0.3316164585],"iteration":661,"passed_time":4.620766814,"remaining_time":2.359243479},
{"learn":[0.3315699279],"iteration":662,"passed_time":4.627731882,"remaining_time":2.352255874},
{"learn":[0.3314445699],"iteration":663,"passed_time":4.63982152,"remaining_time":2.347861492},
{"learn":[0.3313289976],"iteration":664,"passed_time":4.645804691,"remaining_time":2.340367776},
{"learn":[0.3312169838],"iteration":665,"passed_time":4.650350571,"remaining_time":2.332157794},
{"learn":[0.3311170377],"iteration":666,"passed_time":4.654233872,"remaining_time":2.323628005},
{"learn":[0.3310912003],"iteration":667,"passed_time":4.658692616,"remaining_time":2.315398127},
{"learn":[0.3310230869],"iteration":668,"passed_time":4.665227016,"remaining_time":2.308206491},
{"learn":[0.3309009392],"iteration":669,"passed_time":4.670735505,"remaining_time":2.300511517},
{"learn":[0.330833174],"iteration":670,"passed_time":4.675054494,"remaining_time":2.292239834},
{"learn":[0.3306920737],"iteration":671,"passed_time":4.679058784,"remaining_time":2.283826311},
{"learn":[0.3306012559],"iteration":672,"passed_time":4.682638438,"remaining_time":2.275219568},
{"learn":[0.330493342],"iteration":673,"passed_time":4.686950152,"remaining_time":2.266981824},
{"learn":[0.3304167193],"iteration":674,"passed_time":4.692722353,"remaining_time":2.259458911},
{"learn":[0.3303259788],"iteration":675,"passed_time":4.697468535,"remaining_time":2.251449416},
{"learn":[0.3302755416],"iteration":676,"passed_time":4.70094383,"remaining_time":2.242843216},
{"learn":[0.3302027868],"iteration":677,"passed_time":4.70525325,"remaining_time":2.234648299},
{"learn":[0.3301485591],"iteration":678,"passed_time":4.709571057,"remaining_time":2.226468791},
{"learn":[0.3300879881],"iteration":679,"passed_time":4.712896197,"remaining_time":2.217833504},
{"learn":[0.3299694762],"iteration":680,"passed_time":4.717223812,"remaining_time":2.209683401},
{"learn":[0.3299255371],"iteration":681,"passed_time":4.721556587,"remaining_time":2.201546913},
{"learn":[0.329794532],"iteration":682,"passed_time":4.725397357,"remaining_time":2.193193209},
{"learn":[0.3297066924],"iteration":683,"passed_time":4.728673944,"remaining_time":2.184592056},
{"learn":[0.3296052766],"iteration":684,"passed_time":4.73317626,"remaining_time":2.176570105},
{"learn":[0.3295022363],"iteration":685,"passed_time":4.73647441,"remaining_time":2.168007237},
{"learn":[0.3293727783],"iteration":686,"passed_time":4.740709599,"remaining_time":2.159886615},
{"learn":[0.329246608],"iteration":687,"passed_time":4.745494843,"remaini,
{"learn":[0.3306287,
{"learn":[0.3291285603],"iteration":688,"passed_time":4.75026505,"remainin,
{"learn":[0.330485,
{"learn":[0.3290520536],"iteration":689,"passed_time":4.754003886,"remaini,
{"learn":[0.33035517],"iteration":690,"passed_time":4.761761087,"remaining_time":2.129354813},
{"learn":[0.3302025647],"iteration":691,"passed_time":4.768997616,"remaining_time":2.122617436},
{"learn":[0.3301275368],"iteration":692,"passed_time":4.781636111,"remaining_time":2.118271697},
{"learn":[0.3300468389],"iteration":693,"passed_time":4.789522781,"remaining_time":2.111806875},
{"learn":[0.3300069728],"iteration":694,"passed_time":4.795972155,"remaining_time":2.104707205},
{"learn":[0.3298757581],"iteration":695,"passed_time":4.808921754,"remaining_time":2.100448582},
{"learn":[0.3298081705],"iteration":696,"passed_time":4.820460695,"remaining_time":2.09555178},
{"learn":[0.329751176],"iteration":697,"passed_time":4.825839101,"remaining_time":2.087970499},
{"learn":[0.3296625918],"iteration":698,"passed_time":4.833028069,"remaining_time":2.081175177},
{"learn":[0.3296224414],"iteration":699,"passed_time":4.842210336,"remaining_time":2.075233001},
{"learn":[0.3294529848],"iteration":700,"passed_time":4.86635199,"remaining_time":2.075662261},
{"learn":[0.3293883942],"iteration":701,"passed_time":4.885383951,"remaining_time":2.073852446},
{"learn":[0.3292735426],"iteration":702,"passed_time":4.904745591,"remaining_time":2.072132917},
{"learn":[0.3291408472],"iteration":703,"passed_time":4.921355419,"remaining_time":2.069206256},
{"learn":[0.3290159528],"iteration":704,"passed_time":4.933922331,"remaining_time":2.064549061},
{"learn":[0.3289864996],"iteration":705,"passed_time":4.946588013,"remaining_time":2.059910589},
{"learn":[0.3288981347],"iteration":706,"passed_time":4.964866726,"remaining_time":2.057575602},
{"learn":[0.3288275175],"iteration":707,"passed_time":4.980164024,"remaining_time":2.053965953},
{"learn":[0.3287440156],"iteration":708,"passed_time":4.987145493,"remaining_time":2.046910209},
{"learn":[0.3286053118],"iteration":709,"passed_time":4.993114635,"remaining_time":2.039441189},
{"learn":[0.3284896267],"iteration":710,"passed_time":5.006909291,"remaining_time":2.035157222},
{"learn":[0.3283734916],"iteration":711,"passed_time":5.016936499,"remaining_time":2.029322629},
{"learn":[0.3283051019],"iteration":712,"passed_time":5.030882593,"remaining_time":2.025053723},
{"learn":[0.3281910993],"iteration":713,"passed_time":5.046409137,"remaining_time":2.021390775},
{"learn":[0.3281464472],"iteration":714,"passed_time":5.054732943,"remaining_time":2.014823621},
{"learn":[0.3280357284],"iteration":715,"passed_time":5.06317205,"remaining_time":2.008297294},
{"learn":[0.3278494988],"iteration":716,"passed_time":5.070053515,"remaining_time":2.00115083},
{"learn":[0.327700247],"iteration":717,"passed_time":5.078576245,"remaining_time":1.994649723},
{"learn":[0.3275337442],"iteration":718,"passed_time":5.084609318,"remaining_time":1.987169984},
{"learn":[0.3274066648],"iteration":719,"passed_time":5.093691018,"remaining_time":1.98087984},
{"learn":[0.3273534734],"iteration":720,"passed_time":5.100347416,"remaining_time":1.973643452},
{"learn":[0.3272296687],"iteration":721,"passed_time":5.113015256,"remaining_time":1.968723326},
{"learn":[0.3270950714],"iteration":722,"passed_time":5.121685143,"remaining_time":1.962250048},
{"learn":[0.3269758955],"iteration":723,"passed_time":5.13103215,"remaining_time":1.956028831},
{"learn":[0.3269084548],"iteration":724,"passed_time":5.140188259,"remaining_time":1.949726581},
{"learn":[0.3267942952],"iteration":725,"passed_time":5.151897586,"remaining_time":1.944380081},
{"learn":[0.3267061512],"iteration":726,"passed_time":5.167514691,"remaining_time":1.940483508},
{"learn":[0.3266012462],"iteration":727,"passed_time":5.175387797,"remaining_time":1.933661375},
{"learn":[0.3265196695],"iteration":728,"passed_time":5.180296696,"remaining_time":1.925734437},
{"learn":[0.3263985823],"iteration":729,"passed_time":5.185468369,"remaining_time":1.917912958},
{"learn":[0.3263052428],"iteration":730,"passed_time":5.189822923,"remaining_time":1.909798039},
{"learn":[0.326234601],"iteration":731,"passed_time":5.193815406,"remaining_time":1.901560832},
{"learn":[0.3260925656],"iteration":732,"passed_time":5.199098823,"remaining_time":1.893805438},
{"learn":[0.3259702805],"iteration":733,"passed_time":5.207805274,"remaining_time":1.887297279},
{"learn":[0.3258227136],"iteration":734,"passed_time":5.211270081,"remaining_time":1.878893295},
{"learn":[0.3257120505],"iteration":735,"passed_time":5.217339094,"remaining_time":1.871436849},
{"learn":[0.3255473491],"iteration":736,"passed_time":5.227177427,"remaining_time":1.865329258},
{"learn":[0.325506166],"iteration":737,"passed_time":5.233573302,"remaining_time":1.857989438},
{"learn":[0.3253654381],"iteration":738,"passed_time":5.247585052,"remaining_time":1.853341947},
{"learn":[0.3252990771],"iteration":739,"passed_time":5.252603607,"remaining_time":1.845509375},
{"learn":[0.3251218268],"iteration":740,"passed_time":5.256904271,"remaining_time":1.837433477},
{"learn":[0.3250536606],"iteration":741,"passed_time":5.266757427,"remaining_time":1.831298405},
{"learn":[0.3249949396],"iteration":742,"passed_time":5.272503646,"remaining_time":1.823732755},
{"learn":[0.324852168],"iteration":743,"passed_time":5.27778265,"remaining_time":1.816011234},
{"learn":[0.3247308637],"iteration":744,"passed_time":5.282881512,"remaining_time":1.808234611},
{"learn":[0.3246295531],"iteration":745,"passed_time":5.288026302,"remaining_time":1.800480805},
{"learn":[0.3245065678],"iteration":746,"passed_time":5.291912681,"remaining_time":1.792307775},
{"learn":[0.3244361254],"iteration":747,"passed_time":5.297246158,"remaining_time":1.784633732},
{"learn":[0.3243923575],"iteration":748,"passed_time":5.307596188,"remaining_time":1.778647054},
{"learn":[0.3242826386],"iteration":749,"passed_time":5.314791443,"remaining_time":1.771597148},
{"learn":[0.3241195272],"iteration":750,"passed_time":5.325733225,"remaining_time":1.765789045},
{"learn":[0.3240123093],"iteration":751,"passed_time":5.333880902,"remaining_time":1.759045829},
{"learn":[0.3239848452],"iteration":752,"passed_time":5.340421576,"remaining_time":1.751771752},
{"learn":[0.3238279695],"iteration":753,"passed_time":5.349057051,"remaining_time":1.74518307},
{"learn":[0.3237239451],"iteration":754,"passed_time":5.353805896,"remaining_time":1.737327741},
{"learn":[0.3236385467],"iteration":755,"passed_time":5.357855847,"remaining_time":1.729255062},
{"learn":[0.3235286042],"iteration":756,"passed_time":5.366033871,"remaining_time":1.722518138},
{"learn":[0.3234618666],"iteration":757,"passed_time":5.373587875,"remaining_time":1.715578187},
{"learn":[0.3232964039],"iteration":758,"passed_time":5.381824499,"remaining_time":1.708853365},
{"learn":[0.3232274939],"iteration":759,"passed_time":5.388576149,"remaining_time":1.701655626},
{"learn":[0.3230629345],"iteration":760,"passed_time":5.394219051,"remaining_time":1.694110845},
{"learn":[0.3228972669],"iteration":761,"passed_time":5.401126125,"remaining_time":1.686965903},
{"learn":[0.3227498268],"iteration":762,"passed_time":5.415511217,"remaining_time":1.682144375},
{"learn":[0.3226856419],"iteration":763,"passed_time":5.424876454,"remaining_time":1.675747177},
{"learn":[0.3226255013],"iteration":764,"passed_time":5.431354952,"remaining_time":1.668455443},
{"learn":[0.3225009087],"iteration":765,"passed_time":5.439434167,"remaining_time":1.661654824},
{"learn":[0.3223942258],"iteration":766,"passed_time":5.44342181,"remaining_time":1.653607929},
{"learn":[0.3222820548],"iteration":767,"passed_time":5.448088063,"remaining_time":1.645776602},
{"learn":[0.3222129107],"iteration":768,"passed_time":5.458769566,"remaining_time":1.639760429},
{"learn":[0.3220743706],"iteration":769,"passed_time":5.464697851,"remaining_time":1.632312345},
{"learn":[0.3219145481],"iteration":770,"passed_time":5.471383667,"remaining_time":1.625093203},
{"learn":[0.3218748224],"iteration":771,"passed_time":5.47650754,"remaining_time":1.617414144},
{"learn":[0.3217961508],"iteration":772,"passed_time":5.482071387,"remaining_time":1.609870899},
{"learn":[0.3217284579],"iteration":773,"passed_time":5.488460718,"remaining_time":1.602573801},
{"learn":[0.3216233931],"iteration":774,"passed_time":5.494069984,"remaining_time":1.595052576},
{"learn":[0.3215230911],"iteration":775,"passed_time":5.497749405,"remaining_time":1.58697921},
{"learn":[0.3214206303],"iteration":776,"passed_time":5.501661711,"remaining_time":1.578983992},
{"learn":[0.3212893995],"iteration":777,"passed_time":5.507420298,"remaining_time":1.5715261},
{"learn":[0.321183049],"iteration":778,"passed_time":5.512830952,"remaining_time":1.563973865},
{"learn":[0.3210514756],"iteration":779,"passed_time":5.519305578,"remaining_time":1.556727214},
{"learn":[0.3209592047],"iteration":780,"passed_time":5.524398647,"remaining_time":1.549095139},
{"learn":[0.3209215371],"iteration":781,"passed_time":5.530325195,"remaining_time":1.541701909},
{"learn":[0.3208570504],"iteration":782,"passed_time":5.535840083,"remaining_time":1.534198337},
{"learn":[0.3207985763],"iteration":783,"passed_time":5.540395561,"remaining_time":1.526435512},
{"learn":[0.3206636246],"iteration":784,"passed_time":5.54658967,"remaining_time":1.519129655},
{"learn":[0.3205815978],"iteration":785,"passed_time":5.550198245,"remaining_time":1.511122677},
{"learn":[0.320450702],"iteration":786,"passed_time":5.55371334,"remaining_time":1.503101578},
{"learn":[0.3203425035],"iteration":787,"passed_time":5.560841628,"remaining_time":1.496063991},
{"learn":[0.3202149271],"iteration":788,"passed_time":5.566493007,"remaining_time":1.48863121},
{"learn":[0.3201023992],"iteration":789,"passed_time":5.575327041,"remaining_time":1.48204896},
{"learn":[0.3199737307],"iteration":790,"passed_time":5.578849796,"remaining_time":1.474057658},
{"learn":[0.3198464424],"iteration":791,"passed_time":5.583288496,"remaining_time":1.466318191},
{"learn":[0.3197217524],"iteration":792,"passed_time":5.589167027,"remaining_time":1.458962894},
{"learn":[0.3196819038],"iteration":793,"passed_time":5.594689813,"remaining_time":1.45151902},
{"learn":[0.3195905578],"iteration":794,"passed_time":5.599840085,"remaining_time":1.443983921},
{"learn":[0.3195395034],"iteration":795,"passed_time":5.610125917,"remaining_time":1.437770964},
{"learn":[0.31942511],"iteration":796,"passed_time":5.616781764,"remaining_time":1.43062321},
{"learn":[0.3193180584],"iteration":797,"passed_time":5.623811092,"remaining_time":1.423571229},
{"learn":[0.3191787033],"iteration":798,"passed_time":5.627745848,"remaining_time":1.41574082},
{"learn":[0.319143067],"iteration":799,"passed_time":5.631662554,"remaining_time":1.407915639},
{"learn":[0.3190892573],"iteration":800,"passed_time":5.637659047,"remaining_time":1.400616917},
{"learn":[0.3188767099],"iteration":801,"passed_time":5.644582558,"remaining_time":1.393550307},
{"learn":[0.3187568917],"iteration":802,"passed_time":5.65041559,"remaining_time":1.386216527},
{"learn":[0.318682795],"iteration":803,"passed_time":5.65399951,"remaining_time":1.378338189},
{"learn":[0.3185653799],"iteration":804,"passed_time":5.658493716,"remaining_time":1.370691024},
{"learn":[0.3185275447],"iteration":805,"passed_time":5.664894743,"remaining_time":1.363510645},
{"learn":[0.3184039775],"iteration":806,"passed_time":5.670465384,"remaining_time":1.356133605},
{"learn":[0.3183421314],"iteration":807,"passed_time":5.682554562,"remaining_time":1.350309995},
{"learn":[0.3182555479],"iteration":808,"passed_time":5.68961264,"remaining_time":1.343283083},
{"learn":[0.3180918005],"iteration":809,"passed_time":5.697554251,"remaining_time":1.336463343},
{"learn":[0.3180242179],"iteration":810,"passed_time":5.703513796,"remaining_time":1.329178924},
{"learn":[0.3179086528],"iteration":811,"passed_time":5.708663076,"remaining_time":1.32171017},
{"learn":[0.3178503168],"iteration":812,"passed_time":5.715557864,"remaining_time":1.314648611},
{"learn":[0.3177202226],"iteration":813,"passed_time":5.721245052,"remaining_time":1.307311523},
{"learn":[0.3175948067],"iteration":814,"passed_time":5.727464207,"remaining_time":1.300099237},
{"learn":[0.3175385125],"iteration":815,"passed_time":5.731460699,"remaining_time":1.292388197},
{"learn":[0.3174750575],"iteration":816,"passed_time":5.736066117,"remaining_time":1.284822643},
{"learn":[0.3173680577],"iteration":817,"passed_time":5.740151479,"remaining_time":1.277148618},
{"learn":[0.3172890548],"iteration":818,"passed_time":5.745191505,"remaining_time":1.269694337},
{"learn":[0.3171873881],"iteration":819,"passed_time":5.751369892,"remaining_time":1.26249583},
{"learn":[0.3171054632],"iteration":820,"passed_time":5.756303185,"remaining_time":1.255028344},
{"learn":[0.3170379765],"iteration":821,"passed_time":5.760615646,"remaining_time":1.247432585},
{"learn":[0.3169720784],"iteration":822,"passed_time":5.763827504,"remaining_time":1.239608102},
{"learn":[0.3169039848],"iteration":823,"passed_time":5.768438244,"remaining_time":1.232093606},
{"learn":[0.3167898147],"iteration":824,"passed_time":5.773251902,"remaining_time":1.224629191},
{"learn":[0.3167530832],"iteration":825,"passed_time":5.777072175,"remaining_time":1.216961935},
{"learn":[0.3166496069],"iteration":826,"passed_time":5.780738197,"remaining_time":1.209271715},
{"learn":[0.3165481136],"iteration":827,"passed_time":5.787030023,"remaining_time":1.202136671},
{"learn":[0.3164892418],"iteration":828,"passed_time":5.791564334,"remaining_time":1.194641135},
{"learn":[0.3163776982],"iteration":829,"passed_time":5.796449209,"remaining_time":1.187224537},
{"learn":[0.3162782289],"iteration":830,"passed_time":5.803033444,"remaining_time":1.180159629},
{"learn":[0.3161755798],"iteration":831,"passed_time":5.807292738,"remaining_time":1.172626418},
{"learn":[0.3160985688],"iteration":832,"passed_time":5.810465219,"remaining_time":1.164883183},
{"learn":[0.3160659099],"iteration":833,"passed_time":5.816570502,"remaining_time":1.157734656},
{"learn":[0.3159870362],"iteration":834,"passed_time":5.820942611,"remaining_time":1.150246145},
{"learn":[0.3158843085],"iteration":835,"passed_time":5.825839476,"remaining_time":1.142868031},
{"learn":[0.3158092513],"iteration":836,"passed_time":5.832975187,"remaining_time":1.135931846},
{"learn":[0.3157094644],"iteration":837,"passed_time":5.837038557,"remaining_time":1.128401248},
{"learn":[0.3155958545],"iteration":838,"passed_time":5.841604477,"remaining_time":1.120975353},
{"learn":[0.3154751285],"iteration":839,"passed_time":5.847903619,"remaining_time":1.113886404},
{"learn":[0.3153828108],"iteration":840,"passed_time":5.853022762,"remaining_time":1.106576242},
{"learn":[0.3153300897],"iteration":841,"passed_time":5.861029611,"remaining_time":1.099813157},
{"learn":[0.3152876733],"iteration":842,"passed_time":5.868802178,"remaining_time":1.09300349},
{"learn":[0.3152015468],"iteration":843,"passed_time":5.880243273,"remaining_time":1.08686961},
{"learn":[0.3151080526],"iteration":844,"passed_time":5.885737506,"remaining_time":1.079632324},
{"learn":[0.314932781],"iteration":845,"passed_time":5.890342693,"remaining_time":1.072237322},
{"learn":[0.3148119574],"iteration":846,"passed_time":5.897063072,"remaining_time":1.065230992},
{"learn":[0.3147138185],"iteration":847,"passed_time":5.904012344,"remaining_time":1.058266364},
{"learn":[0.3145759616],"iteration":848,"passed_time":5.914038181,"remaining_time":1.051848958},
{"learn":[0.3144832596],"iteration":849,"passed_time":5.919853784,"remaining_time":1.044680079},
{"learn":[0.3144081402],"iteration":850,"passed_time":5.931905849,"remaining_time":1.038606312},
{"learn":[0.3142744711],"iteration":851,"passed_time":5.939342361,"remaining_time":1.031716748},
{"learn":[0.3142091484],"iteration":852,"passed_time":5.950088647,"remaining_time":1.025396285},
{"learn":[0.3141115012],"iteration":853,"passed_time":5.956502742,"remaining_time":1.018324825},
{"learn":[0.3139825793],"iteration":854,"passed_time":5.963576536,"remaining_time":1.011366781},
{"learn":[0.3138790211],"iteration":855,"passed_time":5.971390004,"remaining_time":1.004532898},
{"learn":[0.3138025715],"iteration":856,"passed_time":5.977280572,"remaining_time":0.9973758713},
{"learn":[0.3137163222],"iteration":857,"passed_time":5.984649166,"remaining_time":0.9904664122},
{"learn":[0.3136403468],"iteration":858,"passed_time":5.990197087,"remaining_time":0.9832570307},
{"learn":[0.3135272702],"iteration":859,"passed_time":5.9970034,"remaining_time":0.9762563674},
{"learn":[0.3134270323],"iteration":860,"passed_time":6.002627085,"remaining_time":0.969065232},
{"learn":[0.313331633],"iteration":861,"passed_time":6.01078154,"remaining_time":0.9622828915},
{"learn":[0.3132529502],"iteration":862,"passed_time":6.017646271,"remaining_time":0.9552926293},
{"learn":[0.3131333074],"iteration":863,"passed_time":6.026139818,"remaining_time":0.9485590455},
{"learn":[0.3130135576],"iteration":864,"passed_time":6.033534444,"remaining_time":0.9416498843},
{"learn":[0.3129166193],"iteration":865,"passed_time":6.042490127,"remaining_time":0.9349811512},
{"learn":[0.3128359085],"iteration":866,"passed_time":6.049732777,"remaining_time":0.9280443591},
{"learn":[0.3127296698],"iteration":867,"passed_time":6.056747219,"remaining_time":0.9210721577},
{"learn":[0.3126178682],"iteration":868,"passed_time":6.062982869,"remaining_time":0.9139824579},
{"learn":[0.3125819384],"iteration":869,"passed_time":6.07127726,"remaining_time":0.9072023492},
{"learn":[0.3124567937],"iteration":870,"passed_time":6.077577654,"remaining_time":0.9001234413},
{"learn":[0.3123645686],"iteration":871,"passed_time":6.089537817,"remaining_time":0.8938771107},
{"learn":[0.3122599664],"iteration":872,"passed_time":6.095311266,"remaining_time":0.8867176756},
{"learn":[0.312178407],"iteration":873,"passed_time":6.102658243,"remaining_time":0.8797882594},
{"learn":[0.3120952403],"iteration":874,"passed_time":6.111342422,"remaining_time":0.8730489174},
{"learn":[0.3119318184],"iteration":875,"passed_time":6.117771978,"remaining_time":0.8659859878},
{"learn":[0.3118179344],"iteration":876,"passed_time":6.127116844,"remaining_time":0.8593333772},
{"learn":[0.3117202791],"iteration":877,"passed_time":6.135340906,"remaining_time":0.8525188959},
{"learn":[0.3116213078],"iteration":878,"passed_time":6.145751367,"remaining_time":0.8460021791},
{"learn":[0.3114968465],"iteration":879,"passed_time":6.152656748,"remaining_time":0.8389986475},
{"learn":[0.3114039973],"iteration":880,"passed_time":6.160119541,"remaining_time":0.8320706303},
{"learn":[0.3112982617],"iteration":881,"passed_time":6.170208277,"remaining_time":0.8254927174},
{"learn":[0.3112496271],"iteration":882,"passed_time":6.178058717,"remaining_time":0.8186102716},
{"learn":[0.3111585884],"iteration":883,"passed_time":6.183772465,"remaining_time":0.8114452556},
{"learn":[0.3110454466],"iteration":884,"passed_time":6.195722922,"remaining_time":0.805093939},
{"learn":[0.3109847357],"iteration":885,"passed_time":6.205685112,"remaining_time":0.7984741566},
{"learn":[0.3108385433],"iteration":886,"passed_time":6.211214421,"remaining_time":0.7912821078},
{"learn":[0.3107710158],"iteration":887,"passed_time":6.217390921,"remaining_time":0.7841754315},
{"learn":[0.3106708525],"iteration":888,"passed_time":6.229559955,"remaining_time":0.777819072},
{"learn":[0.3105808735],"iteration":889,"passed_time":6.236267389,"remaining_time":0.7707746211},
{"learn":[0.3104758046],"iteration":890,"passed_time":6.242324385,"remaining_time":0.7636513558},
{"learn":[0.3104412442],"iteration":891,"passed_time":6.249641276,"remaining_time":0.7566830244},
{"learn":[0.3103337474],"iteration":892,"passed_time":6.260868448,"remaining_time":0.7501824456},
{"learn":[0.3102440311],"iteration":893,"passed_time":6.266847962,"remaining_time":0.7430490873},
{"learn":[0.310109191],"iteration":894,"passed_time":6.27463424,"remaining_time":0.736130274},
{"learn":[0.3100250132],"iteration":895,"passed_time":6.284097946,"remaining_time":0.7294042258},
{"learn":[0.309930607],"iteration":896,"passed_time":6.289024884,"remaining_time":0.7221511293},
{"learn":[0.3098131889],"iteration":897,"passed_time":6.296481544,"remaining_time":0.715190554},
{"learn":[0.3097162882],"iteration":898,"passed_time":6.302265666,"remaining_time":0.7080409703},
{"learn":[0.3096176305],"iteration":899,"passed_time":6.308030206,"remaining_time":0.7008922451},
{"learn":[0.30959261],"iteration":900,"passed_time":6.314489832,"remaining_time":0.6938229671},
{"learn":[0.3095205801],"iteration":901,"passed_time":6.320293177,"remaining_time":0.6866837377},
{"learn":[0.30941036],"iteration":902,"passed_time":6.338516983,"remaining_time":0.6808816693},
{"learn":[0.3092857093],"iteration":903,"passed_time":6.371048669,"remaining_time":0.67657154},
{"learn":[0.3091777705],"iteration":904,"passed_time":6.380289107,"remaining_time":0.6697541052},
{"learn":[0.3090718653],"iteration":905,"passed_time":6.386425008,"remaining_time":0.6626092171},
{"learn":[0.3089753457],"iteration":906,"passed_time":6.391815551,"remaining_time":0.6553901281},
{"learn":[0.3088859573],"iteration":907,"passed_time":6.394966043,"remaining_time":0.6479481013},
{"learn":[0.3087306082],"iteration":908,"passed_time":6.399079173,"remaining_time":0.6406118864},
{"learn":[0.3086901976],"iteration":909,"passed_time":6.402761532,"remaining_time":0.6332401515},
{"learn":[0.3085925106],"iteration":910,"passed_time":6.405880676,"remaining_time":0.625821493},
{"learn":[0.3085001118],"iteration":911,"passed_time":6.40999108,"remaining_time":0.6185079112},
{"learn":[0.3084346999],"iteration":912,"passed_time":6.418030079,"remaining_time":0.6115757031},
{"learn":[0.3083806926],"iteration":913,"passed_time":6.423412381,"remaining_time":0.6043910993},
{"learn":[0.3082958951],"iteration":914,"passed_time":6.429197129,"remaining_time":0.5972478207},
{"learn":[0.3082171157],"iteration":915,"passed_time":6.433954303,"remaining_time":0.5900132767},
{"learn":[0.308097597],"iteration":916,"passed_time":6.438744659,"remaining_time":0.5827871393},
{"learn":[0.3079713829],"iteration":917,"passed_time":6.441831992,"remaining_time":0.5754141867},
{"learn":[0.307902584],"iteration":918,"passed_time":6.446497724,"remaining_time":0.5681896797},
{"learn":[0.3077999946],"iteration":919,"passed_time":6.452006779,"remaining_time":0.5610440677},
{"learn":[0.3077236919],"iteration":920,"passed_time":6.456090715,"remaining_time":0.5537797681},
{"learn":[0.3076401742],"iteration":921,"passed_time":6.4594415,"remaining_time":0.5464603438},
{"learn":[0.3075780239],"iteration":922,"passed_time":6.464536269,"remaining_time":0.5392950083},
{"learn":[0.3074959572],"iteration":923,"passed_time":6.469388652,"remaining_time":0.5321142181},
{"learn":[0.3073623803],"iteration":924,"passed_time":6.473950194,"remaining_time":0.5249148806},
{"learn":[0.3072824966],"iteration":925,"passed_time":6.477561705,"remaining_time":0.5176453198},
{"learn":[0.30715228],"iteration":926,"passed_time":6.48098029,"remaining_time":0.5103684587},
{"learn":[0.3070920976],"iteration":927,"passed_time":6.485448285,"remaining_time":0.5031813324},
{"learn":[0.3069869869],"iteration":928,"passed_time":6.489316684,"remaining_time":0.4959542353},
{"learn":[0.3068994222],"iteration":929,"passed_time":6.492827492,"remaining_time":0.4887074457},
{"learn":[0.3068045866],"iteration":930,"passed_time":6.497037036,"remaining_time":0.4815204678},
{"learn":[0.3066888322],"iteration":931,"passed_time":6.500256331,"remaining_time":0.4742676293},
{"learn":[0.3065823273],"iteration":932,"passed_time":6.504066802,"remaining_time":0.4670658904},
{"learn":[0.3065014128],"iteration":933,"passed_time":6.507903361,"remaining_time":0.4598732568},
{"learn":[0.3064073926],"iteration":934,"passed_time":6.511225082,"remaining_time":0.4526520111},
{"learn":[0.3063338763],"iteration":935,"passed_time":6.515118997,"remaining_time":0.445478222},
{"learn":[0.306238451],"iteration":936,"passed_time":6.519128688,"remaining_time":0.4383192181},
{"learn":[0.3062050167],"iteration":937,"passed_time":6.52235131,"remaining_time":0.4311149053},
{"learn":[0.3061519207],"iteration":938,"passed_time":6.525861858,"remaining_time":0.4239377778},
{"learn":[0.306054568],"iteration":939,"passed_time":6.529048682,"remaining_time":0.4167477882},
{"learn":[0.3059052111],"iteration":940,"passed_time":6.532425375,"remaining_time":0.4095782116},
{"learn":[0.3058325622],"iteration":941,"passed_time":6.535734648,"remaining_time":0.4024125367},
{"learn":[0.3057571021],"iteration":942,"passed_time":6.53881234,"remaining_time":0.3952410428},
{"learn":[0.3056541153],"iteration":943,"passed_time":6.542409178,"remaining_time":0.388109019},
{"learn":[0.3055566578],"iteration":944,"passed_time":6.545585708,"remaining_time":0.3809600148},
{"learn":[0.3054153361],"iteration":945,"passed_time":6.548747878,"remaining_time":0.3738185892},
{"learn":[0.3052592654],"iteration":946,"passed_time":6.552041848,"remaining_time":0.366692944},
{"learn":[0.3051936313],"iteration":947,"passed_time":6.555287761,"remaining_time":0.3595727464},
{"learn":[0.30509515],"iteration":948,"passed_time":6.558838118,"remaining_time":0.3524770748},
{"learn":[0.3050427832],"iteration":949,"passed_time":6.561716268,"remaining_time":0.3453534878},
{"learn":[0.304957978],"iteration":950,"passed_time":6.565173259,"remaining_time":0.3382686537},
{"learn":[0.3048440853],"iteration":951,"passed_time":6.567969749,"remaining_time":0.3311581386},
{"learn":[0.3047798109],"iteration":952,"passed_time":6.571340568,"remaining_time":0.3240850018},
{"learn":[0.3047095774],"iteration":953,"passed_time":6.574638697,"remaining_time":0.3170161217},
{"learn":[0.3046563676],"iteration":954,"passed_time":6.577897418,"remaining_time":0.3099532815},
{"learn":[0.3045487975],"iteration":955,"passed_time":6.581891166,"remaining_time":0.3029322294},
{"learn":[0.3044164693],"iteration":956,"passed_time":6.584852721,"remaining_time":0.2958711254},
{"learn":[0.3042811797],"iteration":957,"passed_time":6.589388264,"remaining_time":0.2888875857},
{"learn":[0.304181283],"iteration":958,"passed_time":6.592787667,"remaining_time":0.2818605781},
{"learn":[0.3041487813],"iteration":959,"passed_time":6.595913505,"remaining_time":0.2748297294},
{"learn":[0.3040617995],"iteration":960,"passed_time":6.600143844,"remaining_time":0.2678518314},
{"learn":[0.3039606127],"iteration":961,"passed_time":6.6032868,"remaining_time":0.2608366927},
{"learn":[0.3038584216],"iteration":962,"passed_time":6.606390268,"remaining_time":0.2538280789},
{"learn":[0.3038164141],"iteration":963,"passed_time":6.60985213,"remaining_time":0.2468409509},
{"learn":[0.3037659527],"iteration":964,"passed_time":6.613189837,"remaining_time":0.2398566262},
{"learn":[0.3036872122],"iteration":965,"passed_time":6.617249288,"remaining_time":0.2329052544},
{"learn":[0.3036360174],"iteration":966,"passed_time":6.620243435,"remaining_time":0.2259235092},
{"learn":[0.3035479698],"iteration":967,"passed_time":6.623437894,"remaining_time":0.2189566246},
{"learn":[0.3034570018],"iteration":968,"passed_time":6.626330307,"remaining_time":0.2119878633},
{"learn":[0.3033702938],"iteration":969,"passed_time":6.629741596,"remaining_time":0.2050435545},
{"learn":[0.3032858191],"iteration":970,"passed_time":6.633239918,"remaining_time":0.1981091222},
{"learn":[0.3032017755],"iteration":971,"passed_time":6.636027919,"remaining_time":0.1911612981},
{"learn":[0.3031649694],"iteration":972,"passed_time":6.63932224,"remaining_time":0.1842360745},
{"learn":[0.3030961513],"iteration":973,"passed_time":6.642281941,"remaining_time":0.1773093742},
{"learn":[0.3029921121],"iteration":974,"passed_time":6.645671342,"remaining_time":0.1704018293},
{"learn":[0.3028957924],"iteration":975,"passed_time":6.64899636,"remaining_time":0.1634999105},
{"learn":[0.302823496],"iteration":976,"passed_time":6.652278904,"remaining_time":0.156604314},
{"learn":[0.3027167504],"iteration":977,"passed_time":6.655685563,"remaining_time":0.1497188982},
{"learn":[0.3026679605],"iteration":978,"passed_time":6.658388407,"remaining_time":0.1428254919},
{"learn":[0.3025508958],"iteration":979,"passed_time":6.661703032,"remaining_time":0.1359531231},
{"learn":[0.3024556028],"iteration":980,"passed_time":6.664424166,"remaining_time":0.1290765129},
{"learn":[0.3023316468],"iteration":981,"passed_time":6.6681589,"remaining_time":0.1222269452},
{"learn":[0.3021784992],"iteration":982,"passed_time":6.670943764,"remaining_time":0.1153672879},
{"learn":[0.302110608],"iteration":983,"passed_time":6.674253729,"remaining_time":0.1085244509},
{"learn":[0.3020336844],"iteration":984,"passed_time":6.677074302,"remaining_time":0.1016813346},
{"learn":[0.3019374118],"iteration":985,"passed_time":6.680229154,"remaining_time":0.0948511239},
{"learn":[0.3018252935],"iteration":986,"passed_time":6.683356615,"remaining_time":0.088028},
{"learn":[0.3017565423],"iteration":987,"passed_time":6.686328784,"remaining_time":0.08121047106},
{"learn":[0.3017159271],"iteration":988,"passed_time":6.689608813,"remaining_time":0.07440414251},
{"learn":[0.3015899749],"iteration":989,"passed_time":6.692442105,"remaining_time":0.0676004253},
{"learn":[0.3014900672],"iteration":990,"passed_time":6.695819789,"remaining_time":0.06080966509},
{"learn":[0.301423646],"iteration":991,"passed_time":6.698751558,"remaining_time":0.05402218999},
{"learn":[0.301348839],"iteration":992,"passed_time":6.702663954,"remaining_time":0.04724939344},
{"learn":[0.3012976624],"iteration":993,"passed_time":6.705850538,"remaining_time":0.04047797105},
{"learn":[0.3012446002],"iteration":994,"passed_time":6.709115353,"remaining_time":0.0337141475},
{"learn":[0.3011617198],"iteration":995,"passed_time":6.712519687,"remaining_time":0.02695791039},
{"learn":[0.3010525753],"iteration":996,"passed_time":6.715826054,"remaining_time":0.02020810247},
{"learn":[0.3009443716],"iteration":997,"passed_time":6.719363812,"remaining_time":0.01346565894},
{"learn":[0.3008700526],"iteration":998,"passed_time":6.722257506,"remaining_time":0.006728986493},
{"learn":[0.3007986877],"iteration":999,"passed_time":6.726195711,"remaining_time":0}
]}eration":999,"passed_time":6.38545867,"remaining_time":0}
]}