{
"meta":{"test_sets":[],"test_metrics":[],"learn_metrics":[{"best_value":"Min","name":"Logloss"}],"launch_mode":"Train","parameters":"","iteration_count":1000,"learn_sets":["learn"],"name":"experiment"},
"iterations":[
{"learn":[0.6820877896],"iteration":0,"passed_time":0.09969693687,"remaining_time":99.59723993,,
{"learn":[0.6701028649],"iteration":1,"passed_time":0.1026468734,"remaining_time":51.22078981,,
{"learn":[0.659151237],"iteration":2,"passed_time":0.110840589,"remaining_time":36.8360224},
{"learn":[0.6496278115],"iteration":3,"passed_time":0.117079467,"remaining_time":29.15278728},
{"learn":[0.6404026526],"iteration":4,"passed_time":0.1223579713,"remaining_time":24.34923628},
{"learn":[0.6321354344],"iteration":5,"passed_time":0.127542566,"remaining_time":21.12955177},
{"learn":[0.623886765],"iteration":6,"passed_time":0.131195888,"remaining_time":18.61107383},
{"learn":[0.6160212846],"iteration":7,"passed_time":0.1352616577,"remaining_time":16.77244555},
{"learn":[0.6081877391],"iteration":8,"passed_time":0.1438492611,"remaining_time":15.83940197},
{"learn":[0.5998210355],"iteration":9,"passed_time":0.1482820716,"remaining_time":14.67992509},
{"learn":[0.5934853638],"iteration":10,"passed_time":0.155880259,"remaining_time":14.01505237},
{"learn":[0.5863728285],"iteration":11,"passed_time":0.1613867895,"remaining_time":13.28751233},
{"learn":[0.579497345],"iteration":12,"passed_time":0.164979885,"remaining_time":12.5257805},
{"learn":[0.5736562234],"iteration":13,"passed_time":0.1699120458,"remaining_time":11.96666265},
{"learn":[0.5678341836],"iteration":14,"passed_time":0.1744909507,"remaining_time":11.45823909},
{"learn":[0.5622379692],"iteration":15,"passed_time":0.1812558414,"remaining_time":11.14723425},
{"learn":[0.5570375075],"iteration":16,"passed_time":0.1853081716,"remaining_time":10.71517251},
{"learn":[0.5517472495],"iteration":17,"passed_time":0.189734307,"remaining_time":10.35106053},
{"learn":[0.5464097199],"iteration":18,"passed_time":0.1957390694,"remaining_time":10.10631722},
{"learn":[0.5425654367],"iteration":19,"passed_time":0.2001808712,"remaining_time":9.80886269},
{"learn":[0.5376286117],"iteration":20,"passed_time":0.2033464888,"remaining_time":9.479819646},
{"learn":[0.5333184],"iteration":21,"passed_time":0.2119927088,"remaining_time":9.424039511},
{"learn":[0.5291147708],"iteration":22,"passed_time":0.2171114911,"remaining_time":9.222518556},
{"learn":[0.5246672512],"iteration":23,"passed_time":0.2211793872,"remaining_time":8.994628411},
{"learn":[0.52037885],"iteration":24,"passed_time":0.2279955943,"remaining_time":8.891828179},
{"learn":[0.5165269714],"iteration":25,"passed_time":0.2374595792,"remaining_time":8.895601159},
{"learn":[0.5130654266],"iteration":26,"passed_time":0.2486612685,"remaining_time":8.961015343},
{"learn":[0.5093888239],"iteration":27,"passed_time":0.2557778599,"remaining_time":8.879145708},
{"learn":[0.5057322621],"iteration":28,"passed_time":0.2601614278,"remaining_time":8.710922291},
{"learn":[0.5026779002],"iteration":29,"passed_time":0.2644771398,"remaining_time":8.551427519},
{"learn":[0.4995593018],"iteration":30,"passed_time":0.2696263244,"remaining_time":8.427997043},
{"learn":[0.4965896934],"iteration":31,"passed_time":0.2769622968,"remaining_time":8.378109478},
{"learn":[0.493973653],"iteration":32,"passed_time":0.2842991901,"remaining_time":8.330827782},
{"learn":[0.4910141696],"iteration":33,"passed_time":0.2919633724,"remaining_time":8.295194639},
{"learn":[0.4878972456],"iteration":34,"passed_time":0.2962306703,"remaining_time":8.167502766},
{"learn":[0.4853606874],"iteration":35,"passed_time":0.3014126136,"remaining_time":8.071159987},
{"learn":[0.4826588549],"iteration":36,"passed_time":0.3085829269,"remaining_time":8.031496178},
{"learn":[0.4804775577],"iteration":37,"passed_time":0.3139431458,"remaining_time":7.947718585},
{"learn":[0.477917431],"iteration":38,"passed_time":0.3199945679,"remaining_time":7.884994354},
{"learn":[0.476048263],"iteration":39,"passed_time":0.3261822715,"remaining_time":7.828374516},
{"learn":[0.4741082603],"iteration":40,"passed_time":0.3305000394,"remaining_time":7.730476531},
{"learn":[0.4718429109],"iteration":41,"passed_time":0.3346760623,"remaining_time":7.633801611},
{"learn":[0.4705970238],"iteration":42,"passed_time":0.337125864,"remaining_time":7.503010508},
{"learn":[0.4681674824],"iteration":43,"passed_time":0.3442533524,"remaining_time":7.479686476},
{"learn":[0.4665757275],"iteration":44,"passed_time":0.3491962907,"remaining_time":7.41072128},
{"learn":[0.4648487104],"iteration":45,"passed_time":0.353898476,"remaining_time":7.339546654},
{"learn":[0.4630671263],"iteration":46,"passed_time":0.3598623533,"remaining_time":7.296783462},
{"learn":[0.4612939277],"iteration":47,"passed_time":0.3640460903,"remaining_time":7.220247457},
{"learn":[0.4598298435],"iteration":48,"passed_time":0.3686815706,"remaining_time":7.155432115},
{"learn":[0.4582967582],"iteration":49,"passed_time":0.3740522769,"remaining_time":7.10699326},
{"learn":[0.4564839806],"iteration":50,"passed_time":0.379396387,"remaining_time":7.059748455},
{"learn":[0.4550426647],"iteration":51,"passed_time":0.3841004357,"remaining_time":7.002446405},
{"learn":[0.4535631496],"iteration":52,"passed_time":0.3910374862,"remaining_time":6.987028291},
{"learn":[0.4518856568],"iteration":53,"passed_time":0.4000026028,"remaining_time":7.007453004},
{"learn":[0.4505335822],"iteration":54,"passed_time":0.4052241196,"remaining_time":6.962487145},
{"learn":[0.4494053006],"iteration":55,"passed_time":0.411435945,"remaining_time":6.935634502},
{"learn":[0.4478112389],"iteration":56,"passed_time":0.4177693718,"remaining_time":6.911517854},
{"learn":[0.4465732951],"iteration":57,"passed_time":0.4244983747,"remaining_time":6.89443912},
{"learn":[0.4453206652],"iteration":58,"passed_time":0.4283556963,"remaining_time":6.831910343},
{"learn":[0.4440978526],"iteration":59,"passed_time":0.4326390716,"remaining_time":6.778012122},
{"learn":[0.4428888384],"iteration":60,"passed_time":0.4361049238,"remaining_time":6.713156122},
{"learn":[0.4417539964],"iteration":61,"passed_time":0.4433535229,"remaining_time":6.70750975},
{"learn":[0.440600343],"iteration":62,"passed_time":0.4471747659,"remaining_time":6.650837391},
{"learn":[0.4395527176],"iteration":63,"passed_time":0.4531032986,"remaining_time":6.626635742},
{"learn":[0.4385039714],"iteration":64,"passed_time":0.4570220194,"remaining_time":6.574085972},
{"learn":[0.437504348],"iteration":65,"passed_time":0.4630336776,"remaining_time":6.552628104},
{"learn":[0.4365255075],"iteration":66,"passed_time":0.4665987086,"remaining_time":6.497561121},
{"learn":[0.435558435],"iteration":67,"passed_time":0.4731475595,"remaining_time":6.484904786},
{"learn":[0.4347990065],"iteration":68,"passed_time":0.4803053041,"remaining_time":6.480641132},
{"learn":[0.4338004065],"iteration":69,"passed_time":0.4868649884,"remaining_time":6.468349131},
{"learn":[0.4331151392],"iteration":70,"passed_time":0.4917058375,"remaining_time":6.433728493},
{"learn":[0.4324030946],"iteration":71,"passed_time":0.4980582122,"remaining_time":6.419416957},
{"learn":[0.431713307],"iteration":72,"passed_time":0.5025075675,"remaining_time":6.381157741},
{"learn":[0.4309008458],"iteration":73,"passed_time":0.5066801833,"remaining_time":6.340349321},
{"learn":[0.4301762148],"iteration":74,"passed_time":0.5129396272,"remaining_time":6.326255403},
{"learn":[0.429527324],"iteration":75,"passed_time":0.5181737058,"remaining_time":6.299901371},
{"learn":[0.4288847549],"iteration":76,"passed_time":0.5242328925,"remaining_time":6.28398649},
{"learn":[0.4280337787],"iteration":77,"passed_time":0.5289036237,"remaining_time":6.251912065},
{"learn":[0.427193796],"iteration":78,"passed_time":0.5332859081,"remaining_time":6.217168624},
{"learn":[0.4264666475],"iteration":79,"passed_time":0.543718455,"remaining_time":6.252762233},
{"learn":[0.4258902513],"iteration":80,"passed_time":0.5484470776,"remaining_time":6.222504498},
{"learn":[0.4253021515],"iteration":81,"passed_time":0.5535676043,"remaining_time":6.197256839},
{"learn":[0.4247468613],"iteration":82,"passed_time":0.5584927822,"remaining_time":6.170335919},
{"learn":[0.4242117857],"iteration":83,"passed_time":0.5640954843,"remaining_time":6.151326948},
{"learn":[0.4236717663],"iteration":84,"passed_time":0.5695475607,"remaining_time":6.131011977},
{"learn":[0.4230832244],"iteration":85,"passed_time":0.574023767,"remaining_time":6.100671198},
{"learn":[0.4224009783],"iteration":86,"passed_time":0.5801918908,"remaining_time":6.088680417},
{"learn":[0.421938692],"iteration":87,"passed_time":0.5849491839,"remaining_time":6.062200633},
{"learn":[0.4212851565],"iteration":88,"passed_time":0.5884318969,"remaining_time":6.02316245},
{"learn":[0.4205393608],"iteration":89,"passed_time":0.5941221301,"remaining_time":6.007234871},
{"learn":[0.4201092824],"iteration":90,"passed_time":0.5986190186,"remaining_time":5.979611955},
{"learn":[0.4195013895],"iteration":91,"passed_time":0.6018496521,"remaining_time":5.939994393},
{"learn":[0.4190479672],"iteration":92,"passed_time":0.6057424707,"remaining_time":5.90761743},
{"learn":[0.4183896895],"iteration":93,"passed_time":0.6133352067,"remaining_time":5.911507418},
{"learn":[0.4178683243],"iteration":94,"passed_time":0.6182424524,"remaining_time":5.889572836},
{"learn":[0.4175404962],"iteration":95,"passed_time":0.6227662864,"remaining_time":5.86438253},
{"learn":[0.4169654092],"iteration":96,"passed_time":0.6283508902,"remaining_time":5.849493339},
{"learn":[0.4166679781],"iteration":97,"passed_time":0.6350052501,"remaining_time":5.844640159},
{"learn":[0.4160850655],"iteration":98,"passed_time":0.642939566,"remaining_time":5.851399484},
{"learn":[0.4156026074],"iteration":99,"passed_time":0.648076491,"remaining_time":5.832688419},
{"learn":[0.4150686905],"iteration":100,"passed_time":0.6519152077,"remaining_time":5.802690809},
{"learn":[0.4146340128],"iteration":101,"passed_time":0.6580534514,"remaining_time":5.793450974},
{"learn":[0.4140074473],"iteration":102,"passed_time":0.6620429262,"remaining_time":5.765558299},
{"learn":[0.4135345042],"iteration":103,"passed_time":0.6669940885,"remaining_time":5.746410608},
{"learn":[0.4131587797],"iteration":104,"passed_time":0.6713481367,"remaining_time":5.722443641},
{"learn":[0.4128081632],"iteration":105,"passed_time":0.6763845415,"remaining_time":5.704601699},
{"learn":[0.4122713682],"iteration":106,"passed_time":0.6819254807,"remaining_time":5.691209853},
{"learn":[0.4118114535],"iteration":107,"passed_time":0.686025659,"remaining_time":5.666063776},
{"learn":[0.4115221259],"iteration":108,"passed_time":0.6962287146,"remaining_time":5.691190685},
{"learn":[0.4112208213],"iteration":109,"passed_time":0.70168212,"remaining_time":5.677246244},
{"learn":[0.4109197396],"iteration":110,"passed_time":0.7056970673,"remaining_time":5.65193417},
{"learn":[0.4105376106],"iteration":111,"passed_time":0.7094751394,"remaining_time":5.62512432},
{"learn":[0.4100336668],"iteration":112,"passed_time":0.7158274381,"remaining_time":5.618928651},
{"learn":[0.409765459],"iteration":113,"passed_time":0.7215892628,"remaining_time":5.608141112},
{"learn":[0.4094205594],"iteration":114,"passed_time":0.7265050785,"remaining_time":5.590930387},
{"learn":[0.4091722113],"iteration":115,"passed_time":0.733724599,"remaining_time":5.591487461},
{"learn":[0.408829401],"iteration":116,"passed_time":0.7392031251,"remaining_time":5.578772303},
{"learn":[0.40849203],"iteration":117,"passed_time":0.7483943181,"remaining_time":5.593930411},
{"learn":[0.4082405343],"iteration":118,"passed_time":0.7557196391,"remaining_time":5.594865564},
{"learn":[0.4080756274],"iteration":119,"passed_time":0.7597832014,"remaining_time":5.571743477},
{"learn":[0.4076172622],"iteration":120,"passed_time":0.7661655807,"remaining_time":5.565781367},
{"learn":[0.4073373528],"iteration":121,"passed_time":0.7708993337,"remaining_time":5.547947664},
{"learn":[0.4068121307],"iteration":122,"passed_time":0.7752992601,"remaining_time":5.527946757},
{"learn":[0.4065991892],"iteration":123,"passed_time":0.7812335705,"remaining_time":5.519037159},
{"learn":[0.40625129],"iteration":124,"passed_time":0.7857735188,"remaining_time":5.500414632},
{"learn":[0.4058753884],"iteration":125,"passed_time":0.7920589861,"remaining_time":5.494123444},
{"learn":[0.4056840537],"iteration":126,"passed_time":0.7966213119,"remaining_time":5.475987443},
{"learn":[0.4054441648],"iteration":127,"passed_time":0.8010677392,"remaining_time":5.457273973},
{"learn":[0.4052577001],"iteration":128,"passed_time":0.8075991375,"remaining_time":5.452859293},
{"learn":[0.4049345099],"iteration":129,"passed_time":0.8138493185,"remaining_time":5.446530055},
{"learn":[0.4046718956],"iteration":130,"passed_time":0.8181393338,"remaining_time":5.427199092},
{"learn":[0.4044751289],"iteration":131,"passed_time":0.8224311537,"remaining_time":5.40810789},
{"learn":[0.4042603118],"iteration":132,"passed_time":0.8270684342,"remaining_time":5.391491222},
{"learn":[0.4,
{"learn":[0.4021384816],"iteration":133,"passed_time":0.8318051543,"remaining_tim,
{"learn":[0.4,
{"learn":[0.4018130768],"iteration":134,"passed_time":0.8363593137,"remaining_tim,
{"learn":[0.4034219613],"iteration":135,"passed_time":0.8422522813,"remaining_time":5.350779199},
{"learn":[0.4031153024],"iteration":136,"passed_time":0.8501425447,"remaining_time":5.35527749},
{"learn":[0.4026816698],"iteration":137,"passed_time":0.854238787,"remaining_time":5.335897351},
{"learn":[0.4024596824],"iteration":138,"passed_time":0.8631229037,"remaining_time":5.346394389},
{"learn":[0.4021814355],"iteration":139,"passed_time":0.871930819,"remaining_time":5.35614646},
{"learn":[0.4020027386],"iteration":140,"passed_time":0.8796957388,"remaining_time":5.359281132},
{"learn":[0.4018784533],"iteration":141,"passed_time":0.8841516127,"remaining_time":5.342268195},
{"learn":[0.401550445],"iteration":142,"passed_time":0.8912511839,"remaining_time":5.341274578},
{"learn":[0.4012517224],"iteration":143,"passed_time":0.8958142408,"remaining_time":5.325117987},
{"learn":[0.4010533037],"iteration":144,"passed_time":0.8994430859,"remaining_time":5.303612679},
{"learn":[0.4008,
{"learn":[0.3985297103],"iteration":145,"passed_time":0.9064164536,"remaining_,
{"learn":[0.400,
{"learn":[0.3982230647],"iteration":146,"passed_time":0.9105865731,"remaining,
{"learn":[0.40049,
{"learn":[0.3978811054],"iteration":147,"passed_time":0.9146002329,"remaining,
{"learn":[0,
{"le,
{"learn":[0.3975855219],"iteration":148,"passed_time":0.9205934502,"remaining_time":5.2578,
{"le,
{"learn":[0.3974132852],"iteration":149,"passed_time":0.9295276207,"remaining_time":5.267323184},
{"learn":[0.3971348752],"iteration":150,"passed_time":0.9327865925,"remaining,
{"learn":[0,
{"l,
{"learn":[0.3969497971],"iteration":151,"passed_time":0.93783152,"remaining_time":5.23211,
{"l,
{"learn":[0.3966642314],"iteration":152,"passed_time":0.9436580753,"remaining_ti,
{"learn",
{"le,
{"learn":[0.3964290643],"iteration":153,"passed_time":0.9493505106,"remaining_t,
{"learn":,
{"learn":[0.4026282169],"iteration":154,"passed_time":0.9593933204,"remaining_time":5,
{"learn":,
{"learn":[0.4023257618],"iteration":155,"passed_time":0.9630228007,"remaining_time":5.210200281},
{"learn":[0.4021572634],"iteration":156,"passed_time":0.9715790358,"remaining_time":5.216822466},
{"learn":[0.4019152188],"iteration":157,"passed_time":0.9762564831,"remaining_time":5.202582018},
{"learn":[0.4016556115],"iteration":158,"passed_time":0.9827345369,"remaining_time":5.197985821},
{"learn":[0.4014077156],"iteration":159,"passed_time":0.9882065269,"remaining_time":5.188084266},
{"learn":[0.4010998921],"iteration":160,"passed_time":0.9942387634,"remaining_time":5.181157283},
{"learn":[0.4009177089],"iteration":161,"passed_time":0.999809541,"remaining_time":5.171854292},
{"learn":[0.4007714425],"iteration":162,"passed_time":1.006104917,"remaining_time":5.166317886},
{"learn":[0.4005298589],"iteration":163,"passed_time":1.01306987,"remaining_time":5.164185434},
{"learn":[0.4003508858],"iteration":164,"passed_time":1.019872259,"remaining_time":5.161171733},
{"learn":[0.4000519103],"iteration":165,"passed_time":1.024727352,"remaining_time":5.148328983},
{"learn":[0.3998789884],"iteration":166,"passed_time":1.031202644,"remaining_time":5.143663489},
{"learn":[0.3997398034],"iteration":167,"passed_time":1.036342071,"remaining_time":5.132360731},
{"learn":[0.3996171833],"iteration":168,"passed_time":1.043071993,"remaining_time":5.128951635},
{"learn":[0.3995090358],"iteration":169,"passed_time":1.049706685,"remaining_time":5.125038519},
{"learn":[0.3993527285],"iteration":170,"passed_time":1.054526884,"remaining_time":5.112297},
{"learn":[0.3990846038],"iteration":171,"passed_time":1.062866191,"remaining_time":5.116588407},
{"learn":[0.3990512138],"iteration":172,"passed_time":1.065302632,"remaining_time":5.092516048},
{"learn":[0.3988973994],"iteration":173,"passed_time":1.071814429,"remaining_time":5.088038611},
{"learn":[0.3987867316],"iteration":174,"passed_time":1.075506723,"remaining_time":5.07024598},
{"learn":[0.398632163],"iteration":175,"passed_time":1.081319249,"remaining_time":5.062540121},
{"learn":[0.39852809],"iteration":176,"passed_time":1.086133476,"remaining_time":5.050213847},
{"learn":[0.3983278014],"iteration":177,"passed_time":1.090788464,"remaining_time":5.037236614},
{"learn":[0.3981493502],"iteration":178,"passed_time":1.095501455,"remaining_time":5.024618403},
{"learn":[0.398019887],"iteration":179,"passed_time":1.099790866,"remaining_time":5.010158391},
{"learn":[0.39786652],"iteration":180,"passed_time":1.104382497,"remaining_time":4.997178258},
{"learn":[0.3976869385],"iteration":181,"passed_time":1.108593352,"remaining_time":4.98257,
{"l,
{"learn":[0.3974844916],"iteration":182,"passed_time":1.112959295,"remaining_time":4.96878,
{"l,
{"learn":[0.3973400078],"iteration":183,"passed_time":1.117687094,"remaining_time":4.95669,
{"l,
{"learn":[0.3971618653],"iteration":184,"passed_time":1.122782431,"remaining_time":4.94631,
{"l,
{"learn":[0.3970429556],"iteration":185,"passed_time":1.127043499,"remaining_time":4.9323,
{"le,
{"learn":[0.3968366194],"iteration":186,"passed_time":1.13247156,"remaining_time":4.92352,
{"l,
{"learn":[0.3967579187],"iteration":187,"passed_time":1.138212836,"remaining_time":4.91611,
{",
{"learn":[0.3965094563],"iteration":188,"passed_time":1.143368179,"remaining_time":4.906198,
{",
{"learn":[0.3962252687],"iteration":189,"passed_time":1.150737808,"remaining_time":4.905776,
{",
{"learn":[0.3960022777],"iteration":190,"passed_time":1.154605807,"remaining_time":4.890450,
{",
{"learn":[0.3958746113],"iteration":191,"passed_time":1.158916805,"remaining_time":4.877108,
{",
{"learn":[0.3957285305],"iteration":192,"passed_time":1.167182019,"remaining_time":4.880393,
{",
{"learn":[0.3956398845],"iteration":193,"passed_time":1.173259486,"remaining_time":4.87446,
{"l,
{"learn":[0.3956177487],"iteration":194,"passed_time":1.180869368,"remaining_time":4.874,
{"learn":[0.3916912279],"iteration":195,"passed_time":1.188706983,"remaining_time":4.876124562},
{"learn":[0.3915264474],"iteration":196,"passed_time":1.193024763,"remaining_time":4.862938503},
{"learn":[0.3915086043],"iteration":197,"passed_time":1.196166022,"remaining_time":4.845076513},
{"learn":[0.3913388828],"iteration":198,"passed_time":1.203865586,"remaining_time":4.845710221},
{"learn":[0.3910680931],"iteration":199,"passed_time":1.210013037,"remaining_time":4.840052148},
{"learn":[0.3908688778],"iteration":200,"passed_time":1.21589058,"remaining_time":4.833316284},
{"learn":[0.3907271366],"iteration":201,"passed_time":1.222187754,"remaining_time":4.828246672},
{"learn":[0.3905878509],"iteration":202,"passed_time":1.228745111,"remaining_time":4.824186468},
{"learn":[0.3904109517],"iteration":203,"passed_time":1.234824677,"remaining_time":4.818237464},
{"learn":[0.390133768],"iteration":204,"passed_time":1.238756413,"remaining_time":4.803957795},
{"learn":[0.3900117819],"iteration":205,"passed_time":1.244562095,"remaining_time":4.797001473},
{"learn":[0.3898582732],"iteration":206,"passed_time":1.250028745,"remaining_time":4.788757461},
{"learn":[0.3895740822],"iteration":207,"passed_time":1.256596804,"remaining_time":4.784733985},
{"learn":[0.3894736403],"iteration":208,"passed_time":1.262954203,"remaining_time":4.779888875},
{"learn":[0.3892974965],"iteration":209,"passed_time":1.268896255,"remaining_time":4.773466864},
{"learn":[0.3891117888],"iteration":210,"passed_time":1.277130514,"remaining_time":4.775620736},
{"learn":[0.3889010341],"iteration":211,"passed_time":1.281109173,"remaining_time":4.761858623},
{"learn":[0.3887213152],"iteration":212,"passed_time":1.286322819,"remaining_time":4.752751448},
{"learn":[0.3886148304],"iteration":213,"passed_time":1.292304753,"remaining_time":4.746502503},
{"learn":[0.3885455657],"iteration":214,"passed_time":1.299244231,"remaining_time":4.743752191},
{"learn":[0.3884437695],"iteration":215,"passed_time":1.304886214,"remaining_time":4.736253666},
{"learn":[0.3883487339],"iteration":216,"passed_time":1.311197854,"remaining_time":4.731188571},
{"learn":[0.3881793089],"iteration":217,"passed_time":1.31724703,"remaining_time":4.725170538},
{"learn":[0.388050006],"iteration":218,"passed_time":1.326056351,"remaining_time":4.728995481},
{"learn":[0.3878486765],"iteration":219,"passed_time":1.332803982,"remaining_time":4.725395935},
{"learn":[0.3877033278],"iteration":220,"passed_time":1.338123659,"remaining_time":4.716734527},
{"learn":[0.3876041337],"iteration":221,"passed_time":1.343599963,"remaining_time":4.708652122},
{"learn":[0.3874367122],"iteration":222,"passed_time":1.346988067,"remaining_time":4.693317165},
{"learn":[0.3873441439],"iteration":223,"passed_time":1.351481213,"remaining_time":4.68191706},
{"learn":[0.3871739522],"iteration":224,"passed_time":1.355774639,"remaining_time":4.669890425},
{"learn":[0.3869865925],"iteration":225,"passed_time":1.362248974,"remaining_time":4.665401353},
{"learn":[0.3867733225],"iteration":226,"passed_time":1.370068655,"remaining_time":4.66547608},
{"learn":[0.3866450109],"iteration":227,"passed_time":1.376797226,"remaining_time":4.661787099},
{"learn":[0.3864852925],"iteration":228,"passed_time":1.384124483,"remaining_time":4.660087234},
{"learn":[0.3863217048],"iteration":229,"passed_time":1.388069418,"remaining_time":4.647015007},
{"learn":[0.3862671168],"iteration":230,"passed_time":1.392225449,"remaining_time":4.634724548},
{"learn":[0.3861474789],"iteration":231,"passed_time":1.396987161,"remaining_time":4.624509222},
{"learn":[0.3861254435],"iteration":232,"passed_time":1.400449737,"remaining_time":4.610064156},
{"learn":[0.3860494357],"iteration":233,"passed_time":1.405273683,"remaining_time":4.600169406},
{"learn":[0.3859207132],"iteration":234,"passed_time":1.410009741,"remaining_time":4.590031711},
{"learn":[0.38581031],"iteration":235,"passed_time":1.415692122,"remaining_time":4.583003309},
{"learn":[0.3856805448],"iteration":236,"passed_time":1.422918775,"remaining_time":4.580957914},
{"learn":[0.3855945266],"iteration":237,"passed_time":1.428500512,"remaining_time":4.573602481},
{"learn":[0.3854065477],"iteration":238,"passed_time":1.436058492,"remaining_time":4.572554445},
{"learn":[0.3852766529],"iteration":239,"passed_time":1.442282656,"remaining_time":4.567228412},
{"learn":[0.3850168193],"iteration":240,"passed_time":1.448065798,"remaining_time":4.560505979},
{"learn":[0.3848780352],"iteration":241,"passed_time":1.453547524,"remaining_time":4.552847204},
{"learn":[0.3848726195],"iteration":242,"passed_time":1.457527686,"remaining_time":4.540528635},
{"learn":[0.3847755413],"iteration":243,"passed_time":1.461858425,"remaining_time":4.529364627},
{"learn":[0.384627455],"iteration":244,"passed_time":1.468539272,"remaining_time":4.525498574},
{"learn":[0.3845477747],"iteration":245,"passed_time":1.473081538,"remaining_time":4.515054795},
{"learn":[0.3844758855],"iteration":246,"passed_time":1.479908997,"remaining_time":4.511625404},
{"learn":[0.3843599356],"iteration":247,"passed_time":1.484771098,"remaining_time":4.502209135},
{"learn":[0.3842155725],"iteration":248,"passed_time":1.492323732,"remaining_time":4.500944268},
{"learn":[0.3840907688],"iteration":249,"passed_time":1.49766029,"remaining_time":4.492980871},
{"learn":[0.3839606856],"iteration":250,"passed_time":1.50223432,"remaining_time":4.482762972},
{"learn":[0.3838585774],"iteration":251,"passed_time":1.505544253,"remaining_time":4.468837703},
{"learn":[0.3837635806],"iteration":252,"passed_time":1.511439385,"remaining_time":4.462629331},
{"learn":[0.3835439127],"iteration":253,"passed_time":1.516311334,"remaining_time":4.453418327},
{"learn":[0.3833620966],"iteration":254,"passed_time":1.524269571,"remaining_time":4.453258158},
{"learn":[0.3832625304],"iteration":255,"passed_time":1.530510214,"remaining_time":4.44804531},
{"learn":[0.3831041478],"iteration":256,"passed_time":1.534642243,"remaining_time":4.436728351},
{"learn":[0.3829342048],"iteration":257,"passed_time":1.539884217,"remaining_time":4.428659259},
{"learn":[0.3827867192],"iteration":258,"passed_time":1.544362047,"remaining_time":4.41842578},
{"learn":[0.3826858585],"iteration":259,"passed_time":1.548273994,"remaining_time":4.406625983},
{"learn":[0.382524657],"iteration":260,"passed_time":1.553865374,"remaining_time":4.399641807},
{"learn":[0.3824390004],"iteration":261,"passed_time":1.559744738,"remaining_time":4.393479453},
{"learn":[0.3823447151],"iteration":262,"passed_time":1.563211868,"remaining_time":4.380559494},
{"learn":[0.3822424874],"iteration":263,"passed_time":1.572645009,"remaining_time":4.384343662},
{"learn":[0.3821564908],"iteration":264,"passed_time":1.579690719,"remaining_time":4.381406333},
{"learn":[0.3819651982],"iteration":265,"passed_time":1.585833705,"remaining_time":4.375947141},
{"learn":[0.3818424271],"iteration":266,"passed_time":1.589531166,"remaining_time":4.363769081},
{"learn":[0.3817250753],"iteration":267,"passed_time":1.594276724,"remaining_time":4.354517022},
{"learn":[0.3815875481],"iteration":268,"passed_time":1.597793971,"remaining_time":4.341960568},
{"learn":[0.3813994172],"iteration":269,"passed_time":1.604881745,"remaining_time":4.339124719},
{"learn":[0.3813320578],"iteration":270,"passed_time":1.611523516,"remaining_time":4.335057725},
{"learn":[0.3812602218],"iteration":271,"passed_time":1.616059222,"remaining_time":4.325334976},
{"learn":[0.3810640078],"iteration":272,"passed_time":1.622079009,"remaining_time":4.319602344},
{"learn":[0.3809863752],"iteration":273,"passed_time":1.62748972,"remaining_time":4.312253785},
{"learn":[0.380877236],"iteration":274,"passed_time":1.633342956,"remaining_time":4.306085974},
{"learn":[0.380676487],"iteration":275,"passed_time":1.639987695,"remaining_time":4.301996708},
{"learn":[0.3804822793],"iteration":276,"passed_time":1.645119066,"remaining_time":4.293938933},
{"learn":[0.3803178326],"iteration":277,"passed_time":1.650102188,"remaining_time":4.285517193},
{"learn":[0.3802639203],"iteration":278,"passed_time":1.656997885,"remaining_time":4.282062635},
{"learn":[0.3801581153],"iteration":279,"passed_time":1.668163305,"remaining_time":4.289562784},
{"learn":[0.3799693845],"iteration":280,"passed_time":1.676395639,"remaining_time":4.28942514},
{"learn":[0.3798336245],"iteration":281,"passed_time":1.684449032,"remaining_time":4.288774485},
{"learn":[0.3797856241],"iteration":282,"passed_time":1.691212079,"remaining_time":4.284802334},
{"learn":[0.3797263794],"iteration":283,"passed_time":1.695200504,"remaining_time":4.273815354},
{"learn":[0.3795205823],"iteration":284,"passed_time":1.700690264,"remaining_time":4.266643995},
{"learn":[0.3794103514],"iteration":285,"passed_time":1.70817869,"remaining_time":4.264474073},
{"learn":[0.3792961427],"iteration":286,"passed_time":1.713872245,"remaining_time":4.257808051},
{"learn":[0.3790555095],"iteration":287,"passed_time":1.718133889,"remaining_time":4.247608781},
{"learn":[0.3789663277],"iteration":288,"passed_time":1.723586623,"remaining_time":4.240380931},
{"learn":[0.3787908649],"iteration":289,"passed_time":1.728323624,"remaining_time":4.231413012},
{"learn":[0.3786511114],"iteration":290,"passed_time":1.735129239,"remaining_time":4.227514194},
{"learn":[0.378448868],"iteration":291,"passed_time":1.740344633,"remaining_time":4.219739727},
{"learn":[0.3783471391],"iteration":292,"passed_time":1.748364485,"remaining_time":4.218749799},
{"learn":[0.3782681046],"iteration":293,"passed_time":1.755338257,"remaining_time":4.215200032},
{"learn":[0.3781850147],"iteration":294,"passed_time":1.75969234,"remaining_time":4.205366439},
{"learn":[0.3781279244],"iteration":295,"passed_time":1.767550972,"remaining_time":4.203905014},
{"learn":[0.3779960126],"iteration":296,"passed_time":1.771743181,"remaining_time":4.193722075},
{"learn":[0.3779089753],"iteration":297,"passed_time":1.777618122,"remaining_time":4.18754336},
{"learn":[0.3777435063],"iteration":298,"passed_time":1.784386303,"remaining_time":4.183460865},
{"learn":[0.3776040747],"iteration":299,"passed_time":1.791399689,"remaining_time":4.179932607},
{"learn":[0.3774979169],"iteration":300,"passed_time":1.797133329,"remaining_time":4.173409291},
{"learn":[0.3774430282],"iteration":301,"passed_time":1.801308387,"remaining_time":4.163288922},
{"learn":[0.3773588687],"iteration":302,"passed_time":1.807503542,"remaining_time":4.157854682},
{"learn":[0.3772701612],"iteration":303,"passed_time":1.81273032,"remaining_time":4.150198363},
{"learn":[0.377203181],"iteration":304,"passed_time":1.817315329,"remaining_time":4.141095585},
{"learn":[0.3772019661],"iteration":305,"passed_time":1.819169118,"remaining_time":4.125827999},
{"learn":[0.3770390653],"iteration":306,"passed_time":1.826514149,"remaining_time":4.12304334},
{"learn":[0.3769988945],"iteration":307,"passed_time":1.833445692,"remaining_time":4.119300062},
{"learn":[0.3768165987],"iteration":308,"passed_time":1.838217349,"remaining_time":4.11070611},
{"learn":[0.3766037725],"iteration":309,"passed_time":1.844565573,"remaining_time":4.105645954},
{"learn":[0.3765371353],"iteration":310,"passed_time":1.849363069,"remaining_time":4.097141975},
{"learn":[0.3764813782],"iteration":311,"passed_time":1.854832406,"remaining_time":4.090143254},
{"learn":[0.3764107408],"iteration":312,"passed_time":1.859385786,"remaining_time":4.081143882},
{"learn":[0.3762754493],"iteration":313,"passed_time":1.871455049,"remaining_time":4.088592878},
{"learn":[0.3759952323],"iteration":314,"passed_time":1.878431889,"remaining_time":4.08484395},
{"learn":[0.3758415413],"iteration":315,"passed_time":1.885152639,"remaining_time":4.080520269},
{"learn":[0.3757507631],"iteration":316,"passed_time":1.891574736,"remaining_time":4.075537996},
{"learn":[0.3757005299],"iteration":317,"passed_time":1.898250902,"remaining_time":4.071091556},
{"learn":[0.3756468298],"iteration":318,"passed_time":1.904191099,"remaining_time":4.065059995},
{"learn":[0.3755374753],"iteration":319,"passed_time":1.911197894,"remaining_time":4.061295526},
{"learn":[0.3754365997],"iteration":320,"passed_time":1.918763679,"remaining_time":4.058693265},
{"learn":[0.3753756599],"iteration":321,"passed_time":1.923193911,"remaining_time":4.049457986},
{"learn":[0.375278444],"iteration":322,"passed_time":1.928258299,"remaining_time":4.041581636},
{"learn":[0.3751518514],"iteration":323,"passed_time":1.932304339,"remaining_time":4.031597943},
{"learn":[0.3750783859],"iteration":324,"passed_time":1.937405779,"remaining_time":4.023842773},
{"learn":[0.3749308639],"iteration":325,"passed_time":1.94244449,"remaining_time":4.01597419},
{"learn":[0.3747861961],"iteration":326,"passed_time":1.949206885,"remaining_time":4.011670439},
{"learn":[0.3746844055],"iteration":327,"passed_time":1.956454128,"remaining_time":4.008345043},
{"learn":[0.3745989974],"iteration":328,"passed_time":1.964131721,"remaining_time":4.005873511},
{"learn":[0.3744870324],"iteration":329,"passed_time":1.971830526,"remaining_time":4.003413492},
{"learn":[0.3743757364],"iteration":330,"passed_time":1.980245129,"remaining_time":4.002368554},
{"learn":[0.3742124173],"iteration":331,"passed_time":1.984774725,"remaining_time":3.993462399},
{"learn":[0.374031566],"iteration":332,"passed_time":1.987947816,"remaining_time":3.981865444},
{"learn":[0.3738150804],"iteration":333,"passed_time":1.998390097,"remaining_time":3.984813786},
{"learn":[0.3737621499],"iteration":334,"passed_time":2.002731758,"remaining_time":3.975571997},
{"learn":[0.3736220711],"iteration":335,"passed_time":2.008008928,"remaining_time":3.96820812},
{"learn":[0.3734402208],"iteration":336,"passed_time":2.011684501,"remaining_time":3.95770571},
{"learn":[0.3733400977],"iteration":337,"passed_time":2.016746673,"remaining_time":3.94995946},
{"learn":[0.37322177],"iteration":338,"passed_time":2.022050112,"remaining_time":3.942699482},
{"learn":[0.373104484],"iteration":339,"passed_time":2.026648838,"remaining_time":3.934083038},
{"learn":[0.3730323932],"iteration":340,"passed_time":2.032502232,"remaining_time":3.927914872},
{"learn":[0.3729597086],"iteration":341,"passed_time":2.037435987,"remaining_time":3.91997918},
{"learn":[0.3729589538],"iteration":342,"passed_time":2.039728605,"remaining_time":3.907002021},
{"learn":[0.3729167072],"iteration":343,"passed_time":2.043490278,"remaining_time":3.896888437},
{"learn":[0.3728448495],"iteration":344,"passed_time":2.050530259,"remaining_time":3.893035709},
{"learn":[0.372749751],"iteration":345,"passed_time":2.056138726,"remaining_time":3.886458749},
{"learn":[0.3726035018],"iteration":346,"passed_time":2.060376073,"remaining_time":3.877307134},
{"learn":[0.3725243467],"iteration":347,"passed_time":2.06351833,"remaining_time":3.866132044},
{"learn":[0.372408068],"iteration":348,"passed_time":2.068559417,"remaining_time":3.85854493},
{"learn":[0.3721258641],"iteration":349,"passed_time":2.075289375,"remaining_time":3.854108839},
{"learn":[0.3719842545],"iteration":350,"passed_time":2.081936814,"remaining_time":3.8495071},
{"learn":[0.3719002218],"iteration":351,"passed_time":2.086796956,"remaining_time":3.841603487},
{"learn":[0.3717922402],"iteration":352,"passed_time":2.092105039,"remaining_time":3.834538131},
{"learn":[0.371718043],"iteration":353,"passed_time":2.099704094,"remaining_time":3.831663403},
{"learn":[0.3715711523],"iteration":354,"passed_time":2.105916887,"remaining_time":3.826243358},
{"learn":[0.3714343928],"iteration":355,"passed_time":2.111808824,"remaining_time":3.820238435},
{"learn":[0.3713218278],"iteration":356,"passed_time":2.116772367,"remaining_time":3.812561994},
{"learn":[0.3712545511],"iteration":357,"passed_time":2.122417144,"remaining_time":3.806122364},
{"learn":[0.3711959255],"iteration":358,"passed_time":2.12669029,"remaining_time":3.797238095},
{"learn":[0.3711830273],"iteration":359,"passed_time":2.129126093,"remaining_time":3.785113055},
{"learn":[0.3709656862],"iteration":360,"passed_time":2.134660754,"remaining_time":3.778526931},
{"learn":[0.3708765837],"iteration":361,"passed_time":2.142291404,"remaining_time":3.775640652},
{"learn":[0.3707445748],"iteration":362,"passed_time":2.148877888,"remaining_time":3.770895908},
{"learn":[0.3705535947],"iteration":363,"passed_time":2.152571736,"remaining_time":3.761086879},
{"learn":[0.3704540754],"iteration":364,"passed_time":2.15653925,"remaining_time":3.751787462},
{"learn":[0.3703530432],"iteration":365,"passed_time":2.162574304,"remaining_time":3.746098658},
{"learn":[0.3701796537],"iteration":366,"passed_time":2.168983734,"remaining_time":3.741053689},
{"learn":[0.3700473541],"iteration":367,"passed_time":2.175516819,"remaining_time":3.736213667},
{"learn":[0.3699673211],"iteration":368,"passed_time":2.184335041,"remaining_time":3.735272116},
{"learn":[0.3698844612],"iteration":369,"passed_time":2.191660502,"remaining_time":3.73174626},
{"learn":[0.3696952891],"iteration":370,"passed_time":2.196472726,"remaining_time":3.723938935},
{"learn":[0.3694914435],"iteration":371,"passed_time":2.20068763,"remaining_time":3.715139333},
{"learn":[0.3693328166],"iteration":372,"passed_time":2.205711677,"remaining_time":3.707724455},
{"learn":[0.3692179349],"iteration":373,"passed_time":2.213109124,"remaining_time":3.70429495},
{"learn":[0.3690781171],"iteration":374,"passed_time":2.217159448,"remaining_time":3.695265746},
{"learn":[0.3689710246],"iteration":375,"passed_time":2.225789439,"remaining_time":3.693863324},
{"learn":[0.3688897308],"iteration":376,"passed_time":2.231275878,"remaining_time":3.687227777},
{"learn":[0.3687400161],"iteration":377,"passed_time":2.234599001,"remaining_time":3.677038567},
{"learn":[0.3686577501],"iteration":378,"passed_time":2.238313581,"remaining_time":3.667527001},
{"learn":[0.3685768175],"iteration":379,"passed_time":2.243984747,"remaining_time":3.661238272},
{"learn":[0.3684555916],"iteration":380,"passed_time":2.250049541,"remaining_time":3.655592298},
{"learn":[0.3681852349],"iteration":381,"passed_time":2.255040338,"remaining_time":3.64820662},
{"learn":[0.3680977671],"iteration":382,"passed_time":2.259206981,"remaining_time":3.639505763},
{"learn":[0.3678805445],"iteration":383,"passed_time":2.263845266,"remaining_time":3.631585114},
{"learn":[0.3678182738],"iteration":384,"passed_time":2.268832041,"remaining_time":3.624238195},
{"learn":[0.3676976928],"iteration":385,"passed_time":2.273869857,"remaining_time":3.616984695},
{"learn":[0.3675694551],"iteration":386,"passed_time":2.282425816,"remaining_time":3.615315311},
{"learn":[0.3675100749],"iteration":387,"passed_time":2.287446313,"remaining_time":3.608033875},
{"learn":[0.3674658396],"iteration":388,"passed_time":2.29435099,"remaining_time":3.603723535},
{"learn":[0.3673596226],"iteration":389,"passed_time":2.301161012,"remaining_time":3.599251839},
{"learn":[0.3672685816],"iteration":390,"passed_time":2.308698422,"remaining_time":3.595901123},
{"learn":[0.3671716771],"iteration":391,"passed_time":2.314660295,"remaining_time":3.590085355},
{"learn":[0.3669995112],"iteration":392,"passed_time":2.319653851,"remaining_time":3.58277325},
{"learn":[0.3669331936],"iteration":393,"passed_time":2.325244684,"remaining_time":3.57639157},
{"learn":[0.3668110907],"iteration":394,"passed_time":2.331932704,"remaining_time":3.571694395},
{"learn":[0.3666628348],"iteration":395,"passed_time":2.337566745,"remaining_time":3.565379581},
{"learn":[0.3665495439],"iteration":396,"passed_time":2.346185402,"remaining_time":3.563601505},
{"learn":[0.3664156112],"iteration":397,"passed_time":2.35220892,"remaining_time":3.557863743},
{"learn":[0.3662729941],"iteration":398,"passed_time":2.356454357,"remaining_time":3.549446287},
{"learn":[0.3661756146],"iteration":399,"passed_time":2.365753443,"remaining_time":3.548630164},
{"learn":[0.3660314795],"iteration":400,"passed_time":2.370207794,"remaining_time":3.540534835},
{"learn":[0.3658727539],"iteration":401,"passed_time":2.375879341,"remaining_time":3.534268273},
{"learn":[0.3657303139],"iteration":402,"passed_time":2.384380573,"remaining_time":3.532196531},
{"learn":[0.3656231996],"iteration":403,"passed_time":2.389306836,"remaining_time":3.524818996},
{"learn":[0.3655722139],"iteration":404,"passed_time":2.394398206,"remaining_time":3.51769613},
{"learn":[0.3654607717],"iteration":405,"passed_time":2.399811556,"remaining_time":3.511054345},
{"learn":[0.3653480847],"iteration":406,"passed_time":2.407437832,"remaining_time":3.507642836},
{"learn":[0.365251062],"iteration":407,"passed_time":2.413047545,"remaining_time":3.501284673},
{"learn":[0.3651575757],"iteration":408,"passed_time":2.41747024,"remaining_time":3.493214943},
{"learn":[0.3650540677],"iteration":409,"passed_time":2.42379646,"remaining_time":3.487902223},
{"learn":[0.3649897198],"iteration":410,"passed_time":2.430900063,"remaining_time":3.483698631},
{"learn":[0.3648330619],"iteration":411,"passed_time":2.43580745,"remaining_time":3.476346554},
{"learn":[0.3647324864],"iteration":412,"passed_time":2.439432572,"remaining_time":3.467183825},
{"learn":[0.3644787389],"iteration":413,"passed_time":2.445209918,"remaining_time":3.461094232},
{"learn":[0.3643810783],"iteration":414,"passed_time":2.451019171,"remaining_time":3.45505112},
{"learn":[0.3642852139],"iteration":415,"passed_time":2.456866523,"remaining_time":3.449062619},
{"learn":[0.3641900521],"iteration":416,"passed_time":2.463132984,"remaining_time":3.443660742},
{"learn":[0.363978732],"iteration":417,"passed_time":2.467937991,"remaining_time":3.436219882},
{"learn":[0.3639086065],"iteration":418,"passed_time":2.475997082,"remaining_time":3.433303829},
{"learn":[0.363847916],"iteration":419,"passed_time":2.480778798,"remaining_time":3.425837388},
{"learn":[0.3637976676],"iteration":420,"passed_time":2.48488359,"remaining_time":3.417452728},
{"learn":[0.3637027361],"iteration":421,"passed_time":2.489877461,"remaining_time":3.410306096},
{"learn":[0.363588792],"iteration":422,"passed_time":2.493556967,"remaining_time":3.401376761},
{"learn":[0.3634945012],"iteration":423,"passed_time":2.49847062,"remaining_time":3.394148767},
{"learn":[0.3634048297],"iteration":424,"passed_time":2.507950973,"remaining_time":3.39311014},
{"learn":[0.3633292934],"iteration":425,"passed_time":2.51162241,"remaining_time":3.384204843},
{"learn":[0.3632055355],"iteration":426,"passed_time":2.517097657,"remaining_time":3.377744631},
{"learn":[0.3630998696],"iteration":427,"passed_time":2.524314199,"remaining_time":3.373616172},
{"learn":[0.3630038252],"iteration":428,"passed_time":2.528383068,"remaining_time":3.365283757},
{"learn":[0.3628906045],"iteration":429,"passed_time":2.532128843,"remaining_time":3.356542885},
{"learn":[0.3628764229],"iteration":430,"passed_time":2.534396755,"remaining_time":3.345874138},
{"learn":[0.3627134548],"iteration":431,"passed_time":2.539908537,"remaining_time":3.339509373},
{"learn":[0.3625679003],"iteration":432,"passed_time":2.545776121,"remaining_time":3.333614458},
{"learn":[0.3624777172],"iteration":433,"passed_time":2.549541968,"remaining_time":3.324978695},
{"learn":[0.3624046694],"iteration":434,"passed_time":2.55395047,"remaining_time":3.317200036},
{"learn":[0.3623398739],"iteration":435,"passed_time":2.557985176,"remaining_time":3.308953301},
{"learn":[0.36214079],"iteration":436,"passed_time":2.561712055,"remaining_time":3.30032926},
{"learn":[0.3619645454],"iteration":437,"passed_time":2.568082639,"remaining_time":3.295119733},
{"learn":[0.3618472578],"iteration":438,"passed_time":2.574577899,"remaining_time":3.290064239},
{"learn":[0.3616941207],"iteration":439,"passed_time":2.580631998,"remaining_time":3.284440725},
{"learn":[0.3615510621],"iteration":440,"passed_time":2.58563796,"remaining_time":3.277486666},
{"learn":[0.3614535564],"iteration":441,"passed_time":2.589849379,"remaining_time":3.269538356},
{"learn":[0.3612966083],"iteration":442,"passed_time":2.59510099,"remaining_time":3.262914789},
{"learn":[0.3612504157],"iteration":443,"passed_time":2.601825763,"remaining_time":3.258142172},
{"learn":[0.3611294092],"iteration":444,"passed_time":2.606631561,"remaining_time":3.250967453},
{"learn":[0.3610147061],"iteration":445,"passed_time":2.612701249,"remaining_time":3.2453733},
{"learn":[0.360914211],"iteration":446,"passed_time":2.618899432,"remaining_time":3.239935987},
{"learn":[0.3608087381],"iteration":447,"passed_time":2.62332354,"remaining_time":3.232309362},
{"learn":[0.3607297201],"iteration":448,"passed_time":2.629326598,"remaining_time":3.226634645},
{"learn":[0.360708932],"iteration":449,"passed_time":2.633639542,"remaining_time":3.218892774},
{"learn":[0.3605875803],"iteration":450,"passed_time":2.63802655,"remaining_time":3.211256266},
{"learn":[0.3605038025],"iteration":451,"passed_time":2.642536608,"remaining_time":3.203783321},
{"learn":[0.3603428815],"iteration":452,"passed_time":2.646991753,"remaining_time":3.19625715},
{"learn":[0.360190079],"iteration":453,"passed_time":2.653092403,"remaining_time":3.190723463},
{"learn":[0.360059217],"iteration":454,"passed_time":2.660017738,"remaining_time":3.186175092},
{"learn":[0.359976964],"iteration":455,"passed_time":2.664617878,"remaining_time":3.178842381},
{"learn":[0.3597999369],"iteration":456,"passed_time":2.671980298,"remaining_time":3.174803724},
{"learn":[0.3596590571],"iteration":457,"passed_time":2.681384654,"remaining_time":3.173166993},
{"learn":[0.3595231237],"iteration":458,"passed_time":2.685758712,"remaining_time":3.165567458},
{"learn":[0.3594571517],"iteration":459,"passed_time":2.690516823,"remaining_time":3.158432792},
{"learn":[0.3593474922],"iteration":460,"passed_time":2.700470336,"remaining_time":3.157382888},
{"learn":[0.359218661],"iteration":461,"passed_time":2.708160787,"remaining_time":3.153659098},
{"learn":[0.3591415146],"iteration":462,"passed_time":2.712059162,"remaining_time":3.145520022},
{"learn":[0.3590390843],"iteration":463,"passed_time":2.718066567,"remaining_time":3.139835517},
{"learn":[0.3589498861],"iteration":464,"passed_time":2.728517674,"remaining_time":3.139262271},
{"learn":[0.3588311683],"iteration":465,"passed_time":2.735173794,"remaining_time":3.134297867},
{"learn":[0.3586426115],"iteration":466,"passed_time":2.740720395,"remaining_time":3.128059894},
{"learn":[0.3584901944],"iteration":467,"passed_time":2.745641802,"remaining_time":3.121114186},
{"learn":[0.358335834],"iteration":468,"passed_time":2.749956718,"remaining_time":3.113490442},
{"learn":[0.358251337],"iteration":469,"passed_time":2.754988825,"remaining_time":3.106689526},
{"learn":[0.3581840439],"iteration":470,"passed_time":2.7597503,"remaining_time":3.099592162},
{"learn":[0.3580661517],"iteration":471,"passed_time":2.764552117,"remaining_time":3.092549826},
{"learn":[0.357960639],"iteration":472,"passed_time":2.771060667,"remaining_time":3.087418544},
{"learn":[0.3578233434],"iteration":473,"passed_time":2.777445394,"remaining_time":3.082144045},
{"learn":[0.3576565718],"iteration":474,"passed_time":2.782074691,"remaining_time":3.074924658},
{"learn":[0.3575332895],"iteration":475,"passed_time":2.786240493,"remaining_time":3.067205921},
{"learn":[0.3573809517],"iteration":476,"passed_time":2.794745677,"remaining_time":3.064259935},
{"learn":[0.3572949373],"iteration":477,"passed_time":2.799263639,"remaining_time":3.056936443},
{"learn":[0.3572059403],"iteration":478,"passed_time":2.80323679,"remaining_time":3.049032082},
{"learn":[0.3571071282],"iteration":479,"passed_time":2.80922774,"remaining_time":3.043330051},
{"learn":[0.3569407809],"iteration":480,"passed_time":2.817999006,"remaining_time":3.040626787},
{"learn":[0.356726309],"iteration":481,"passed_time":2.822242691,"remaining_time":3.033032602},
{"learn":[0.3565976151],"iteration":482,"passed_time":2.825392964,"remaining_time":3.02428191},
{"learn":[0.3565091634],"iteration":483,"passed_time":2.831120781,"remaining_time":3.01830232},
{"learn":[0.3562614982],"iteration":484,"passed_time":2.836852454,"remaining_time":3.012327863},
{"learn":[0.356208329],"iteration":485,"passed_time":2.843334543,"remaining_time":3.007148056},
{"learn":[0.3561523957],"iteration":486,"passed_time":2.848167965,"remaining_time":3.000226214},
{"learn":[0.355962847],"iteration":487,"passed_time":2.852964025,"remaining_time":2.993273731},
{"learn":[0.3558557082],"iteration":488,"passed_time":2.862919439,"remaining_time":2.99172154},
{"learn":[0.3557153393],"iteration":489,"passed_time":2.868971243,"remaining_time":2.98607211},
{"learn":[0.3555680454],"iteration":490,"passed_time":2.875685754,"remaining_time":2.981108042},
{"learn":[0.3555219906],"iteration":491,"passed_time":2.883989702,"remaining_time":2.977777985},
{"learn":[0.3553469519],"iteration":492,"passed_time":2.88974108,"remaining_time":2.971802693},
{"learn":[0.3552615147],"iteration":493,"passed_time":2.897591713,"remaining_time":2.967978556},
{"learn":[0.3551680582],"iteration":494,"passed_time":2.903070691,"remaining_time":2.961718584},
{"learn":[0.3551056467],"iteration":495,"passed_time":2.907406263,"remaining_time":2.954299912},
{"learn":[0.354935437],"iteration":496,"passed_time":2.914430537,"remaining_time":2.949614809},
{"learn":[0.3548140845],"iteration":497,"passed_time":2.919265334,"remaining_time":2.942713248},
{"learn":[0.3547435383],"iteration":498,"passed_time":2.923679774,"remaining_time":2.935397929},
{"learn":[0.3546239758],"iteration":499,"passed_time":2.928361999,"remaining_time":2.928361999},
{"learn":[0.3544766595],"iteration":500,"passed_time":2.933531847,"remaining_time":2.921821141},
{"learn":[0.3542706741],"iteration":501,"passed_time":2.937022493,"remaining_time":2.913619923},
{"learn":[0.3541593218],"iteration":502,"passed_time":2.944801691,"remaining_time":2.909674832},
{"learn":[0.3540305414],"iteration":503,"passed_time":2.949350325,"remaining_time":2.902535241},
{"learn":[0.3538529969],"iteration":504,"passed_time":2.955005012,"remaining_time":2.896490061},
{"learn":[0.3536068199],"iteration":505,"passed_time":2.960924226,"remaining_time":2.890704679},
{"learn":[0.3534144181],"iteration":506,"passed_time":2.969161569,"remaining_time":2.887172887},
{"learn":[0.3533069884],"iteration":507,"passed_time":2.976431969,"remaining_time":2.88268608},
{"learn":[0.35319218],"iteration":508,"passed_time":2.982031143,"remaining_time":2.876576211},
{"learn":[0.3531363441],"iteration":509,"passed_time":2.986634593,"remaining_time":2.869511668},
{"learn":[0.3530670379],"iteration":510,"passed_time":2.992585442,"remaining_time":2.863746147},
{"learn":[0.3528568746],"iteration":511,"passed_time":2.999281134,"remaining_time":2.85868983},
{"learn":[0.3527043658],"iteration":512,"passed_time":3.004002439,"remaining_time":2.851752803},
{"learn":[0.3525110446],"iteration":513,"passed_time":3.010117815,"remaining_time":2.846142526},
{"learn":[0.3524040942],"iteration":514,"passed_time":3.014037486,"remaining_time":2.838462486},
{"learn":[0.3522572555],"iteration":515,"passed_time":3.020454178,"remaining_time":2.83313919},
{"learn":[0.35212394],"iteration":516,"passed_time":3.027539434,"remaining_time":2.828436261},
{"learn":[0.3520046559],"iteration":517,"passed_time":3.031736903,"remaining_time":2.821037041},
{"learn":[0.3519281384],"iteration":518,"passed_time":3.036552721,"remaining_time":2.814223235},
{"learn":[0.3517751724],"iteration":519,"passed_time":3.042508455,"remaining_time":2.808469343},
{"learn":[0.3517236258],"iteration":520,"passed_time":3.046870026,"remaining_time":2.801249026},
{"learn":[0.3516090065],"iteration":521,"passed_time":3.05096352,"remaining_time":2.793794181},
{"learn":[0.3515093947],"iteration":522,"passed_time":3.054875506,"remaining_time":2.786186647},
{"learn":[0.3513722578],"iteration":523,"passed_time":3.059749751,"remaining_time":2.779467331},
{"learn":[0.3512281346],"iteration":524,"passed_time":3.067135804,"remaining_time":2.775027632},
{"learn":[0.3510825837],"iteration":525,"passed_time":3.072586337,"remaining_time":2.768832554},
{"learn":[0.3510477715],"iteration":526,"passed_time":3.08211342,"remaining_time":2.766299142},
{"learn":[0.3509415877],"iteration":527,"passed_time":3.095671337,"remaining_time":2.767342559},
{"learn":[0.3508138992],"iteration":528,"passed_time":3.113610607,"remaining_time":2.77223175},
{"learn":[0.350645603],"iteration":529,"passed_time":3.127936829,"remaining_time":2.773830773},
{"learn":[0.3505448679],"iteration":530,"passed_time":3.131868646,"remaining_time":2.766189068},
{"learn":[0.3503282452],"iteration":531,"passed_time":3.146612809,"remaining_time":2.768072922},
{"learn":[0.3501924916],"iteration":532,"passed_time":3.15485454,"remaining_time":2.76419713},
{"learn":[0.3499736197],"iteration":533,"passed_time":3.162779733,"remaining_time":2.760028755},
{"learn":[0.3498393526],"iteration":534,"passed_time":3.169268828,"remaining_time":2.754598141},
{"learn":[0.3497167894],"iteration":535,"passed_time":3.178918512,"remaining_time":2.751899607},
{"learn":[0.3495871901],"iteration":536,"passed_time":3.184723241,"remaining_time":2.745860075},
{"learn":[0.3495155617],"iteration":537,"passed_time":3.188769231,"remaining_time":2.738311124},
{"learn":[0.3493461184],"iteration":538,"passed_time":3.194479314,"remaining_time":2.732198448},
{"learn":[0.3492788309],"iteration":539,"passed_time":3.200599272,"remaining_time":2.726436417},
{"learn":[0.3491614222],"iteration":540,"passed_time":3.205850343,"remaining_time":2.719935873},
{"learn":[0.3489876601],"iteration":541,"passed_time":3.210040182,"remaining_time":2.712543179},
{"learn":[0.3489084158],"iteration":542,"passed_time":3.215278258,"remaining_time":2.706044501},
{"learn":[0.3487507086],"iteration":543,"passed_time":3.220561254,"remaining_time":2.69958811},
{"learn":[0.3486094321],"iteration":544,"passed_time":3.226961288,"remaining_time":2.694068598},
{"learn":[0.3484275772],"iteration":545,"passed_time":3.230897207,"remaining_time":2.686496945},
{"learn":[0.3483144447],"iteration":546,"passed_time":3.236860333,"remaining_time":2.680617424},
{"learn":[0.3482278674],"iteration":547,"passed_time":3.24153607,"remaining_time":2.673675736},
{"learn":[0.3481598181],"iteration":548,"passed_time":3.245622798,"remaining_time":2.666258437},
{"learn":[0.3480334646],"iteration":549,"passed_time":3.249815716,"remaining_time":2.658940131},
{"learn":[0.3479410218],"iteration":550,"passed_time":3.256486684,"remaining_time":2.653652489},
{"learn":[0.3478372647],"iteration":551,"passed_time":3.263351909,"remaining_time":2.648517491},
{"learn":[0.3477489407],"iteration":552,"passed_time":3.267245509,"remaining_time":2.640974218},
{"learn":[0.3476634529],"iteration":553,"passed_time":3.273788723,"remaining_time":2.635577203},
{"learn":[0.3475930791],"iteration":554,"passed_time":3.278165389,"remaining_time":2.628438916},
{"learn":[0.3475413967],"iteration":555,"passed_time":3.28456152,"remaining_time":2.622923228},
{"learn":[0.3474898255],"iteration":556,"passed_time":3.292022529,"remaining_time":2.618251311},
{"learn":[0.3474180451],"iteration":557,"passed_time":3.29840174,"remaining_time":2.612712489},
{"learn":[0.3472570491],"iteration":558,"passed_time":3.304575547,"remaining_time":2.607008615},
{"learn":[0.3470999481],"iteration":559,"passed_time":3.310640082,"remaining_time":2.601217208},
{"learn":[0.3469974124],"iteration":560,"passed_time":3.316139537,"remaining_time":2.594982632},
{"learn":[0.3467981327],"iteration":561,"passed_time":3.322523932,"remaining_time":2.58944036},
{"learn":[0.3466872909],"iteration":562,"passed_time":3.327280343,"remaining_time":2.582631456},
{"learn":[0.3465750102],"iteration":563,"passed_time":3.332443183,"remaining_time":2.576144021},
{"learn":[0.3464473077],"iteration":564,"passed_time":3.337064451,"remaining_time":2.569244312},
{"learn":[0.3463908687],"iteration":565,"passed_time":3.342993032,"remaining_time":2.563355081},
{"learn":[0.3462967854],"iteration":566,"passed_time":3.349410328,"remaining_time":2.557838928},
{"learn":[0.3461607487],"iteration":567,"passed_time":3.355401814,"remaining_time":2.551995746},
{"learn":[0.3460830338],"iteration":568,"passed_time":3.35958446,"remaining_time":2.544781902},
{"learn":[0.3460145735],"iteration":569,"passed_time":3.366091597,"remaining_time":2.539332257},
{"learn":[0.3459220681],"iteration":570,"passed_time":3.373193494,"remaining_time":2.53432576},
{"learn":[0.3458359034],"iteration":571,"passed_time":3.380883104,"remaining_time":2.529751693},
{"learn":[0.3456964477],"iteration":572,"passed_time":3.386460557,"remaining_time":2.523592771},
{"learn":[0.3455355581],"iteration":573,"passed_time":3.392633426,"remaining_time":2.517877769},
{"learn":[0.3453773576],"iteration":574,"passed_time":3.396988126,"remaining_time":2.510817311},
{"learn":[0.3452441997],"iteration":575,"passed_time":3.404788336,"remaining_time":2.506302525},
{"learn":[0.3451901349],"iteration":576,"passed_time":3.410235643,"remaining_time":2.500051434},
{"learn":[0.3451053879],"iteration":577,"passed_time":3.41504894,"remaining_time":2.49334023},
{"learn":[0.3449724795],"iteration":578,"passed_time":3.422081931,"remaining_time":2.488249556},
{"learn":[0.3448241746],"iteration":579,"passed_time":3.426862693,"remaining_time":2.48152126},
{"learn":[0.3446911439],"iteration":580,"passed_time":3.433375396,"remaining_time":2.476048694},
{"learn":[0.3446171577],"iteration":581,"passed_time":3.439396527,"remaining_time":2.470219499},
{"learn":[0.344438461],"iteration":582,"passed_time":3.445063551,"remaining_time":2.464136365},
{"learn":[0.3443290002],"iteration":583,"passed_time":3.449228399,"remaining_time":2.456984613},
{"learn":[0.3441678493],"iteration":584,"passed_time":3.453502176,"remaining_time":2.449920347},
{"learn":[0.3440294025],"iteration":585,"passed_time":3.459604972,"remaining_time":2.444157779},
{"learn":[0.343916863],"iteration":586,"passed_time":3.465023287,"remaining_time":2.437912466},
{"learn":[0.3437808941],"iteration":587,"passed_time":3.47042105,"remaining_time":2.431655565},
{"learn":[0.3436430076],"iteration":588,"passed_time":3.477014937,"remaining_time":2.426236229},
{"learn":[0.343593257],"iteration":589,"passed_time":3.484701615,"remaining_time":2.421572309},
{"learn":[0.3434764169],"iteration":590,"passed_time":3.489643485,"remaining_time":2.414998622},
{"learn":[0.3433000919],"iteration":591,"passed_time":3.495839512,"remaining_time":2.409294799},
{"learn":[0.3431357371],"iteration":592,"passed_time":3.499661077,"remaining_time":2.401959626},
{"learn":[0.3430340108],"iteration":593,"passed_time":3.504893783,"remaining_time":2.395600801},
{"learn":[0.342969575],"iteration":594,"passed_time":3.510485459,"remaining_time":2.389490103},
{"learn":[0.3428600665],"iteration":595,"passed_time":3.516442839,"remaining_time":2.383629039},
{"learn":[0.3428052944],"iteration":596,"passed_time":3.52075169,"remaining_time":2.376654826},
{"learn":[0.3427092255],"iteration":597,"passed_time":3.525706006,"remaining_time":2.370123435},
{"learn":[0.3425606371],"iteration":598,"passed_time":3.529460777,"remaining_time":2.362794276},
{"learn":[0.3424176329],"iteration":599,"passed_time":3.535365769,"remaining_time":2.356910513},
{"learn":[0.3422573418],"iteration":600,"passed_time":3.542286341,"remaining_time":2.351700915},
{"learn":[0.3421332659],"iteration":601,"passed_time":3.545702302,"remaining_time":2.344168632},
{"learn":[0.3420246329],"iteration":602,"passed_time":3.549709746,"remaining_time":2.337039418},
{"learn":[0.3418392992],"iteration":603,"passed_time":3.554094738,"remaining_time":2.330168073},
{"learn":[0.3417293026],"iteration":604,"passed_time":3.557433517,"remaining_time":2.322621883},
{"learn":[0.3416582781],"iteration":605,"passed_time":3.562022754,"remaining_time":2.315902583},
{"learn":[0.3415706871],"iteration":606,"passed_time":3.565860667,"remaining_time":2.308703859},
{"learn":[0.3415043061],"iteration":607,"passed_time":3.569065613,"remaining_time":2.301108093},
{"learn":[0.3413806657],"iteration":608,"passed_time":3.574642706,"remaining_time":2.295049751},
{"learn":[0.3412423457],"iteration":609,"passed_time":3.578167386,"remaining_time":2.287680788},
{"learn":[0.3411017711],"iteration":610,"passed_time":3.581237947,"remaining_time":2.280035289},
{"learn":[0.3409591289],"iteration":611,"passed_time":3.584844734,"remaining_time":2.2727447},
{"learn":[0.3408500529],"iteration":612,"passed_time":3.588122218,"remaining_time":2.265258236},
{"learn":[0.3407413709],"iteration":613,"passed_time":3.591187021,"remaining_time":2.257651776},
{"learn":[0.3406005798],"iteration":614,"passed_time":3.594459231,"remaining_time":2.250189925},
{"learn":[0.3405129481],"iteration":615,"passed_time":3.597503933,"remaining_time":2.242599854},
{"learn":[0.3403830463],"iteration":616,"passed_time":3.60066932,"remaining_time":2.235099432},
{"learn":[0.3402181221],"iteration":617,"passed_time":3.60363251,"remaining_time":2.227488056},
{"learn":[0.3400988755],"iteration":618,"passed_time":3.606759761,"remaining_time":2.21999268},
{"learn":[0.3399835235],"iteration":619,"passed_time":3.609842678,"remaining_time":2.212484222},
{"learn":[0.3399132423],"iteration":620,"passed_time":3.613164899,"remaining_time":2.205136065},
{"learn":[0.3398099548],"iteration":621,"passed_time":3.616116848,"remaining_time":2.197575833},
{"learn":[0.3396629011],"iteration":622,"passed_time":3.619535944,"remaining_time":2.190313083},
{"learn":[0.3395241681],"iteration":623,"passed_time":3.622467256,"remaining_time":2.182768731},
{"learn":[0.3394472687],"iteration":624,"passed_time":3.625619693,"remaining_time":2.175371816},
{"learn":[0.3393156038],"iteration":625,"passed_time":3.62862261,"remaining_time":2.167899131},
{"learn":[0.3391746036],"iteration":626,"passed_time":3.631637334,"remaining_time":2.160447728},
{"learn":[0.3390430928],"iteration":627,"passed_time":3.635033627,"remaining_time":2.153236479},
{"learn":[0.3388755051],"iteration":628,"passed_time":3.638024578,"remaining_time":2.14579828},
{"learn":[0.3387820611],"iteration":629,"passed_time":3.641264922,"remaining_time":2.138520668},
{"learn":[0.3386281822],"iteration":630,"passed_time":3.64421559,"remaining_time":2.131086454},
{"learn":[0.3384786645],"iteration":631,"passed_time":3.647302852,"remaining_time":2.123745965},
{"learn":[0.3383209027],"iteration":632,"passed_time":3.65033587,"remaining_time":2.116387464},
{"learn":[0.3381774964],"iteration":633,"passed_time":3.653509081,"remaining_time":2.109123539},
{"learn":[0.3380628727],"iteration":634,"passed_time":3.656484536,"remaining_time":2.101758828},
{"learn":[0.3379629757],"iteration":635,"passed_time":3.659791374,"remaining_time":2.094597579},
{"learn":[0.3379156858],"iteration":636,"passed_time":3.662759973,"remaining_time":2.087255683},
{"learn":[0.3378401509],"iteration":637,"passed_time":3.665855097,"remaining_time":2.079999287},
{"learn":[0.3378027237],"iteration":638,"passed_time":3.668753646,"remaining_time":2.072644861},
{"learn":[0.3377389282],"iteration":639,"passed_time":3.672026159,"remaining_time":2.065514715},
{"learn":[0.3376424323],"iteration":640,"passed_time":3.675062609,"remaining_time":2.058264394},
{"learn":[0.3374558117],"iteration":641,"passed_time":3.678510988,"remaining_time":2.051256906},
{"learn":[0.337393989],"iteration":642,"passed_time":3.681767519,"remaining_time":2.044153973},
{"learn":[0.3373111998],"iteration":643,"passed_time":3.684656191,"remaining_time":2.036859634},
{"learn":[0.3372447939],"iteration":644,"passed_time":3.687684346,"remaining_time":2.029655725},
{"learn":[0.3371241327],"iteration":645,"passed_time":3.690691326,"remaining_time":2.022453142},
{"learn":[0.3370788674],"iteration":646,"passed_time":3.693999362,"remaining_time":2.015427782},
{"learn":[0.3369681254],"iteration":647,"passed_time":3.69700551,"remaining_time":2.008249907},
{"learn":[0.3369242493],"iteration":648,"passed_time":3.70009235,"remaining_time":2.001128528},
{"learn":[0.3367908907],"iteration":649,"passed_time":3.703130303,"remaining_time":1.99399324},
{"learn":[0.3367483716],"iteration":650,"passed_time":3.706416002,"remaining_time":1.987003356},
{"learn":[0.3366645271],"iteration":651,"passed_time":3.709380308,"remaining_time":1.979853293},
{"learn":[0.3364768411],"iteration":652,"passed_time":3.712456763,"remaining_time":1.972775646},
{"learn":[0.3363635959],"iteration":653,"passed_time":3.715478275,"remaining_time":1.965681167},
{"learn":[0.3362763746],"iteration":654,"passed_time":3.718765931,"remaining_time":1.958739307},
{"learn":[0.3361700733],"iteration":655,"passed_time":3.721713713,"remaining_time":1.951630362},
{"learn":[0.3360022068],"iteration":656,"passed_time":3.724965716,"remaining_time":1.944692908},
{"learn":[0.3358958074],"iteration":657,"passed_time":3.727995379,"remaining_time":1.937651094},
{"learn":[0.3358117467],"iteration":658,"passed_time":3.730897703,"remaining_time":1.930555564},
{"learn":[0.3357577111],"iteration":659,"passed_time":3.73387419,"remaining_time":1.923510946},
{"learn":[0.3356900497],"iteration":660,"passed_time":3.736894977,"remaining_time":1.916501357},
{"learn":[0.3355274893],"iteration":661,"passed_time":3.740105535,"remaining_time":1.909600711},
{"learn":[0.3354137208],"iteration":662,"passed_time":3.743148554,"remaining_time":1.902626037},
{"learn":[0.3352745616],"iteration":663,"passed_time":3.746146185,"remaining_time":1.895640238},
{"learn":[0.3350959984],"iteration":664,"passed_time":3.749143305,"remaining_time":1.888666176},
{"learn":[0.3349410281],"iteration":665,"passed_time":3.752228942,"remaining_time":1.881748448},
{"learn":[0.334890183],"iteration":666,"passed_time":3.755134236,"remaining_time":1.874752175},
{"learn":[0.3347723439],"iteration":667,"passed_time":3.758223788,"remaining_time":1.867859727},
{"learn":[0.3346958945],"iteration":668,"passed_time":3.761155555,"remaining_time":1.860900581},
{"learn":[0.3345379243],"iteration":669,"passed_time":3.764424223,"remaining_time":1.854119394},
{"learn":[0.3344762439],"iteration":670,"passed_time":3.767474375,"remaining_time":1.847241534},
{"learn":[0.3343515785],"iteration":671,"passed_time":3.770692822,"remaining_time":1.840457211},
{"learn":[0.3342567766],"iteration":672,"passed_time":3.773656601,"remaining_time":1.833559745},
{"learn":[0.3341793244],"iteration":673,"passed_time":3.777270689,"remaining_time":1.826988494},
{"learn":[0.3341087712],"iteration":674,"passed_time":3.780463373,"remaining_time":1.820223106},
{"learn":[0.3340329889],"iteration":675,"passed_time":3.783511497,"remaining_time":1.813399002},
{"learn":[0.3339909702],"iteration":676,"passed_time":3.786538827,"remaining_time":1.806576132},
{"learn":[0.3338803665],"iteration":677,"passed_time":3.789612729,"remaining_time":1.799786576},
{"learn":[0.3337669357],"iteration":678,"passed_time":3.792759495,"remaining_time":1.793042412},
{"learn":[0.3336625211],"iteration":679,"passed_time":3.795788115,"remaining_time":1.786253231},
{"learn":[0.3335359917],"iteration":680,"passed_time":3.798808755,"remaining_time":1.779471355},
{"learn":[0.3334087267],"iteration":681,"passed_time":3.801816322,"remaining_time":1.772694414},
{"learn":[0.3333257143],"iteration":682,"passed_time":3.805121123,"remaining_time":1.766066466},
{"learn":[0.3332309829],"iteration":683,"passed_time":3.8080224,"remaining_time":1.759261811},
{"learn":[0.3331844161],"iteration":684,"passed_time":3.810938029,"remaining_time":1.752475152},
{"learn":[0.3331354683],"iteration":685,"passed_time":3.813874247,"remaining_time":1.745709203},
{"learn":[0.3330339945],"iteration":686,"passed_time":3.816900344,"remaining_time":1.738995353},
{"learn":[0.332985846],"iteration":687,"passed_time":3.819749473,"remaining_time":1.73221197},
{"learn":[0.3328541946],"iteration":688,"passed_time":3.823069551,"remaining_time":1.725652584},
{"learn":[0.3327853211],"iteration":689,"passed_time":3.826086942,"remaining_time":1.718966597},
{"learn":[0.3326770391],"iteration":690,"passed_time":3.829368268,"remaining_time":1.712409254},
{"learn":[0.332585282],"iteration":691,"passed_time":3.832231343,"remaining_time":1.705675222},
{"learn":[0.3324654058],"iteration":692,"passed_time":3.835729466,"remaining_time":1.699233689},
{"learn":[0.3323275382],"iteration":693,"passed_time":3.83914312,"remaining_time":1.692763393},
{"learn":[0.3322220841],"iteration":694,"passed_time":3.842269335,"remaining_time":1.686175751},
{"learn":[0.3321866488],"iteration":695,"passed_time":3.845339019,"remaining_time":1.679573365},
{"learn":[0.3321518022],"iteration":696,"passed_time":3.84830978,"remaining_time":1.672938111},
{"learn":[0.3320485477],"iteration":697,"passed_time":3.851365626,"remaining_time":1.666350171},
{"learn":[0.3319256866],"iteration":698,"passed_time":3.854337244,"remaining_time":1.659736067},
{"learn":[0.3318792111],"iteration":699,"passed_time":3.857511974,"remaining_time":1.653219418},
{"learn":[0.3317414919],"iteration":700,"passed_time":3.860492866,"remaining_time":1.646629625},
{"learn":[0.3316951843],"iteration":701,"passed_time":3.8636408,"remaining_time":1.640121023},
{"learn":[0.3316616979],"iteration":702,"passed_time":3.866439772,"remaining_time":1.633474555},
{"learn":[0.3315446539],"iteration":703,"passed_time":3.869712403,"remaining_time":1.627038169},
{"learn":[0.3314181005],"iteration":704,"passed_time":3.872701819,"remaining_time":1.62049225},
{"learn":[0.3313340273],"iteration":705,"passed_time":3.875892041,"remaining_time":1.614040029},
{"learn":[0.3312288219],"iteration":706,"passed_time":3.878886027,"remaining_time":1.607515708},
{"learn":[0.3310994218],"iteration":707,"passed_time":3.88209192,"remaining_time":1.601088758},
{"learn":[0.3310021639],"iteration":708,"passed_time":3.8851604,"remaining_time":1.594614494},
{"learn":[0.330961089],"iteration":709,"passed_time":3.888205073,"remaining_time":1.5881401},
{"learn":[0.3308527724],"iteration":710,"passed_time":3.891590939,"remaining_time":1.581814039},
{"learn":[0.3307813156],"iteration":711,"passed_time":3.894607412,"remaining_time":1.575346818},
{"learn":[0.3306035085],"iteration":712,"passed_time":3.89774984,"remaining_time":1.568939978},
{"learn":[0.3304786634],"iteration":713,"passed_time":3.900748574,"remaining_time":1.562484723},
{"learn":[0.3302935034],"iteration":714,"passed_time":3.904269362,"remaining_time":1.556247228},
{"learn":[0.3301775407],"iteration":715,"passed_time":3.907216823,"remaining_time":1.549789913},
{"learn":[0.3300815725],"iteration":716,"passed_time":3.910424988,"remaining_time":1.543445288},
{"learn":[0.329891071],"iteration":717,"passed_time":3.913390072,"remaining_time":1.537013928},
{"learn":[0.3297832041],"iteration":718,"passed_time":3.916716083,"remaining_time":1.530733268},
{"learn":[0.3296785154],"iteration":719,"passed_time":3.919779885,"remaining_time":1.524358844},
{"learn":[0.3296399822],"iteration":720,"passed_time":3.923093498,"remaining_time":1.518090272},
{"learn":[0.3295355949],"iteration":721,"passed_time":3.926210859,"remaining_time":1.51175432},
{"learn":[0.3295083351],"iteration":722,"passed_time":3.929150648,"remaining_time":1.505359239},
{"learn":[0.3294692001],"iteration":723,"passed_time":3.932193705,"remaining_time":1.49901307},
{"learn":[0.3294354415],"iteration":724,"passed_time":3.935086296,"remaining_time":1.49261894},
{"learn":[0.3293677238],"iteration":725,"passed_time":3.938203922,"remaining_time":1.486319387},
{"learn":[0.3292449084],"iteration":726,"passed_time":3.941181273,"remaining_time":1.479975911},
{"learn":[0.3290742767],"iteration":727,"passed_time":3.944333341,"remaining_time":1.473706962},
{"learn":[0.3288986027],"iteration":728,"passed_time":3.947331914,"remaining_time":1.467389504},
{"learn":[0.3287749561],"iteration":729,"passed_time":3.95031727,"remaining_time":1.46107625},
{"learn":[0.3287058491],"iteration":730,"passed_time":3.953305183,"remaining_time":1.454773043},
{"learn":[0.3285467835],"iteration":731,"passed_time":3.956534411,"remaining_time":1.448567243},
{"learn":[0.3284474359],"iteration":732,"passed_time":3.95939808,"remaining_time":1.442236408},
{"learn":[0.3284202788],"iteration":733,"passed_time":3.962312665,"remaining_time":1.435933473},
{"learn":[0.3283277617],"iteration":734,"passed_time":3.965149297,"remaining_time":1.429611651},
{"learn":[0.3282670161],"iteration":735,"passed_time":3.968139255,"remaining_time":1.423354298},
{"learn":[0.3281714906],"iteration":736,"passed_time":3.971046425,"remaining_time":1.417076268},
{"learn":[0.3281069236],"iteration":737,"passed_time":3.974410881,"remaining_time":1.410969716},
{"learn":[0.3279956981],"iteration":738,"passed_time":3.977443081,"remaining_time":1.40475324},
{"learn":[0.3278746232],"iteration":739,"passed_time":3.980719085,"remaining_time":1.39863103},
{"learn":[0.327709249],"iteration":740,"passed_time":3.984034635,"remaining_time":1.392530324},
{"learn":[0.3275905198],"iteration":741,"passed_time":3.9870967,"remaining_time":1.386348987},
{"learn":[0.3275069225],"iteration":742,"passed_time":3.990106811,"remaining_time":1.380158076},
{"learn":[0.3273603176],"iteration":743,"passed_time":3.993281435,"remaining_time":1.374032322},
{"learn":[0.3272561149],"iteration":744,"passed_time":3.996600816,"remaining_time":1.367964038},
{"learn":[0.3271347779],"iteration":745,"passed_time":3.999550362,"remaining_time":1.361777201},
{"learn":[0.3269967542],"iteration":746,"passed_time":4.002561114,"remaining_time":1.355619761},
{"learn":[0.3269083186],"iteration":747,"passed_time":4.005477536,"remaining_time":1.349438956},
{"learn":[0.3268185076],"iteration":748,"passed_time":4.008506241,"remaining_time":1.343304495},
{"learn":[0.3266747637],"iteration":749,"passed_time":4.011471771,"remaining_time":1.337157257},
{"learn":[0.3265736204],"iteration":750,"passed_time":4.014578049,"remaining_time":1.331065159},
{"learn":[0.3265373818],"iteration":751,"passed_time":4.017440364,"remaining_time":1.324900546},
{"learn":[0.3264551949],"iteration":752,"passed_time":4.020553664,"remaining_time":1.318827032},
{"learn":[0.3263403015],"iteration":753,"passed_time":4.023501114,"remaining_time":1.31270726},
{"learn":[0.3263161542],"iteration":754,"passed_time":4.026389025,"remaining_time":1.306576571},
{"learn":[0.3261780515],"iteration":755,"passed_time":4.029251855,"remaining_time":1.300446366},
{"learn":[0.3260411711],"iteration":756,"passed_time":4.032553787,"remaining_time":1.294465747},
{"learn":[0.3259432268],"iteration":757,"passed_time":4.035500807,"remaining_time":1.288378886},
{"learn":[0.3258707409],"iteration":758,"passed_time":4.038585911,"remaining_time":1.282344143},
{"learn":[0.3257306944],"iteration":759,"passed_time":4.041548218,"remaining_time":1.276278385},
{"learn":[0.3256226633],"iteration":760,"passed_time":4.04482519,"remaining_time":1.270319606},
{"learn":[0.3254624458],"iteration":761,"passed_time":4.047749195,"remaining_time":1.264257623},
{"learn":[0.3253110333],"iteration":762,"passed_time":4.050797595,"remaining_time":1.258242503},
{"learn":[0.3252112453],"iteration":763,"passed_time":4.053788049,"remaining_time":1.252217251},
{"learn":[0.3251004607],"iteration":764,"passed_time":4.057001176,"remaining_time":1.246268335},
{"learn":[0.3249826444],"iteration":765,"passed_time":4.060197611,"remaining_time":1.240321464},
{"learn":[0.3249455486],"iteration":766,"passed_time":4.063169364,"remaining_time":1.23431351},
{"learn":[0.3248573835],"iteration":767,"passed_time":4.066336492,"remaining_time":1.228372482},
{"learn":[0.3247657403],"iteration":768,"passed_time":4.069272602,"remaining_time":1.222369273},
{"learn":[0.3245890736],"iteration":769,"passed_time":4.072806731,"remaining_time":1.21655266},
{"learn":[0.324549795],"iteration":770,"passed_time":4.075812472,"remaining_time":1.210585027},
{"learn":[0.3244044248],"iteration":771,"passed_time":4.079149351,"remaining_time":1.204722865},
{"learn":[0.3242902603],"iteration":772,"passed_time":4.082097765,"remaining_time":1.19875316},
{"learn":[0.3242219994],"iteration":773,"passed_time":4.085293812,"remaining_time":1.192863568},
{"learn":[0.3241527424],"iteration":774,"passed_time":4.088178606,"remaining_time":1.186890563},
{"learn":[0.3240850225],"iteration":775,"passed_time":4.091561797,"remaining_time":1.181069385},
{"learn":[0.3239884525],"iteration":776,"passed_time":4.094587263,"remaining_time":1.175151814},
{"learn":[0.3239655271],"iteration":777,"passed_time":4.0975666,"remaining_time":1.169228516},
{"learn":[0.3238684432],"iteration":778,"passed_time":4.10064364,"remaining_time":1.163340494},
{"learn":[0.3237578387],"iteration":779,"passed_time":4.103585595,"remaining_time":1.157421578},
{"learn":[0.3236673579],"iteration":780,"passed_time":4.106806528,"remaining_time":1.151588514},
{"learn":[0.3236341649],"iteration":781,"passed_time":4.109734234,"remaining_time":1.145680388},
{"learn":[0.323504261],"iteration":782,"passed_time":4.112841591,"remaining_time":1.139829662},
{"learn":[0.3234397564],"iteration":783,"passed_time":4.115906736,"remaining_time":1.133974305},
{"learn":[0.3232666301],"iteration":784,"passed_time":4.118824426,"remaining_time":1.128085671},
{"learn":[0.3231671056],"iteration":785,"passed_time":4.121781576,"remaining_time":1.12221534},
{"learn":[0.3230607534],"iteration":786,"passed_time":4.124755686,"remaining_time":1.116357003},
{"learn":[0.3229553629],"iteration":787,"passed_time":4.127695864,"remaining_time":1.110496857},
{"learn":[0.3228064423],"iteration":788,"passed_time":4.13075803,"remaining_time":1.104676736},
{"learn":[0.3227436504],"iteration":789,"passed_time":4.133689513,"remaining_time":1.098828858},
{"learn":[0.3226862721],"iteration":790,"passed_time":4.137035825,"remaining_time":1.093097961},
{"learn":[0.3225970862],"iteration":791,"passed_time":4.139974861,"remaining_time":1.087266125},
{"learn":[0.3225031941],"iteration":792,"passed_time":4.143100308,"remaining_time":1.081490244},
{"learn":[0.3224212743],"iteration":793,"passed_time":4.145944708,"remaining_time":1.075648123},
{"learn":[0.3223251147],"iteration":794,"passed_time":4.149286554,"remaining_time":1.069941816},
{"learn":[0.3222647208],"iteration":795,"passed_time":4.152316474,"remaining_time":1.064161508},
{"learn":[0.3221396039],"iteration":796,"passed_time":4.155371458,"remaining_time":1.058394487},
{"learn":[0.3220789513],"iteration":797,"passed_time":4.158460204,"remaining_time":1.052642809},
{"learn":[0.3220059377],"iteration":798,"passed_time":4.161590858,"remaining_time":1.046908338},
{"learn":[0.3218926369],"iteration":799,"passed_time":4.164554987,"remaining_time":1.041138747},
{"learn":[0.3218411378],"iteration":800,"passed_time":4.167796283,"remaining_time":1.035445019},
{"learn":[0.3217633125],"iteration":801,"passed_time":4.170897206,"remaining_time":1.029722752},
{"learn":[0.3216760643],"iteration":802,"passed_time":4.174220177,"remaining_time":1.024061488},
{"learn":[0.3216511456],"iteration":803,"passed_time":4.177313417,"remaining_time":1.018350037},
{"learn":[0.3215442522],"iteration":804,"passed_time":4.180293582,"remaining_time":1.0126177},
{"learn":[0.3214952508],"iteration":805,"passed_time":4.183380326,"remaining_time":1.006917845},
{"learn":[0.321419042],"iteration":806,"passed_time":4.18644464,"remaining_time":1.001219102},
{"learn":[0.3212931526],"iteration":807,"passed_time":4.189543044,"remaining_time":0.9955349808},
{"learn":[0.3211637273],"iteration":808,"passed_time":4.192597888,"remaining_time":0.9898469674},
{"learn":[0.3210740185],"iteration":809,"passed_time":4.195813136,"remaining_time":0.9842030813},
{"learn":[0.3210419972],"iteration":810,"passed_time":4.198661107,"remaining_time":0.9784795921},
{"learn":[0.3209455228],"iteration":811,"passed_time":4.201847516,"remaining_time":0.9728415431},
{"learn":[0.3209149078],"iteration":812,"passed_time":4.204601534,"remaining_time":0.9671100699},
{"learn":[0.3207935071],"iteration":813,"passed_time":4.207626116,"remaining_time":0.9614477367},
{"learn":[0.3207170235],"iteration":814,"passed_time":4.210526265,"remaining_time":0.9557636307},
{"learn":[0.3206380317],"iteration":815,"passed_time":4.213760437,"remaining_time":0.9501616672},
{"learn":[0.3205198367],"iteration":816,"passed_time":4.216701269,"remaining_time":0.9444997947},
{"learn":[0.320418065],"iteration":817,"passed_time":4.219768256,"remaining_time":0.9388726437},
{"learn":[0.3202991341],"iteration":818,"passed_time":4.222945283,"remaining_time":0.9332760637},
{"learn":[0.3202060339],"iteration":819,"passed_time":4.226045042,"remaining_time":0.9276684239},
{"learn":[0.3201035584],"iteration":820,"passed_time":4.229292967,"remaining_time":0.9220991974},
{"learn":[0.3199769395],"iteration":821,"passed_time":4.232365524,"remaining_time":0.9164976439},
{"learn":[0.3198667169],"iteration":822,"passed_time":4.235494503,"remaining_time":0.9109143706},
{"learn":[0.3197234162],"iteration":823,"passed_time":4.238474841,"remaining_time":0.9053053057},
{"learn":[0.3196491404],"iteration":824,"passed_time":4.241752226,"remaining_time":0.8997656237},
{"learn":[0.3195321224],"iteration":825,"passed_time":4.244680273,"remaining_time":0.8941578299},
{"learn":[0.3194062555],"iteration":826,"passed_time":4.247910941,"remaining_time":0.8886198221},
{"learn":[0.3193415854],"iteration":827,"passed_time":4.250911019,"remaining_time":0.8830394871},
{"learn":[0.3192810978],"iteration":828,"passed_time":4.254114713,"remaining_time":0.8775073774},
{"learn":[0.3192652682],"iteration":829,"passed_time":4.25701123,"remaining_time":0.8719179628},
{"learn":[0.3191867779],"iteration":830,"passed_time":4.260261537,"remaining_time":0.8664069793},
{"learn":[0.3190277076],"iteration":831,"passed_time":4.263132583,"remaining_time":0.8608248485},
{"learn":[0.318998176],"iteration":832,"passed_time":4.266204768,"remaining_time":0.8552895514},
{"learn":[0.3189413559],"iteration":833,"passed_time":4.269313736,"remaining_time":0.8497674823},
{"learn":[0.3188618592],"iteration":834,"passed_time":4.272532634,"remaining_time":0.8442729158},
{"learn":[0.3187718354],"iteration":835,"passed_time":4.275802917,"remaining_time":0.8387938737},
{"learn":[0.3186994766],"iteration":836,"passed_time":4.278870384,"remaining_time":0.8332806124},
{"learn":[0.3186708755],"iteration":837,"passed_time":4.281892474,"remaining_time":0.8277644163},
{"learn":[0.3185675377],"iteration":838,"passed_time":4.284875081,"remaining_time":0.8222465888},
{"learn":[0.3185258657],"iteration":839,"passed_time":4.288102178,"remaining_time":0.8167813673},
{"learn":[0.3185030482],"iteration":840,"passed_time":4.291030782,"remaining_time":0.8112650349},
{"learn":[0.3184326798],"iteration":841,"passed_time":4.294249925,"remaining_time":0.8058093683},
{"learn":[0.3183521093],"iteration":842,"passed_time":4.297174949,"remaining_time":0.8003042314},
{"learn":[0.3182743683],"iteration":843,"passed_time":4.300423906,"remaining_time":0.7948650822},
{"learn":[0.3181168308],"iteration":844,"passed_time":4.303359743,"remaining_time":0.7893736807},
{"learn":[0.3180899423],"iteration":845,"passed_time":4.306401923,"remaining_time":0.7839076787},
{"learn":[0.3180309583],"iteration":846,"passed_time":4.309284689,"remaining_time":0.7784186037},
{"learn":[0.3179362269],"iteration":847,"passed_time":4.312461255,"remaining_time":0.7729883382},
{"learn":[0.3178391301],"iteration":848,"passed_time":4.31539743,"remaining_time":0.7675206265},
{"learn":[0.3177178643],"iteration":849,"passed_time":4.3191381,"remaining_time":0.7622008411},
{"learn":[0.3176188139],"iteration":850,"passed_time":4.322240969,"remaining_time":0.7567730957},
{"learn":[0.3174808743],"iteration":851,"passed_time":4.325213214,"remaining_time":0.751328117},
{"learn":[0.3174482391],"iteration":852,"passed_time":4.328416676,"remaining_time":0.7459287824},
{"learn":[0.3173934441],"iteration":853,"passed_time":4.331496534,"remaining_time":0.740513459},
{"learn":[0.3172399616],"iteration":854,"passed_time":4.334679454,"remaining_time":0.735121077},
{"learn":[0.3171015288],"iteration":855,"passed_time":4.337755331,"remaining_time":0.7297158501},
{"learn":[0.3170345098],"iteration":856,"passed_time":4.340867427,"remaining_time":0.7243221028},
{"learn":[0.3169479439],"iteration":857,"passed_time":4.343955362,"remaining_time":0.7189296753},
{"learn":[0.3168586561],"iteration":858,"passed_time":4.347012764,"remaining_time":0.7135376015},
{"learn":[0.3167653524],"iteration":859,"passed_time":4.350020566,"remaining_time":0.7081428828},
{"learn":[0.3166249742],"iteration":860,"passed_time":4.353296085,"remaining_time":0.7027969289},
{"learn":[0.3165037894],"iteration":861,"passed_time":4.356293691,"remaining_time":0.697411287},
{"learn":[0.3163950012],"iteration":862,"passed_time":4.359581492,"remaining_time":0.6920772472},
{"learn":[0.3163403092],"iteration":863,"passed_time":4.362814452,"remaining_time":0.6867393119},
{"learn":[0.3162304182],"iteration":864,"passed_time":4.366176581,"remaining_time":0.6814264028},
{"learn":[0.3160811581],"iteration":865,"passed_time":4.369315849,"remaining_time":0.6760835147},
{"learn":[0.3160188147],"iteration":866,"passed_time":4.372488118,"remaining_time":0.6707507724},
{"learn":[0.3159201046],"iteration":867,"passed_time":4.375621237,"remaining_time":0.6654170545},
{"learn":[0.3158400074],"iteration":868,"passed_time":4.378662641,"remaining_time":0.6600745753},
{"learn":[0.3157657644],"iteration":869,"passed_time":4.381946314,"remaining_time":0.6547735872},
{"learn":[0.315688701],"iteration":870,"passed_time":4.38476582,"remaining_time":0.6494084854},
{"learn":[0.3156014681],"iteration":871,"passed_time":4.38816854,"remaining_time":0.6441348315},
{"learn":[0.3155008979],"iteration":872,"passed_time":4.391068728,"remaining_time":0.6387923579},
{"learn":[0.3154161921],"iteration":873,"passed_time":4.394174796,"remaining_time":0.6334851537},
{"learn":[0.3153265483],"iteration":874,"passed_time":4.397109217,"remaining_time":0.6281584596},
{"learn":[0.3152303788],"iteration":875,"passed_time":4.400485415,"remaining_time":0.622899762},
{"learn":[0.3151119581],"iteration":876,"passed_time":4.403592009,"remaining_time":0.6176075451},
{"learn":[0.3150169904],"iteration":877,"passed_time":4.406676227,"remaining_time":0.6123171979},
{"learn":[0.3149267081],"iteration":878,"passed_time":4.409855129,"remaining_time":0.607044904},
{"learn":[0.3148514803],"iteration":879,"passed_time":4.412816954,"remaining_time":0.6017477665},
{"learn":[0.3147876881],"iteration":880,"passed_time":4.415971276,"remaining_time":0.5964819317},
{"learn":[0.3146798818],"iteration":881,"passed_time":4.418977815,"remaining_time":0.5912011136},
{"learn":[0.3146003408],"iteration":882,"passed_time":4.422271489,"remaining_time":0.5859634929},
{"learn":[0.3145430726],"iteration":883,"passed_time":4.425385631,"remaining_time":0.5807067118},
{"learn":[0.3144800317],"iteration":884,"passed_time":4.428462406,"remaining_time":0.5754499172},
{"learn":[0.3143892797],"iteration":885,"passed_time":4.431403693,"remaining_time":0.5701806106},
{"learn":[0.3143358364],"iteration":886,"passed_time":4.43465522,"remaining_time":0.5649560764},
{"learn":[0.3142544619],"iteration":887,"passed_time":4.437568357,"remaining_time":0.5596933063},
{"learn":[0.3141031238],"iteration":888,"passed_time":4.440962653,"remaining_time":0.5544958993},
{"learn":[0.3139412185],"iteration":889,"passed_time":4.444056525,"remaining_time":0.5492654131},
{"learn":[0.3138508701],"iteration":890,"passed_time":4.447213807,"remaining_time":0.5440474803},
{"learn":[0.3137416313],"iteration":891,"passed_time":4.450668104,"remaining_time":0.5388701292},
{"learn":[0.3136806103],"iteration":892,"passed_time":4.453606857,"remaining_time":0.5336348642},
{"learn":[0.3135471231],"iteration":893,"passed_time":4.456699104,"remaining_time":0.5284229363},
{"learn":[0.3134574621],"iteration":894,"passed_time":4.459657828,"remaining_time":0.5232000804},
{"learn":[0.3133798421],"iteration":895,"passed_time":4.462788191,"remaining_time":0.5180022007},
{"learn":[0.3133252246],"iteration":896,"passed_time":4.465795281,"remaining_time":0.5127947758},
{"learn":[0.3132330194],"iteration":897,"passed_time":4.46901791,"remaining_time":0.5076167337},
{"learn":[0.313148042],"iteration":898,"passed_time":4.472034991,"remaining_time":0.5024199489},
{"learn":[0.313072719],"iteration":899,"passed_time":4.475404412,"remaining_time":0.4972671569},
{"learn":[0.3129753687],"iteration":900,"passed_time":4.47841401,"remaining_time":0.4920787869},
{"learn":[0.3129010576],"iteration":901,"passed_time":4.481596779,"remaining_time":0.4869140625},
{"learn":[0.312782942],"iteration":902,"passed_time":4.484616181,"remaining_time":0.4817361789},
{"learn":[0.3126948027],"iteration":903,"passed_time":4.487827852,"remaining_time":0.4765834887},
{"learn":[0.3125853135],"iteration":904,"passed_time":4.490961457,"remaining_time":0.4714268933},
{"learn":[0.3125640069],"iteration":905,"passed_time":4.493853723,"remaining_time":0.466249724},
{"learn":[0.3124742822],"iteration":906,"passed_time":4.497037424,"remaining_time":0.4611074757},
{"learn":[0.3123863874],"iteration":907,"passed_time":4.500049344,"remaining_time":0.4559521362},
{"learn":[0.31230922],"iteration":908,"passed_time":4.503188276,"remaining_time":0.4508142279},
{"learn":[0.3122501668],"iteration":909,"passed_time":4.506168455,"remaining_time":0.445665012},
{"learn":[0.3120843003],"iteration":910,"passed_time":4.509320091,"remaining_time":0.4405373085},
{"learn":[0.3120003468],"iteration":911,"passed_time":4.51222399,"remaining_time":0.4353900342},
{"learn":[0.311923834],"iteration":912,"passed_time":4.515389296,"remaining_time":0.4302725835},
{"learn":[0.3118291722],"iteration":913,"passed_time":4.51831494,"remaining_time":0.4251368543},
{"learn":[0.3117282854],"iteration":914,"passed_time":4.521484048,"remaining_time":0.4200285728},
{"learn":[0.311705204],"iteration":915,"passed_time":4.52426076,"remaining_time":0.4148885413},
{"learn":[0.3115689766],"iteration":916,"passed_time":4.527335228,"remaining_time":0.409780615},
{"learn":[0.3114880808],"iteration":917,"passed_time":4.530235525,"remaining_time":0.4046615611},
{"learn":[0.3114060656],"iteration":918,"passed_time":4.533380692,"remaining_time":0.3995689185},
{"learn":[0.3113718312],"iteration":919,"passed_time":4.536141521,"remaining_time":0.3944470888},
{"learn":[0.3112760883],"iteration":920,"passed_time":4.539231179,"remaining_time":0.3893585919},
{"learn":[0.3111784864],"iteration":921,"passed_time":4.542168871,"remaining_time":0.3842615747},
{"learn":[0.3111556855],"iteration":922,"passed_time":4.545370486,"remaining_time":0.379191254},
{"learn":[0.3111333411],"iteration":923,"passed_time":4.548197704,"remaining_time":0.3740941834},
{"learn":[0.3110599635],"iteration":924,"passed_time":4.551381856,"remaining_time":0.3690309613},
{"learn":[0.3109144726],"iteration":925,"passed_time":4.554256067,"remaining_time":0.3639470291},
{"learn":[0.3108904219],"iteration":926,"passed_time":4.557449875,"remaining_time":0.3588930322},
{"learn":[0.3107705955],"iteration":927,"passed_time":4.560580842,"remaining_time":0.3538381688},
{"learn":[0.3106850824],"iteration":928,"passed_time":4.56349075,"remaining_time":0.3487705525},
{"learn":[0.3106098977],"iteration":929,"passed_time":4.566476721,"remaining_time":0.3437133016},
{"learn":[0.3104711757],"iteration":930,"passed_time":4.569719336,"remaining_time":0.3386795211},
{"learn":[0.3103649757],"iteration":931,"passed_time":4.572935084,"remaining_time":0.3336476241},
{"learn":[0.3102938503],"iteration":932,"passed_time":4.575887359,"remaining_time":0.3286007},
{"learn":[0.3102246924],"iteration":933,"passed_time":4.57928677,"remaining_time":0.3235898574},
{"learn":[0.3101087838],"iteration":934,"passed_time":4.58244988,"remaining_time":0.3185660345},
{"learn":[0.3100164825],"iteration":935,"passed_time":4.585897549,"remaining_time":0.3135656444},
{"learn":[0.3099245478],"iteration":936,"passed_time":4.588920271,"remaining_time":0.3085399969},
{"learn":[0.309834217],"iteration":937,"passed_time":4.592371995,"remaining_time":0.3035469762},
{"learn":[0.3097185044],"iteration":938,"passed_time":4.595565567,"remaining_time":0.2985404682},
{"learn":[0.3096582414],"iteration":939,"passed_time":4.598652774,"remaining_time":0.2935310281},
{"learn":[0.3095290488],"iteration":940,"passed_time":4.60190764,"remaining_time":0.2885361857},
{"learn":[0.309373732],"iteration":941,"passed_time":4.604921455,"remaining_time":0.2835301957},
{"learn":[0.3092863008],"iteration":942,"passed_time":4.608217967,"remaining_time":0.2785455187},
{"learn":[0.3092323565],"iteration":943,"passed_time":4.611315646,"remaining_time":0.273552623},
{"learn":[0.3091805252],"iteration":944,"passed_time":4.614946851,"remaining_time":0.2685947903},
{"learn":[0.3090812349],"iteration":945,"passed_time":4.618084513,"remaining_time":0.2636115895},
{"learn":[0.3090195003],"iteration":946,"passed_time":4.621341337,"remaining_time":0.2586389555},
{"learn":[0.3088924014],"iteration":947,"passed_time":4.624221533,"remaining_time":0.2536492824},
{"learn":[0.3088044433],"iteration":948,"passed_time":4.627854034,"remaining_time":0.2487044844},
{"learn":[0.3087079237],"iteration":949,"passed_time":4.632006906,"remaining_time":0.2437898371},
{"learn":[0.3085968557],"iteration":950,"passed_time":4.635472758,"remaining_time":0.2388413934},
{"learn":[0.3085459971],"iteration":951,"passed_time":4.639150218,"remaining_time":0.2339067337},
{"learn":[0.308395404],"iteration":952,"passed_time":4.642629109,"remaining_time":0.2289649193},
{"learn":[0.3083099071],"iteration":953,"passed_time":4.646216514,"remaining_time":0.2240314042},
{"learn":[0.3082646232],"iteration":954,"passed_time":4.652373698,"remaining_time":0.2192217973},
{"learn":[0.3081618119],"iteration":955,"passed_time":4.659140346,"remaining_time":0.2144374218},
{"learn":[0.3081400088],"iteration":956,"passed_time":4.670004668,"remaining_time":0.2098330206},
{"learn":[0.3080933756],"iteration":957,"passed_time":4.678687017,"remaining_time":0.2051198901},
{"learn":[0.3080317211],"iteration":958,"passed_time":4.684188007,"remaining_time":0.2002624695},
{"learn":[0.3080046569],"iteration":959,"passed_time":4.694037999,"remaining_time":0.1955849166},
{"learn":[0.3079683859],"iteration":960,"passed_time":4.697589278,"remaining_time":0.1906409801},
{"learn":[0.3079082827],"iteration":961,"passed_time":4.701035913,"remaining_time":0.1856958053},
{"learn":[0.3078407795],"iteration":962,"passed_time":4.716362595,"remaining_time":0.1812101932},
{"learn":[0.3077721592],"iteration":963,"passed_time":4.753484179,"remaining_time":0.1775160067},
{"learn":[0.3077044412],"iteration":964,"passed_time":4.758107763,"remaining_time":0.1725738567},
{"learn":[0.3076615445],"iteration":965,"passed_time":4.761019153,"remaining_time":0.1675721027},
{"learn":[0.3075216885],"iteration":966,"passed_time":4.764031561,"remaining_time":0.1625781195},
{"learn":[0.3074696589],"iteration":967,"passed_time":4.766991868,"remaining_time":0.157586508},
{"learn":[0.3073625936],"iteration":968,"passed_time":4.770165201,"remaining_time":0.1526059043},
{"learn":[0.3073130974],"iteration":969,"passed_time":4.773207828,"remaining_time":0.1476249844},
{"learn":[0.3072812302],"iteration":970,"passed_time":4.776224466,"remaining_time":0.1426472807},
{"learn":[0.3072142946],"iteration":971,"passed_time":4.779281676,"remaining_time":0.1376747808},
{"learn":[0.3071064428],"iteration":972,"passed_time":4.782309661,"remaining_time":0.1327054068},
{"learn":[0.3070305776],"iteration":973,"passed_time":4.78544623,"remaining_time":0.1277429179},
{"learn":[0.3069672902],"iteration":974,"passed_time":4.789687278,"remaining_time":0.1228124943},
{"learn":[0.3068553731],"iteration":975,"passed_time":4.793376373,"remaining_time":0.1178699108},
{"learn":[0.3068101339],"iteration":976,"passed_time":4.798114295,"remaining_time":0.1129545842},
{"learn":[0.3066415617],"iteration":977,"passed_time":4.801170644,"remaining_time":0.1080017936},
{"learn":[0.3065366113],"iteration":978,"passed_time":4.804459024,"remaining_time":0.1030578544},
{"learn":[0.3064153128],"iteration":979,"passed_time":4.807339951,"remaining_time":0.0981089786},
{"learn":[0.3063152651],"iteration":980,"passed_time":4.810666431,"remaining_time":0.09317294821},
{"learn":[0.3062753218],"iteration":981,"passed_time":4.813773533,"remaining_time":0.08823617473},
{"learn":[0.3061749912],"iteration":982,"passed_time":4.81671602,"remaining_time":0.08330027705},
{"learn":[0.3061340938],"iteration":983,"passed_time":4.81977286,"remaining_time":0.07837029041},
{"learn":[0.3060678515],"iteration":984,"passed_time":4.822994539,"remaining_time":0.07344661735},
{"learn":[0.3059044978],"iteration":985,"passed_time":4.825921836,"remaining_time":0.06852221674},
{"learn":[0.3058177878],"iteration":986,"passed_time":4.829054066,"remaining_time":0.06360456217},
{"learn":[0.3056703598],"iteration":987,"passed_time":4.8323391,"remaining_time":0.05869237774},
{"learn":[0.3055227898],"iteration":988,"passed_time":4.835436591,"remaining_time":0.05378139787},
{"learn":[0.3054282067],"iteration":989,"passed_time":4.838437267,"remaining_time":0.0488731037},
{"learn":[0.3053598389],"iteration":990,"passed_time":4.841336191,"remaining_time":0.04396773533},
{"learn":[0.3052943435],"iteration":991,"passed_time":4.844427585,"remaining_time":0.03906796439},
{"learn":[0.3052094808],"iteration":992,"passed_time":4.847521694,"remaining_time":0.03417185484},
{"learn":[0.3050458743],"iteration":993,"passed_time":4.850917072,"remaining_time":0.02928118957},
{"learn":[0.304898107],"iteration":994,"passed_time":4.853837255,"remaining_time":0.02439114198},
{"learn":[0.3047807886],"iteration":995,"passed_time":4.858389841,"remaining_time":0.01951160579},
{"learn":[0.3047268727],"iteration":996,"passed_time":4.861615731,"remaining_time":0.01462873339},
{"learn":[0.304647605],"iteration":997,"passed_time":4.864839021,"remaining_time":0.009749176396},
{"learn":[0.3045988322],"iteration":998,"passed_time":4.868000903,"remaining_time":0.004872873777},
{"learn":[0.3045464132],"iteration":999,"passed_time":4.871298876,"remaining_time":0}
]}3309766},
{"learn":[0.3008700526],"iteration":998,"passed_time":3.51321746,"remaining_time":0.003516734194},
{"learn":[0.3007986877],"iteration":999,"passed_time":3.517339205,"remaining_time":0}
]}